Workbook

Sheet Clientes Novos
B1: Nome | C1: Conta | D1: Escritório | E1: UF | F1: Assessor | G1: APP | H1: Observações | I1: Carteira | J1: TX. de Gestão | K1: Benchmark | L1: TX. Perf. | M1: CPF/CNPJ | N1: Telefone | O1: E-mail | P1: Aniversário | Q1: UF cliente | R1: Suitability | S1: Observações
A2: BTG | B2: Franklin Silva de Novais | C2: 004826721 | D2: Investeseg | E2: BA | F2: Murilo Silva | G2: PIPE | H2: Aguardando FA | I2: CON | J2: 0.012 | K2: CDI | L2: 0.1 | M2: 017.737.005-02 | N2: 71 99907-7741 | O2: franknovais@hotmail.com | P2: 31599 | Q2: BA | R2: Moderado | S2: TEM OBS
A3: BTG | B3: Andre Albuquerque Villas | C3: 003537823 | D3: Expert | E3: GO | F3: Felipe Ouriveis | G3: PIPE | H3: Aguardando Vinculação de conta | I3: INC | J3: 0.012 | K3: ------ | L3: 0 | M3: 761.414.111-34 | N3: 67 99982-4900 | O3: aavillas75@gmail.com | P3: 27556 | Q3: MS | R3: Moderado | S3: Manter 30% em liquidez, por enquanto.
A4: BTG | B4: Ana Paula Herrero | C4: 008475532 | D4: Miura | E4: SUL | F4: Victor | G4: PIPE | H4: Aguardando Cobrança de Taxas | I4: INC | J4: 0.012 | K4: ------ | L4: 0 | N4: (43) 99922-6163 | O4: anapaula_herrero@hotmail.com | R4: Conservador
A5: Pershing | B5: Rubens Dias da Costa Neto Souza | C5: xxxxxxx | D5: Bluemetrix | E5: GO | F5: Felipe Rios | G5: PIPE | H5: Em Análise pela Corretora | I5: INT | J5: 0.016 | K5: ------ | L5: 0 | M5: 755.745.001-91 | N5: 62 99845-8856 | O5: rubensdnetos@gmail.com | P5: 36178 | Q5: GO | R5: Arrojado
A6: BTG | B6: Cardiointerv S/S | C6: xxxxxxx | D6: VcInvest | E6: GO | F6: Bruno | G6: PIPE | H6: Em Análise pela Corretora | I6: INC | J6: 0.012 | K6: ------ | L6: 0 | M6: 13.552.357/0001-24 | N6: 62 98115-0222 | O6: afreitasjr@msn.com | P6: 40653 | Q6: GO | R6: Moderado | S6: Desistiu
A7: BTG | B7: ARGIO SERVICOS LTDA | C7: xxxxxxx | D7: Bluemetrix | E7: GO | F7: felipe | G7: PIPE | H7: Em Análise pela Corretora | I7: INC | J7: 0.012 | K7: ------ | L7: 0 | M7: 54.744.253/0001-07 | N7: 62 98285-8250 | O7: Argioservicos@gmail.com | P7: 45398 | Q7: GO | R7: Conservador
A8: BTG | B8: Aline Kanyo De Queiroz e/ou Rafael Crispim Gonçalves | C8: xxxxxxx | D8: Bluemetrix | E8: DF | F8: Thiago | G8: PIPE | H8: Em Análise pela Corretora | I8: MONT | J8: 0 | K8: ------ | L8: 0 | M8: 001.773.141-09 | N8: 61999777420 | O8: alinekanyo@gmail.com | P8: 31275 | Q8: DF | R8: Conservador
A9: Ágora | B9: Ricardo Roberto Arquitetura LTDA | C9: xxxxxxx | D9: MI Smart | E9: DF | F9: Mariana | G9: PIPE | H9: Em Análise pela Corretora | I9: CORP | J9: 0.01 | K9: ------ | L9: 0 | M9: 29.450.428/0001-18 | N9: 61 99413-7963 | O9: ricardo.roberto.df@gmail.com | P9: 43116 | Q9: DF | R9: Conservador | S9: Deixar tudo em liquidez
A10: XP | B10: Adriana Carneiro Macedo | C10: 19831186 | D10: Investeseg | E10: BA | F10: Murilo Silva | G10: PIPE | H10: Pendente de Aceite do Termo | I10: INC | J10: 0.012 | K10: ------ | L10: 0 | M10: 940.673.765-53 | N10: 11 99732-6602 | O10: adrimacedo@hotmail.com | P10: 28251 | Q10: BA | R10: Moderado
A11: Interactive Brokers | B11: Wellington Coelho de Souza Junior | C11: xxxxxxx | D11: Expert | E11: GO | F11: Felipe Ouriveis | G11: PIPE | H11: Pendente assinaturas | I11: INT | J11: 0.0115 | K11: ------ | L11: 0 | M11: 730.614.501-06 | N11: 67 99256-9156 | O11: wellingtoncsjr@hotmail.com | P11: 31473 | Q11: MS | R11: Moderado
A12: BTG | B12: Daniel Francisco dos Santos e Silva | C12: 005275706 | D12: Expert | E12: GO | F12: Felipe Ouriveis | G12: PIPE | H12: Pendente assinaturas | I12: CON | J12: 0.012 | K12: ------ | L12: 0 | M12: 904.565.561-68 | N12: 61 98250-8228 | O12: danisilv@gmail.com | P12: 29409 | Q12: DF | R12: Moderado
A13: BTG | B13: Fabiano Cury Rodrigues | C13: xxxxxxx | D13: VcInvest | E13: GO | F13: Bruno | G13: PIPE | H13: Pendente assinaturas | I13: INC | J13: 0.012 | K13: ------ | L13: 0 | M13: 877.730.071-87 | N13: 62 99219-7777 | O13: fabianocr@gmail.com | P13: 28669 | Q13: GO | R13: Moderado | S13: 20 a 30% de liquidez mais rápida, prazo máximo de 2 anos em ativos da carteira
A14: BTG | B14: Leandro Augusto De Araujo Cunha T Bueno e/ou Naiara Cunha Teixeira Bueno | C14: xxxxxxx | D14: Bluemetrix | E14: DF | F14: Thiago | G14: PIPE | H14: Pendente assinaturas | I14: INC | J14: 0.0085 | K14: ------ | L14: 0 | M14: 342.258.488 92 | S14: Vencido
A15: BTG | B15: Marcos Roberto Grimm | C15: 004109781 | D15: Expert | E15: GO | F15: Felipe Ouriveis | G15: PIPE | H15: Pendente assinaturas | I15: INC | J15: 0.012 | K15: ------ | L15: 0 | M15: 404.497.001-78 | N15: 67 99901-9497 | O15: marcosgrimm.mg@gmail.com | P15: 24369 | Q15: MS | S15: Manter 50% da carteira em liquidez D0 ou D+1, por enquanto e trabalhar com ativos mais curtos.
A16: BTG | B16: Sergio Alberto Ramos e/ou Elisa Kioko Matsumoto Ramos | C16: xxxxxxx | D16: Expert | E16: GO | F16: Felipe Ouriveis | G16: PIPE | H16: Pendente assinaturas | I16: INC | J16: 0.012 | K16: ------ | L16: 0 | M16: 056.674.278-00 | N16: 67 98425-2820 | O16: sar.ramos@hotmail.com | P16: 23566 | Q16: MS | R16: Conservador
A17: XP | B17: Ethel Ferreira Poll | C17: xxxxxxx | D17: Investeseg | E17: BA | F17: Carol | G17: PIPE | H17: Pendente assinaturas | I17: INC | J17: 0.012 | K17: ------ | L17: 0 | M17: 585.217.470-04 | N17: 71 99965-3709 | O17: ethelpoll@hotmail.com | P17: 26036 | Q17: BA | R17: Moderado
A18: BTG | B18: OLIVEIRA COMERCIO DO VESTUARIO LTDA | C18: xxxxxxx | D18: Bluemetrix | E18: GO | F18: Fabricio | G18: PIPE | H18: Pendente assinaturas | I18: INC | J18: 0.012 | K18: ------ | L18: 0 | M18: 27.265.200/0001-22 | N18: 62 98244-9400 | O18: dellufitness@gmail.com | P18: 42803 | Q18: GO | R18: Moderado

Sheet BTG
A1: Backoffice | G1: Mesa de Operação | H1: Backoffice/ Mesa | J1: Backoffice | Q1: Mesa de Operação | R1: Backoffice | S1: Anbima | AF1: Financeiro | AG1: Financeiro | AH1: Financeiro | AI1: Financeiro | AJ1: Financeiro | AK1: Financeiro | AL1: Financeiro | AM1: Financeiro | AN1: Financeiro | AO1: Financeiro | AP1: Financeiro | AQ1: Financeiro | AR1: Financeiro | AS1: Financeiro | AT1: Financeiro | AU1: Financeiro | AV1: Financeiro | AW1: Financeiro | AX1: Financeiro | AY1: Financeiro | AZ1: Financeiro | BA1: Financeiro | BB1: Financeiro | BC1: Financeiro | BD1: Financeiro | BE1: Financeiro | BF1: Financeiro | BG1: Financeiro | BH1: Financeiro | BI1: Financeiro | BJ1: Financeiro | BK1: Financeiro | BL1: Financeiro | BM1: Financeiro | BN1: Financeiro | BO1: Financeiro | BP1: Financeiro | BQ1: Financeiro | BR1: Financeiro | BS1: Financeiro | BT1: Financeiro | BU1: Financeiro | BV1: Financeiro | BW1: Financeiro | BX1: Financeiro | BY1: Financeiro
A2: Corretora | B2: Cliente | C2: Conta | D2: Escritório | E2: UF | F2: Assessor | G2: Operador | H2: Status | I2: Situação | J2: Exceção | K2: Início da Gestão | L2: Data distrato | M2: Carteira | N2: Taxa de Gestão | O2: Benchmark TX. Perf. | P2: TX. Perf. | Q2: Observações | R2: Observações Backoffice | S2: PF/ PJ | T2: CPF/CNPJ | U2: Telefone | V2: E-mail | W2: Aniversário | X2: UF cliente | Y2: Status Anbima | Z2: Perfil de risco da carteira | AA2: Perfil de risco do investidor | AB2: Classificação do Investidor | AC2: Grupo Econômico (Região) | AD2: Data Primeiro Aporte | AE2: Código Anbima | AF2: 31/10/2022 | AG2: 30/11/2022 | AH2: 30/12/2022 | AI2: 31/01/2023 | AJ2: 28/02/2023 | AK2: 31/03/2023 | AL2: 28/04/2023 | AM2: 31/05/2023 | AN2: 30/06/2023 | AO2: 31/07/2023 | AP2: 31/08/2023 | AQ2: 29/09/2023 | AR2: 31/10/2023 | AS2: 30/11/2023 | AT2: 29/12/2023 | AU2: 31/01/2024 | AV2: 29/02/2024 | AW2: 28/03/2024 | AX2: 30/04/2024 | AY2: 31/05/2024 | AZ2: 28/06/2024 | BA2: 31/07/2024 | BB2: 30/08/2024 | BC2: 30/09/2024 | BD2: 31/10/2024 | BE2: 29/11/2024 | BF2: 31/12/2024 | BG2: 31/01/2025 | BH2: 28/02/2025 | BI2: 31/03/2025 | BJ2: 30/04/2025 | BK2: 30/05/2025 | BL2: 30/06/2025 | BM2: 31/07/2025 | BN2: 31/08/2025 | BO2: 30/09/2025 | BP2: 31/10/2025 | BQ2: 30/11/2025 | BR2: 31/12/2025 | BS2: 31/01/2026 | BT2: 28/02/2026 | BU2: 31/03/2026 | BV2: 30/04/2026 | BW2: 31/05/2026 | BX2: 30/06/2026 | BY2: Julho (D-1)
A3: BTG | B3: Adao Baum Penha | C3: 026476960 | D3: Miura | E3: SUL | F3: Lucas Zambrin | G3: =IFS($BS$4:$BS$1280<=250000,"David",$BS$4:$BS$1280<=800000,"Gabriel", $BS$4:$BS$1280>800000,"Marcus") -> #VALUE! | H3: Ativo | I3: ------ | J3: =IF(Q3=0,"Não","Sim") -> Não | K3: 46217 | M3: MOD | N3: 0.015 | O3: CDI | P3: 0.1 | S3: PF | T3: 086.751.079-00 | U3: 43 99962-0426 | V3: adaobaum@gmail.com | W3: 33735 | X3: PR | Y3: =IFS(H:H="Encerrado","Encerrado",COUNTBLANK(AZ3:BK3)>0,"Ativo",SUM(AZ3:BK3)=0,"Inativo",SUM(AZ3:BK3)>0,"Ativo") -> Ativo | AA3: Moderado | BX3: 0 | BY3: {=XLOOKUP(C3,'PL TOTAL D0'!$A$3:$A$1991,'PL TOTAL D0'!$C$3:$C$1991,"")} -> 1151901.7
A4: BTG | B4: Adele Rossi Heusi | C4: 004575632 | D4: Voga | E4: DF | F4: Theo Ramos Moutinho | G4: =IFS($BS$4:$BS$1280<=250000,"David",$BS$4:$BS$1280<=800000,"Gabriel", $BS$4:$BS$1280>800000,"Marcus") -> David | H4: Encerrado | I4: ------ | J4: =IF(Q4=0,"Não","Sim") -> Não | K4: 45105 | L4: 45552 | M4: CON | N4: 0.012 | O4: CDI | P4: 0.1 | R4: Cliente solicitou troca de assessoria (08/08/2024) | S4: PF | T4: 334.053.601-53 | X4: DF | Y4: =IFS(H:H="Encerrado","Encerrado",COUNTBLANK(AZ4:BK4)>0,"Ativo",SUM(AZ4:BK4)=0,"Inativo",SUM(AZ4:BK4)>0,"Ativo") -> Encerrado | AB4: Qualificado | AD4: 45105 | AE4: 49075100007179 | AN4: 11645.25 | AO4: 101705.9 | AP4: 87680.81 | AQ4: 97773.76 | AR4: 94701.07 | AS4: 97855.43 | AT4: 93543.64 | AU4: 346111.38 | AV4: 469765.42 | AW4: 504924.71 | AX4: 496452.34 | AY4: 471980.3 | AZ4: 412836.6 | BA4: 399202.4 | BB4: 0 | BC4: 0 | BD4: 0 | BE4: 0 | BF4: 0 | BG4: 0 | BH4: 0 | BI4: 0 | BJ4: 0 | BK4: 0 | BL4: 0 | BM4: 0 | BN4: 0 | BO4: 0 | BP4: 0 | BQ4: 0 | BR4: 0 | BS4: 0 | BT4: 0 | BU4: 0 | BW4: 0 | BX4: 0 | BY4: {=XLOOKUP(C4,'PL TOTAL D0'!$A$3:$A$1991,'PL TOTAL D0'!$C$3:$C$1991,"")}
A5: BTG | B5: Adriana Amorin Monteiro | C5: 002471066 | D5: Poupinvista | E5: DF | F5: Bruno Rodrigues | G5: =IFS($BS$4:$BS$1280<=250000,"David",$BS$4:$BS$1280<=800000,"Gabriel", $BS$4:$BS$1280>800000,"Marcus") -> Gabriel | H5: Ativo | I5: ------ | J5: =IF(Q5=0,"Não","Sim") -> Não | K5: 45923 | M5: INC | N5: 0.012 | O5: ------ | P5: 0 | S5: PF | T5: 622.372.763-15 | U5: 81 98900-0164 | V5: drikas.amorim@gmail.com | W5: 28556 | X5: PE | Y5: =IFS(H:H="Encerrado","Encerrado",COUNTBLANK(AZ5:BK5)>0,"Ativo",SUM(AZ5:BK5)=0,"Inativo",SUM(AZ5:BK5)>0,"Ativo") -> Ativo | AA5: Moderado | AD5: 45923 | AE5: 49075100019428 | BO5: 391712.81 | BP5: 403957.9 | BQ5: 406166.3 | BR5: 548723.1 | BS5: 550961.42 | BT5: 536101.1 | BU5: 494037.2 | BV5: 490251.4 | BW5: 472634.2 | BX5: 478704.69 | BY5: {=XLOOKUP(C5,'PL TOTAL D0'!$A$3:$A$1991,'PL TOTAL D0'!$C$3:$C$1991,"")} -> 504296.39
A6: BTG | B6: Adriana Dos Santos Alcantara | C6: 026362731 | D6: Bluemetrix | E6: DF | F6: Thiago Canabrava | G6: =IFS($BS$4:$BS$1280<=250000,"David",$BS$4:$BS$1280<=800000,"Gabriel", $BS$4:$BS$1280>800000,"Marcus") -> David | H6: Ativo | I6: ------ | J6: =IF(Q6=0,"Não","Sim") -> Não | K6: 46216 | M6: INC | N6: 0.012 | O6: ------ | P6: 0 | S6: PF | T6: 540.112.301-97 | U6: 61 98116-7402 | V6: Adriana.Alcantara2020@outlook.com | W6: 24/11/0170 | X6: DF | Y6: =IFS(H:H="Encerrado","Encerrado",COUNTBLANK(AZ6:BK6)>0,"Ativo",SUM(AZ6:BK6)=0,"Inativo",SUM(AZ6:BK6)>0,"Ativo") -> Ativo | AA6: Moderado | BX6: 0 | BY6: {=XLOOKUP(C6,'PL TOTAL D0'!$A$3:$A$1991,'PL TOTAL D0'!$C$3:$C$1991,"")} -> 30201.01
A7: BTG | B7: Adriana Dos Santos Alcantara | C7: 036660678 | D7: Bluemetrix | E7: DF | F7: Thiago Canabrava | G7: =IFS($BS$4:$BS$1280<=250000,"David",$BS$4:$BS$1280<=800000,"Gabriel", $BS$4:$BS$1280>800000,"Marcus") -> David | H7: Pode Operar | I7: ------ | J7: =IF(Q7=0,"Não","Sim") -> Não | K7: 46234 | M7: INC | N7: 0.012 | O7: ------ | P7: 0 | S7: PF | T7: 540.112.301-97 | U7: 61 98116-7402 | V7: Adriana.Alcantara2020@outlook.com | W7: 24/11/0170 | X7: DF | Y7: =IFS(H:H="Encerrado","Encerrado",COUNTBLANK(AZ7:BK7)>0,"Ativo",SUM(AZ7:BK7)=0,"Inativo",SUM(AZ7:BK7)>0,"Ativo") -> Ativo | AA7: Moderado
A8: BTG | B8: Adriana Garcia Rosa | C8: 005715733 | D8: Bluemetrix | E8: GO | F8: Vivian | G8: =IFS($BS$4:$BS$1280<=250000,"David",$BS$4:$BS$1280<=800000,"Gabriel", $BS$4:$BS$1280>800000,"Marcus") -> David | H8: Encerrado | I8: ------ | J8: =IF(Q8=0,"Não","Sim") -> Não | K8: 45575 | L8: 45873 | M8: INC | N8: 0.012 | O8: ------ | P8: 0 | R8: Distrato Unilateral | S8: PF | T8: 778.127.601-97 | X8: GO | Y8: =IFS(H:H="Encerrado","Encerrado",COUNTBLANK(AZ8:BK8)>0,"Ativo",SUM(AZ8:BK8)=0,"Inativo",SUM(AZ8:BK8)>0,"Ativo") -> Encerrado | AA8: Conservador | AD8: 45575 | AE8: 49075100015937 | BD8: 25129.32 | BE8: 28365.69 | BF8: 42735.29 | BG8: 43359.18 | BH8: 43783.43 | BI8: 46235.25 | BJ8: 43169.62 | BK8: 47521.44 | BL8: 0 | BM8: 0 | BN8: 0 | BO8: 0 | BP8: 0 | BQ8: 0 | BR8: 0 | BS8: 0 | BT8: 0 | BU8: 0 | BV8: 0 | BW8: 0 | BX8: 0 | BY8: {=XLOOKUP(C8,'PL TOTAL D0'!$A$3:$A$1991,'PL TOTAL D0'!$C$3:$C$1991,"")}
A9: BTG | B9: Adriana Sobral Lourenco | C9: 004240400 | D9: Altum | E9: DF | F9: Alexandre Xavier | G9: =IFS($BS$4:$BS$1280<=250000,"David",$BS$4:$BS$1280<=800000,"Gabriel", $BS$4:$BS$1280>800000,"Marcus") -> David | H9: Ativo | I9: ------ | J9: =IF(Q9=0,"Não","Sim") -> Não | K9: 45448 | M9: CON | N9: 0.012 | O9: CDI | P9: 0.1 | S9: PF | T9: 607.674.302-63 | U9: 5561981347034 | V9: drisobrallourenco@gmail.com | W9: 27638 | X9: DF | Y9: =IFS(H:H="Encerrado","Encerrado",COUNTBLANK(AZ9:BK9)>0,"Ativo",SUM(AZ9:BK9)=0,"Inativo",SUM(AZ9:BK9)>0,"Ativo") -> Ativo | AA9: Moderado | AB9: Qualificado | AD9: 45448 | AE9: 49075100015023 | AZ9: 121700.5 | BA9: 123070.4 | BB9: 123754.77 | BC9: 127558.92 | BD9: 143233.67 | BE9: 142815.33 | BF9: 153533.2 | BG9: 164010.93 | BH9: 168227.15 | BI9: 202632.33 | BJ9: 206574.72 | BK9: 178281.56 | BL9: 182801.31 | BM9: 185347.86 | BN9: 189197.2 | BO9: 193123.36 | BP9: 204372.5 | BQ9: 206026.5 | BR9: 211050.1 | BS9: 213379.81 | BT9: 215053.2 | BU9: 217325.5 | BV9: 219246.2 | BW9: 219899.3 | BX9: 220858.3 | BY9: {=XLOOKUP(C9,'PL TOTAL D0'!$A$3:$A$1991,'PL TOTAL D0'!$C$3:$C$1991,"")} -> 216111.18
A10: BTG | B10: Adriano Antônio Alves | C10: 004451996 | D10: Bluemetrix | E10: GO | F10: Vivian | G10: =IFS($BS$4:$BS$1280<=250000,"David",$BS$4:$BS$1280<=800000,"Gabriel", $BS$4:$BS$1280>800000,"Marcus") -> David | H10: Inativo | I10: Sem Saldo | J10: =IF(Q10=0,"Não","Sim") -> Não | K10: 45036 | M10: INC | N10: 0.012 | O10: ------ | P10: 0 | S10: PF | T10: 548.976.961-00 | U10: 62984152005 | V10: adriano@orais.com.br | W10: 26149 | X10: GO | Y10: =IFS(H:H="Encerrado","Encerrado",COUNTBLANK(AZ10:BK10)>0,"Ativo",SUM(AZ10:BK10)=0,"Inativo",SUM(AZ10:BK10)>0,"Ativo") -> Ativo | AB10: Qualificado | AD10: 45036 | AE10: 49075100008310 | AK10: 0 | AL10: 10017.88 | AM10: 10121.37 | AN10: 10216.79 | AO10: 10266.22 | AP10: 10256.52 | AQ10: 10245.37 | AR10: 10303.3 | AS10: 10380.65 | AT10: 10461.92 | AU10: 10552.25 | AV10: 10641.25 | AW10: 10727.74 | AX10: 10819.52 | AY10: 10903.41 | AZ10: 0 | BA10: 0 | BB10: 0.09 | BC10: 0.09 | BD10: 0.09 | BE10: 0.09 | BF10: 0.09 | BG10: 0.09 | BH10: 0.09 | BI10: 0.09 | BJ10: 0 | BK10: 0 | BL10: 0 | BM10: 0 | BN10: 0 | BO10: 0 | BP10: 0 | BQ10: 0 | BR10: 0 | BS10: 0 | BT10: 0 | BU10: 0 | BV10: 0 | BW10: 0 | BX10: 0 | BY10: {=XLOOKUP(C10,'PL TOTAL D0'!$A$3:$A$1991,'PL TOTAL D0'!$C$3:$C$1991,"")}
A11: BTG | B11: Adriano Carvalho Costa | C11: 003916735 | D11: Bluemetrix | E11: GO | F11: Felipe Rios | G11: =IFS($BS$4:$BS$1280<=250000,"David",$BS$4:$BS$1280<=800000,"Gabriel", $BS$4:$BS$1280>800000,"Marcus") -> David | H11: Inativo | I11: Sem Saldo | J11: =IF(Q11=0,"Não","Sim") -> Não | K11: 45474 | M11: INC | N11: 0.012 | O11: ------ | P11: 0 | S11: PF | T11: 006.352.131-84 | U11: 5562999714102 | V11: didasgyn@gmail.com | W11: 31314 | X11: GO | Y11: =IFS(H:H="Encerrado","Encerrado",COUNTBLANK(AZ11:BK11)>0,"Ativo",SUM(AZ11:BK11)=0,"Inativo",SUM(AZ11:BK11)>0,"Ativo") -> Ativo | AA11: Arrojado | AB11: Qualificado | AD11: 45474 | AE11: 49075100015503 | BA11: 0 | BB11: 0 | BC11: 0 | BD11: 0 | BE11: 0 | BF11: 0 | BG11: 0 | BH11: 0 | BI11: 0 | BJ11: 0 | BK11: 0 | BL11: 0 | BM11: 0 | BN11: 0 | BO11: 0 | BP11: 0 | BQ11: 0 | BR11: 0 | BS11: 0 | BT11: 0 | BU11: 0 | BV11: 0 | BW11: 0 | BX11: 0 | BY11: {=XLOOKUP(C11,'PL TOTAL D0'!$A$3:$A$1991,'PL TOTAL D0'!$C$3:$C$1991,"")}
A12: BTG | B12: Adriano de Moraes Arantes | C12: 003039255 | D12: VcInvest | E12: GO | F12: Bruno Ribeiro | G12: =IFS($BS$4:$BS$1280<=250000,"David",$BS$4:$BS$1280<=800000,"Gabriel", $BS$4:$BS$1280>800000,"Marcus") -> David | H12: Ativo | I12: ------ | J12: =IF(Q12=0,"Não","Sim") -> Não | K12: 46174 | M12: INC | N12: 0.012 | O12: ------ | P12: 0 | S12: PF | T12: 784.374.231-04 | U12: 62 99980-8750 | V12: arantesadriano@hotmail.com | W12: 27757 | X12: GO | Y12: =IFS(H:H="Encerrado","Encerrado",COUNTBLANK(AZ12:BK12)>0,"Ativo",SUM(AZ12:BK12)=0,"Inativo",SUM(AZ12:BK12)>0,"Ativo") -> Ativo | AA12: Moderado | AD12: 46203 | BX12: 199096.49 | BY12: {=XLOOKUP(C12,'PL TOTAL D0'!$A$3:$A$1991,'PL TOTAL D0'!$C$3:$C$1991,"")} -> 251715.28
A13: BTG | B13: Adriano Marcio de Oliveira Flausino Filho | C13: 004231371 | D13: Bluemetrix | E13: DF | F13: Bruno Henrique | G13: =IFS($BS$4:$BS$1280<=250000,"David",$BS$4:$BS$1280<=800000,"Gabriel", $BS$4:$BS$1280>800000,"Marcus") -> David | H13: Ativo | I13: ------ | J13: =IF(Q13=0,"Não","Sim") -> Não | K13: 45309 | M13: FUND | N13: 0 | O13: ------ | P13: 0 | S13: PF | T13: 009.594.841-40 | U13: 5561981389093 | V13: amoffilho@gmail.com | W13: 34824 | X13: DF | Y13: =IFS(H:H="Encerrado","Encerrado",COUNTBLANK(AZ13:BK13)>0,"Ativo",SUM(AZ13:BK13)=0,"Inativo",SUM(AZ13:BK13)>0,"Ativo") -> Ativo | AB13: Qualificado | AD13: 45309 | AE13: 49075100013111 | AU13: 1001.72 | AV13: 4019.27 | AW13: 1001.59 | AX13: 2014.05 | AY13: 2604.93 | AZ13: 3315.03 | BA13: 3698.13 | BB13: 4081.22 | BC13: 4615.4 | BD13: 5031.39 | BE13: 5380.13 | BF13: 6021.15 | BG13: 6818.24 | BH13: 7518.39 | BI13: 8204.11 | BJ13: 0 | BK13: 0.29 | BL13: 0.29 | BM13: 0.29 | BN13: 0.29 | BO13: 2015.63 | BP13: 0 | BQ13: 6500 | BR13: 5062.04 | BS13: 5041 | BT13: 2059.92 | BU13: 4595.68 | BV13: 4645.22 | BW13: 1821.17 | BX13: 1835.28 | BY13: {=XLOOKUP(C13,'PL TOTAL D0'!$A$3:$A$1991,'PL TOTAL D0'!$C$3:$C$1991,"")}
A14: BTG | B14: Adson Rodrigues de Souza | C14: 004404342 | D14: Bluemetrix | E14: GO | F14: Vivian | G14: =IFS($BS$4:$BS$1280<=250000,"David",$BS$4:$BS$1280<=800000,"Gabriel", $BS$4:$BS$1280>800000,"Marcus") -> David | H14: Encerrado | I14: ------ | J14: =IF(Q14=0,"Não","Sim") -> Não | K14: 44974 | L14: 45940 | M14: INC | N14: 0.012 | O14: ------ | P14: 0 | S14: PF | T14: 375.046.571-15 | X14: GO | Y14: =IFS(H:H="Encerrado","Encerrado",COUNTBLANK(AZ14:BK14)>0,"Ativo",SUM(AZ14:BK14)=0,"Inativo",SUM(AZ14:BK14)>0,"Ativo") -> Encerrado | AB14: Qualificado | AD14: 44974 | AE14: 49075100003300 | AJ14: 0 | AK14: 831494.82 | AL14: 839282.3 | AM14: 850795.67 | AN14: 861974.11 | AO14: 862874.84 | AP14: 838055.38 | AQ14: 839394.89 | AR14: 844581.11 | AS14: 855717.31 | AT14: 867240.53 | AU14: 875442.71 | AV14: 883735.44 | AW14: 889186.44 | AX14: 891932.67 | AY14: 900933.7 | AZ14: 902936.8 | BA14: 910147.4 | BB14: 929204.87 | BC14: 935280.85 | BD14: 943521.07 | BE14: 951328.95 | BF14: 958000.56 | BG14: 966488.7 | BH14: 972248.01 | BI14: 977734.4 | BJ14: 985579.28 | BK14: 997622.25 | BL14: 1006792.4 | BM14: 0 | BN14: 0 | BO14: 0 | BP14: 0 | BQ14: 0 | BR14: 0 | BS14: 0 | BT14: 0 | BU14: 0 | BV14: 0 | BW14: 0 | BX14: 0 | BY14: {=XLOOKUP(C14,'PL TOTAL D0'!$A$3:$A$1991,'PL TOTAL D0'!$C$3:$C$1991,"")}
A15: BTG | B15: Aécio Araújo Barros | C15: 016322281 | D15: Poupinvista | E15: DF | F15: Bruno Rodrigues | G15: =IFS($BS$4:$BS$1280<=250000,"David",$BS$4:$BS$1280<=800000,"Gabriel", $BS$4:$BS$1280>800000,"Marcus") -> Gabriel | H15: Ativo | I15: ------ | J15: =IF(Q15=0,"Não","Sim") -> Não | K15: 45957 | M15: INC | N15: 0.012 | O15: ------ | P15: 0 | S15: PF | T15: 006.320.061-96 | U15: 61 98542-0349 | V15: aeciohsf@gmail.com | W15: 31347 | X15: DF | Y15: Ativo | AA15: Moderado | AD15: 45972 | AE15: 49075100019746 | BP15: 0 | BQ15: 452427.4 | BR15: 650471.9 | BS15: 677600.62 | BT15: 689496.6 | BU15: 697605.9 | BV15: 708323.7 | BW15: 718819.2 | BX15: 728945.98 | BY15: {=XLOOKUP(C15,'PL TOTAL D0'!$A$3:$A$1991,'PL TOTAL D0'!$C$3:$C$1991,"")} -> 738397.44
A16: BTG | B16: Aguinaldo Figueiredo de Freitas Junior | C16: 005645211 | D16: VcInvest | E16: GO | F16: Bruno Ribeiro | G16: =IFS($BS$4:$BS$1280<=250000,"David",$BS$4:$BS$1280<=800000,"Gabriel", $BS$4:$BS$1280>800000,"Marcus") -> Marcus | H16: Ativo | I16: ------ | J16: =IF(Q16=0,"Não","Sim") -> Não | K16: 45450 | M16: INC | N16: 0.012 | O16: ------ | P16: 0 | S16: PF | T16: 817.848.051-49 | U16: 62981150222 | V16: afreitasjr@msn.com | W16: 28348 | X16: GO | Y16: =IFS(H:H="Encerrado","Encerrado",COUNTBLANK(AZ16:BK16)>0,"Ativo",SUM(AZ16:BK16)=0,"Inativo",SUM(AZ16:BK16)>0,"Ativo") -> Ativo | AA16: Arrojado | AB16: Qualificado | AD16: 45450 | AE16: 49075100015090 | AZ16: 778994.8 | BA16: 1000481 | BB16: 1009940.4 | BC16: 1015213.2 | BD16: 1024360 | BE16: 1032672.2 | BF16: 1041614.6 | BG16: 1252480.7 | BH16: 1264087.8 | BI16: 1277280.9 | BJ16: 1392309.6 | BK16: 1758966.9 | BL16: 1773460.9 | BM16: 1892288.7 | BN16: 2007259 | BO16: 2126336.3 | BP16: 2352474 | BQ16: 2573545 | BR16: 2786134 | BS16: 2814450.8 | BT16: 2861943 | BU16: 3082585 | BV16: 3115363 | BW16: 3146930 | BX16: 3256988.5 | BY16: {=XLOOKUP(C16,'PL TOTAL D0'!$A$3:$A$1991,'PL TOTAL D0'!$C$3:$C$1991,"")} -> 3334568.9
A17: BTG | B17: Aguinaldo Figueiredo de Freitas Junior | C17: 005662526 | D17: VcInvest | E17: GO | F17: Bruno Ribeiro | G17: =IFS($BS$4:$BS$1280<=250000,"David",$BS$4:$BS$1280<=800000,"Gabriel", $BS$4:$BS$1280>800000,"Marcus") -> David | H17: Inativo | I17: Sem Saldo | J17: =IF(Q17=0,"Não","Sim") -> Não | K17: 45450 | M17: EQT/ COADM | N17: 0.025 | O17: IBOVESPA | P17: 0.2 | S17: PF | T17: 817.848.051-49 | U17: 62981150222 | V17: afreitasjr@msn.com | W17: 28348 | X17: GO | Y17: =IFS(H:H="Encerrado","Encerrado",COUNTBLANK(AZ17:BK17)>0,"Ativo",SUM(AZ17:BK17)=0,"Inativo",SUM(AZ17:BK17)>0,"Ativo") -> Ativo | AA17: Arrojado | AB17: Qualificado | AD17: 45450 | AE17: 49075100015104 | AZ17: 104571.6 | BA17: 87237.69 | BB17: 91041.85 | BC17: 85312.49 | BD17: 88737.71 | BE17: 0 | BF17: 0.44 | BG17: 0.44 | BH17: 0.44 | BI17: 0.44 | BJ17: 0 | BK17: 0 | BL17: 0 | BM17: 0 | BN17: 0 | BO17: 0 | BP17: 0 | BQ17: 0 | BR17: 0 | BS17: 0 | BT17: 0 | BU17: 0 | BV17: 0 | BW17: 0 | BX17: 0 | BY17: {=XLOOKUP(C17,'PL TOTAL D0'!$A$3:$A$1991,'PL TOTAL D0'!$C$3:$C$1991,"")}
A18: BTG | B18: Ahmad Taha Comercio De Moveis LTDA | C18: 004368468 | D18: Miura | E18: SUL | F18: Lucas Zambrin | G18: =IFS($BS$4:$BS$1280<=250000,"David",$BS$4:$BS$1280<=800000,"Gabriel", $BS$4:$BS$1280>800000,"Marcus") -> Gabriel | H18: Inativo | I18: Monitoramento | J18: =IF(Q18=0,"Não","Sim") -> Sim | K18: 45582 | M18: CON | N18: 0.012 | O18: CDI | P18: 0.1 | Q18: Investimentos seguem a Sharia, Lei islamica. Investimentos Halal. ETF de Referência, ISWD. | R18: Cliente identificado como monitoramento por restrição devido a religião | S18: PJ | T18: 10.574.646/0001-36 | U18: 5511981868000 | V18: diretoria@todeschinisumare.com.br | W18: 39783 | X18: SP | Y18: =IFS(H:H="Encerrado","Encerrado",COUNTBLANK(AZ18:BK18)>0,"Ativo",SUM(AZ18:BK18)=0,"Inativo",SUM(AZ18:BK18)>0,"Ativo") -> Ativo | AA18: Moderado | AD18: 45582 | AE18: 49075100016097 | BD18: 483681.1 | BE18: 487885.79 | BF18: 489606.03 | BG18: 477789.7 | BH18: 477589.96 | BI18: 236577.61 | BJ18: 133028.09 | BK18: 136607.22 | BL18: 137215.12 | BM18: 138721.41 | BN18: 140304.7 | BO18: 142967.2 | BP18: 149312.2 | BQ18: 171247 | BR18: 384258.9 | BS18: 399197.96 | BT18: 504224.4 | BU18: 497980.1 | BV18: 507379 | BW18: 525045.4 | BX18: 519751.67 | BY18: {=XLOOKUP(C18,'PL TOTAL D0'!$A$3:$A$1991,'PL TOTAL D0'!$C$3:$C$1991,"")} -> 507506.12
A19: BTG | B19: Alan Mosele Tonin e/ou Laís Salgueiro Ribeiro | C19: 005312963 | D19: Bluemetrix | E19: GO | F19: Felipe Rios | G19: =IFS($BS$4:$BS$1280<=250000,"David",$BS$4:$BS$1280<=800000,"Gabriel", $BS$4:$BS$1280>800000,"Marcus") -> David | H19: Ativo | I19: ------ | J19: =IF(Q19=0,"Não","Sim") -> Sim | K19: 45357 | M19: CON/ GR | N19: 0.012 | O19: CDI | P19: 0.1 | Q19: Sem RV (15/05/2026) | S19: PF | T19: 026.921.410-08 | U19: 5561982721320 | V19: tonin.alan@gmail.com | W19: 32888 | X19: GO | Y19: =IFS(H:H="Encerrado","Encerrado",COUNTBLANK(AZ19:BK19)>0,"Ativo",SUM(AZ19:BK19)=0,"Inativo",SUM(AZ19:BK19)>0,"Ativo") -> Ativo | AB19: Qualificado | AD19: 45357 | AE19: 49075100013713 | AV19: 0 | AW19: 33983.76 | AX19: 98177.05 | AY19: 98794.34 | AZ19: 98998.72 | BA19: 100281 | BB19: 101463.62 | BC19: 101825.97 | BD19: 102496.99 | BE19: 102836.03 | BF19: 103617.96 | BG19: 104550.42 | BH19: 105483.12 | BI19: 106114.76 | BJ19: 105697.46 | BK19: 106672.82 | BL19: 107723.62 | BM19: 108914.2 | BN19: 109983.7 | BO19: 111106.01 | BP19: 112405.1 | BQ19: 113095 | BR19: 113976.9 | BS19: 92826.63 | BT19: 93627.6 | BU19: 94674.27 | BV19: 95779.62 | BW19: 180147 | BX19: 195646.56 | BY19: {=XLOOKUP(C19,'PL TOTAL D0'!$A$3:$A$1991,'PL TOTAL D0'!$C$3:$C$1991,"")} -> 202526.35
A20: BTG | B20: Alana Abreu Coimbra | C20: 005994117 | D20: Poupinvista | E20: DF | F20: Bruno Rodrigues | G20: =IFS($BS$4:$BS$1280<=250000,"David",$BS$4:$BS$1280<=800000,"Gabriel", $BS$4:$BS$1280>800000,"Marcus") -> Gabriel | H20: Ativo | I20: ------ | J20: =IF(Q20=0,"Não","Sim") -> Sim | K20: 45546 | M20: INC | N20: 0.012 | O20: ------ | P20: 0 | Q20: Aportes e vencimentos em D+0 (18/03/2026). | S20: PF | T20: 344.229.001-53 | U20: 61999715439 | V20: alanacoimbra@gmail.com | W20: 23857 | X20: DF | Y20: =IFS(H:H="Encerrado","Encerrado",COUNTBLANK(AZ20:BK20)>0,"Ativo",SUM(AZ20:BK20)=0,"Inativo",SUM(AZ20:BK20)>0,"Ativo") -> Ativo | AA20: Moderado | AD20: 45546 | AE20: 49075100015708 | BC20: 401814.81 | BD20: 405330.59 | BE20: 408226.49 | BF20: 411164.62 | BG20: 415332.78 | BH20: 419486.15 | BI20: 423535.35 | BJ20: 428483.6 | BK20: 432722.69 | BL20: 430542.53 | BM20: 421366.38 | BN20: 407408.5 | BO20: 396416.63 | BP20: 379280.6 | BQ20: 376706.4 | BR20: 376564.8 | BS20: 371963.16 | BT20: 354311.1 | BU20: 387271 | BV20: 383078.4 | BW20: 387174.8 | BX20: 400309.75 | BY20: {=XLOOKUP(C20,'PL TOTAL D0'!$A$3:$A$1991,'PL TOTAL D0'!$C$3:$C$1991,"")} -> 395290.08
A21: BTG | B21: Alberto Carlos de Aguiar Rodrigues | C21: 004376853 | D21: Bluemetrix | E21: DF | F21: Thiago Canabrava | G21: =IFS($BS$4:$BS$1280<=250000,"David",$BS$4:$BS$1280<=800000,"Gabriel", $BS$4:$BS$1280>800000,"Marcus") -> Gabriel | H21: Ativo | I21: ------ | J21: =IF(Q21=0,"Não","Sim") -> Sim | K21: 44980 | M21: MOD | N21: 0.015 | O21: ------ | P21: 0 | Q21: Não aumentar posição de RV. Sem CrPr e Aplicações com vencimento até 01/10/2027 (30/04/2026) Histórico | S21: PF | T21: 359.321.801-10 | U21: 5561999845191 | V21: alberto@ctecnet.com.br | W21: 24014 | X21: DF | Y21: =IFS(H:H="Encerrado","Encerrado",COUNTBLANK(AZ21:BK21)>0,"Ativo",SUM(AZ21:BK21)=0,"Inativo",SUM(AZ21:BK21)>0,"Ativo") -> Ativo | AB21: Qualificado | AD21: 44980 | AE21: 49075100005400 | AI21: 0 | AJ21: 172295.8 | AK21: 482402.02 | AL21: 483551.39 | AM21: 534786.71 | AN21: 567339.85 | AO21: 565993.39 | AP21: 562995.45 | AQ21: 566653.1 | AR21: 564056.01 | AS21: 587232.97 | AT21: 608841.45 | AU21: 599756.89 | AV21: 605484 | AW21: 622694.76 | AX21: 580164.47 | AY21: 559654.4 | AZ21: 572944.1 | BA21: 585837 | BB21: 602819.49 | BC21: 610879.04 | BD21: 529157.64 | BE21: 545335.75 | BF21: 463775.38 | BG21: 478567.58 | BH21: 493133.12 | BI21: 457393.45 | BJ21: 471644.77 | BK21: 481920.61 | BL21: 491582.81 | BM21: 506687.58 | BN21: 521512.6 | BO21: 536523.28 | BP21: 530847 | BQ21: 545331.1 | BR21: 560900.6 | BS21: 576247.53 | BT21: 586143.5 | BU21: 592275.8 | BV21: 702290.5 | BW21: 709674.2 | BX21: 726053.87 | BY21: {=XLOOKUP(C21,'PL TOTAL D0'!$A$3:$A$1991,'PL TOTAL D0'!$C$3:$C$1991,"")} -> 745514.65
A22: BTG | B22: Alberto de Oliveira Faleiro Neto | C22: 005142592 | D22: Bluemetrix | E22: DF | F22: Bruno Henrique | G22: =IFS($BS$4:$BS$1280<=250000,"David",$BS$4:$BS$1280<=800000,"Gabriel", $BS$4:$BS$1280>800000,"Marcus") -> David | H22: Inativo | I22: Monitoramento | J22: =IF(Q22=0,"Não","Sim") -> Sim | K22: 45279 | M22: MONT | N22: 0.003 | O22: ------ | P22: 0 | Q22: Carteira Monitoramento Especial para Fundos (SPMG FII criado pelo cliente) (04/10/2024) | S22: PF | T22: 898.277.406-87 | U22: 5531987441177 | V22: alberto@construtoraatrium.com.br | W22: 27458 | X22: MG | Y22: =IFS(H:H="Encerrado","Encerrado",COUNTBLANK(AZ22:BK22)>0,"Ativo",SUM(AZ22:BK22)=0,"Inativo",SUM(AZ22:BK22)>0,"Ativo") -> Ativo | AB22: Qualificado | AD22: 45279 | AE22: 49075100013268 | AS22: 0 | AT22: 0 | AU22: 0 | AV22: 551.13 | AW22: 551.26 | AX22: 551.37 | AY22: 551.48 | AZ22: 555.33 | BA22: 380631.3 | BB22: 376347.14 | BC22: 376252.33 | BD22: 2155715.1 | BE22: 2155437.8 | BF22: 2155439.1 | BG22: 2155440.5 | BH22: 2155441.8 | BI22: 2155443.1 | BJ22: 2155444.6 | BK22: 2155445 | BL22: 2155446.5 | BM22: 2155448.4 | BN22: 2155752 | BO22: 2155756.9 | BP22: 2155863 | BQ22: 0 | BR22: 18.73 | BS22: 385.91 | BT22: 386.03 | BU22: 0 | BV22: 0 | BW22: 0 | BX22: 0 | BY22: {=XLOOKUP(C22,'PL TOTAL D0'!$A$3:$A$1991,'PL TOTAL D0'!$C$3:$C$1991,"")}
A23: BTG | B23: Alberto Vilar Trindade | C23: 004480970 | D23: Bluemetrix | E23: DF | F23: Matheus Vilar | G23: =IFS($BS$4:$BS$1280<=250000,"David",$BS$4:$BS$1280<=800000,"Gabriel", $BS$4:$BS$1280>800000,"Marcus") -> David | H23: Encerrado | I23: ------ | J23: =IF(Q23=0,"Não","Sim") -> Não | K23: 45036 | L23: 45693 | M23: INC | N23: 0.012 | O23: ------ | P23: 0 | S23: PF | T23: 191.136.174-00 | X23: DF | Y23: =IFS(H:H="Encerrado","Encerrado",COUNTBLANK(AZ23:BK23)>0,"Ativo",SUM(AZ23:BK23)=0,"Inativo",SUM(AZ23:BK23)>0,"Ativo") -> Encerrado | AB23: Qualificado | AD23: 45036 | AE23: 49075100003963 | AL23: 20036.96 | AM23: 20245.2 | AN23: 20421.27 | AO23: 103098.95 | AP23: 104109.61 | AQ23: 104930.65 | AR23: 105845.33 | AS23: 106619.36 | AT23: 107450.42 | AU23: 128227.68 | AV23: 129200.16 | AW23: 130282.38 | AX23: 131317.71 | AY23: 132328.3 | AZ23: 9998.49 | BA23: 10088.41 | BB23: 412821.05 | BC23: 415876.47 | BD23: 0 | BE23: 0 | BF23: 0 | BG23: 0 | BH23: 0 | BI23: 0 | BJ23: 0 | BK23: 0 | BL23: 0 | BM23: 0 | BN23: 0 | BO23: 0 | BP23: 0 | BQ23: 0 | BR23: 0 | BS23: 0 | BT23: 0 | BU23: 0 | BV23: 0 | BW23: 0 | BX23: 0 | BY23: {=XLOOKUP(C23,'PL TOTAL D0'!$A$3:$A$1991,'PL TOTAL D0'!$C$3:$C$1991,"")}
A24: BTG | B24: Alessandra Andrade Vieira | C24: 005993550 | D24: Miura | E24: SUL | F24: Rodrigo Milanez | G24: =IFS($BS$4:$BS$1280<=250000,"David",$BS$4:$BS$1280<=800000,"Gabriel", $BS$4:$BS$1280>800000,"Marcus") -> David | H24: Encerrado | I24: ------ | J24: =IF(Q24=0,"Não","Sim") -> Não | K24: 45544 | L24: 45692 | M24: MONT | N24: 0 | O24: ------ | P24: 0 | R24: Alteração de carteira finalizada (17/12/2024) | S24: PF | T24: 864.270.919-72 | X24: PR | Y24: =IFS(H:H="Encerrado","Encerrado",COUNTBLANK(AZ24:BK24)>0,"Ativo",SUM(AZ24:BK24)=0,"Inativo",SUM(AZ24:BK24)>0,"Ativo") -> Encerrado | AA24: Moderado | AD24: 45544 | AE24: 49075100016151 | BC24: 0 | BD24: 0 | BE24: 0 | BF24: 540312.14 | BG24: 423046.77 | BH24: 0 | BI24: 0 | BJ24: 0 | BK24: 0 | BL24: 0 | BM24: 0 | BN24: 0 | BO24: 0 | BP24: 0 | BQ24: 0 | BR24: 0 | BS24: 0 | BT24: 0 | BU24: 0 | BV24: 0 | BW24: 0 | BX24: 0 | BY24: {=XLOOKUP(C24,'PL TOTAL D0'!$A$3:$A$1991,'PL TOTAL D0'!$C$3:$C$1991,"")}
A25: BTG | B25: Alessandra Charbel Janiques Rebouças | C25: 004713953 | D25: Bluemetrix | E25: DF | F25: Bluemetrix Asset | G25: =IFS($BS$4:$BS$1280<=250000,"David",$BS$4:$BS$1280<=800000,"Gabriel", $BS$4:$BS$1280>800000,"Marcus") -> Gabriel | H25: Ativo | I25: ------ | J25: =IF(Q25=0,"Não","Sim") -> Não | K25: 45106 | M25: INC | N25: 0.012 | O25: ------ | P25: 0 | S25: PF | T25: 539.413.301-87 | U25: 5561992140992 | V25: acjreboucas@gmail.com | W25: 26973 | X25: DF | Y25: =IFS(H:H="Encerrado","Encerrado",COUNTBLANK(AZ25:BK25)>0,"Ativo",SUM(AZ25:BK25)=0,"Inativo",SUM(AZ25:BK25)>0,"Ativo") -> Ativo | AB25: Qualificado | AD25: 45106 | AE25: 49075100006857 | AN25: 70008.87 | AO25: 70636.99 | AP25: 71354.76 | AQ25: 71920.45 | AR25: 72317.98 | AS25: 72834.21 | AT25: 73387.99 | AU25: 167576.59 | AV25: 191999.9 | AW25: 193638.73 | AX25: 205029.58 | AY25: 206188.7 | AZ25: 207731.3 | BA25: 209396.6 | BB25: 211112.7 | BC25: 212369.64 | BD25: 214181.97 | BE25: 215756.79 | BF25: 216568.79 | BG25: 218479.1 | BH25: 220076.86 | BI25: 303240.92 | BJ25: 306102.24 | BK25: 308447.91 | BL25: 311130.11 | BM25: 331553.92 | BN25: 334803.2 | BO25: 337750.82 | BP25: 341677 | BQ25: 344247 | BR25: 346599.5 | BS25: 350378.71 | BT25: 353240.9 | BU25: 355817.7 | BV25: 359291.8 | BW25: 363036.7 | BX25: 366457.95 | BY25: {=XLOOKUP(C25,'PL TOTAL D0'!$A$3:$A$1991,'PL TOTAL D0'!$C$3:$C$1991,"")} -> 369891.49
A26: BTG | B26: Alessandra Charbel Janiques Rebouças e/ou André Airton de Macedo Rebouças | C26: 005312576 | D26: Bluemetrix | E26: DF | F26: Bluemetrix Asset | G26: =IFS($BS$4:$BS$1280<=250000,"David",$BS$4:$BS$1280<=800000,"Gabriel", $BS$4:$BS$1280>800000,"Marcus") -> David | H26: Inativo | I26: Bloqueado | J26: =IF(Q26=0,"Não","Sim") -> Não | K26: 45356 | M26: CON | N26: 0.01 | O26: CDI | P26: 0.1 | S26: PF | T26: 539.413.301-87 | U26: 5561992140992 | V26: acjreboucas@gmail.com | W26: 26973 | X26: DF | Y26: =IFS(H:H="Encerrado","Encerrado",COUNTBLANK(AZ26:BK26)>0,"Ativo",SUM(AZ26:BK26)=0,"Inativo",SUM(AZ26:BK26)>0,"Ativo") -> Inativo | AB26: Qualificado | AD26: 45356 | AE26: 49075100013721 | AV26: 0 | AW26: 0 | AX26: 0 | AY26: 0 | AZ26: 0 | BA26: 0 | BB26: 0 | BC26: 0 | BD26: 0 | BE26: 0 | BF26: 0 | BG26: 0 | BH26: 0 | BI26: 0 | BJ26: 0 | BK26: 0 | BL26: 0 | BM26: 0 | BN26: 0 | BO26: 0 | BP26: 0 | BQ26: 0 | BR26: 0 | BS26: 0 | BT26: 0 | BU26: 0 | BV26: 0 | BW26: 0 | BX26: 0 | BY26: {=XLOOKUP(C26,'PL TOTAL D0'!$A$3:$A$1991,'PL TOTAL D0'!$C$3:$C$1991,"")}
A27: BTG | B27: Alessandra Daibert Couri | C27: 004872395 | D27: Voga | E27: DF | F27: Theo Ramos Moutinho | G27: =IFS($BS$4:$BS$1280<=250000,"David",$BS$4:$BS$1280<=800000,"Gabriel", $BS$4:$BS$1280>800000,"Marcus") -> David | H27: Encerrado | I27: ------ | J27: =IF(Q27=0,"Não","Sim") -> Não | K27: 45148 | L27: 45513 | M27: MOD/ PREV MOD | N27: 0.01 | O27: ------ | P27: 0 | S27: PF | T27: 030.345.906-95 | X27: DF | Y27: =IFS(H:H="Encerrado","Encerrado",COUNTBLANK(AZ27:BK27)>0,"Ativo",SUM(AZ27:BK27)=0,"Inativo",SUM(AZ27:BK27)>0,"Ativo") -> Encerrado | AB27: Qualificado | AD27: 45148 | AE27: 49075100012156 | AP27: 221510.59 | AQ27: 242583.64 | AR27: 243545.23 | AS27: 249632.92 | AT27: 267670.75 | AU27: 267143.19 | AV27: 272226.07 | AW27: 276789.02 | AX27: 291365.65 | AY27: 293881.1 | AZ27: 295514.8 | BA27: 0 | BB27: 0 | BC27: 0 | BD27: 0 | BE27: 0 | BF27: 0 | BG27: 0 | BH27: 0 | BI27: 0 | BJ27: 0 | BK27: 0 | BL27: 0 | BM27: 0 | BN27: 0 | BO27: 0 | BP27: 0 | BQ27: 0 | BR27: 0 | BS27: 0 | BT27: 0 | BU27: 0 | BV27: 0 | BW27: 0 | BX27: 0 | BY27: {=XLOOKUP(C27,'PL TOTAL D0'!$A$3:$A$1991,'PL TOTAL D0'!$C$3:$C$1991,"")}
A28: BTG | B28: Alessandra Nazare Crispim Goncalves | C28: 005749972 | D28: Bluemetrix | E28: DF | F28: Thiago Canabrava | G28: =IFS($BS$4:$BS$1280<=250000,"David",$BS$4:$BS$1280<=800000,"Gabriel", $BS$4:$BS$1280>800000,"Marcus") -> Gabriel | H28: Ativo | I28: ------ | J28: =IF(Q28=0,"Não","Sim") -> Não | K28: 45488 | M28: INC | N28: 0.012 | O28: ------ | P28: 0 | S28: PF | T28: 712.174.601-87 | U28: 61998010160 | V28: alessacrispim@gmail.com | W28: 29188 | X28: DF | Y28: =IFS(H:H="Encerrado","Encerrado",COUNTBLANK(AZ28:BK28)>0,"Ativo",SUM(AZ28:BK28)=0,"Inativo",SUM(AZ28:BK28)>0,"Ativo") -> Ativo | AA28: Conservador | AB28: Qualificado | AD28: 45488 | AE28: 49075100015473 | BA28: 80196.25 | BB28: 470775.27 | BC28: 483335.63 | BD28: 487785.93 | BE28: 491549.24 | BF28: 495553.15 | BG28: 500406.42 | BH28: 505027.51 | BI28: 510415.32 | BJ28: 515491.31 | BK28: 520845.98 | BL28: 525177.79 | BM28: 530486.51 | BN28: 533248.5 | BO28: 538162.47 | BP28: 544608.5 | BQ28: 549288.8 | BR28: 538424.5 | BS28: 543859.22 | BT28: 544891.8 | BU28: 546435.6 | BV28: 538739.1 | BW28: 544751.1 | BX28: 549764.32 | BY28: {=XLOOKUP(C28,'PL TOTAL D0'!$A$3:$A$1991,'PL TOTAL D0'!$C$3:$C$1991,"")} -> 550274.29
A29: BTG | B29: Alessandra Padilha Valle Kanitz | C29: 004946542 | D29: Bluemetrix | E29: DF | F29: Gustavo Amorim | G29: =IFS($BS$4:$BS$1280<=250000,"David",$BS$4:$BS$1280<=800000,"Gabriel", $BS$4:$BS$1280>800000,"Marcus") -> David | H29: Ativo | I29: ------ | J29: =IF(Q29=0,"Não","Sim") -> Sim | K29: 45160 | M29: INC | N29: 0.012 | O29: ------ | P29: 0 | Q29: 30k D+0 (29/09/2025) | S29: PF | T29: 610.888.701-04 | U29: 61992757864 | V29: alepvk@gmail.com | W29: 26873 | X29: DF | Y29: =IFS(H:H="Encerrado","Encerrado",COUNTBLANK(AZ29:BK29)>0,"Ativo",SUM(AZ29:BK29)=0,"Inativo",SUM(AZ29:BK29)>0,"Ativo") -> Ativo | AB29: Qualificado | AD29: 45160 | AE29: 49075100008019 | AP29: 601175.9 | AQ29: 606237.94 | AR29: 611489.99 | AS29: 615841.54 | AT29: 619579.86 | AU29: 625184.81 | AV29: 629881.63 | AW29: 633953.26 | AX29: 638440.22 | AY29: 643538.6 | AZ29: 648288.5 | BA29: 653705.9 | BB29: 654754.17 | BC29: 659134.65 | BD29: 665198.12 | BE29: 670243.63 | BF29: 675415.97 | BG29: 681856.15 | BH29: 688297.79 | BI29: 180510.23 | BJ29: 182238.25 | BK29: 184182 | BL29: 185869.95 | BM29: 188064.14 | BN29: 189376.3 | BO29: 191357.53 | BP29: 162856.3 | BQ29: 164474 | BR29: 160669.3 | BS29: 162463.56 | BT29: 128469.9 | BU29: 130178.5 | BV29: 131884.7 | BW29: 126506.8 | BX29: 122955.71 | BY29: {=XLOOKUP(C29,'PL TOTAL D0'!$A$3:$A$1991,'PL TOTAL D0'!$C$3:$C$1991,"")} -> 114440.98
A30: BTG | B30: Alessandra Sado | C30: 020016028 | D30: VcInvest | E30: GO | F30: Bruno Ribeiro | G30: Gabriel | H30: Ativo | I30: ------ | J30: =IF(Q30=0,"Não","Sim") -> Não | K30: 46094 | M30: INC | N30: 0.012 | O30: ------ | P30: 0 | S30: PF | T30: 788.043.611-15 | U30: 62 98139-0612 | V30: alessandrasado@gmail.com | W30: 27672 | X30: GO | Y30: =IFS(H:H="Encerrado","Encerrado",COUNTBLANK(AZ30:BK30)>0,"Ativo",SUM(AZ30:BK30)=0,"Inativo",SUM(AZ30:BK30)>0,"Ativo") -> Ativo | AA30: Moderado | AD30: 46203 | BU30: 688247 | BV30: 677760.6 | BW30: 1619387 | BX30: 1925112.2 | BY30: {=XLOOKUP(C30,'PL TOTAL D0'!$A$3:$A$1991,'PL TOTAL D0'!$C$3:$C$1991,"")} -> 1950686.6
A31: BTG | B31: Alessandro Alcantara Correira | C31: 008032597 | D31: Bluemetrix | E31: DF | F31: Thiago Canabrava | G31: =IFS($BS$4:$BS$1280<=250000,"David",$BS$4:$BS$1280<=800000,"Gabriel", $BS$4:$BS$1280>800000,"Marcus") -> David | H31: Ativo | I31: ------ | J31: =IF(Q31=0,"Não","Sim") -> Sim | K31: 45565 | M31: INC | N31: 0.012 | O31: ------ | P31: 0 | Q31: 40K até D+1 (17/10/2024) | S31: PF | T31: 092.878.271-92 | U31: 61998002436 | V31: alessandrocorreira@gmail.com | W31: 38545 | X31: DF | Y31: =IFS(H:H="Encerrado","Encerrado",COUNTBLANK(AZ31:BK31)>0,"Ativo",SUM(AZ31:BK31)=0,"Inativo",SUM(AZ31:BK31)>0,"Ativo") -> Ativo | AA31: Conservador | AD31: 45565 | AE31: 49075100016070 | BC31: 0 | BD31: 144963.23 | BE31: 146156.63 | BF31: 147289.33 | BG31: 148666.98 | BH31: 141273.71 | BI31: 143140.31 | BJ31: 118564.79 | BK31: 117015.29 | BL31: 118039.22 | BM31: 110912.16 | BN31: 112195.6 | BO31: 112891.31 | BP31: 113730.6 | BQ31: 107003.4 | BR31: 108003.4 | BS31: 109198.28 | BT31: 106322 | BU31: 107565.8 | BV31: 105829.7 | BW31: 106818.8 | BX31: 107802.44 | BY31: {=XLOOKUP(C31,'PL TOTAL D0'!$A$3:$A$1991,'PL TOTAL D0'!$C$3:$C$1991,"")} -> 109077.68
A32: BTG | B32: Alessandro Alcantara Correira | C32: 008569831 | D32: Bluemetrix | E32: DF | F32: Thiago Canabrava | G32: =IFS($BS$4:$BS$1280<=250000,"David",$BS$4:$BS$1280<=800000,"Gabriel", $BS$4:$BS$1280>800000,"Marcus") -> David | H32: Inativo | I32: Monitoramento | J32: =IF(Q32=0,"Não","Sim") -> Não | K32: 45743 | M32: MONT | N32: 0.005 | O32: ------ | P32: 0 | S32: PF | T32: 092.878.271-92 | U32: 61998002436 | V32: alessandrocorreira@gmail.com | W32: 38545 | X32: DF | Y32: =IFS(H:H="Encerrado","Encerrado",COUNTBLANK(AZ32:BK32)>0,"Ativo",SUM(AZ32:BK32)=0,"Inativo",SUM(AZ32:BK32)>0,"Ativo") -> Ativo | AA32: Conservador | AD32: 45757 | AE32: 49075100018723 | BI32: 0 | BJ32: 20829.9 | BK32: 21006.05 | BL32: 9091.95 | BM32: 9198.3 | BN32: 9303.51 | BO32: 1270.16 | BP32: 1286.84 | BQ32: 1287.07 | BR32: 0.53 | BS32: 0.53 | BT32: 0.53 | BU32: 0.53 | BV32: 2054 | BW32: 0 | BX32: 0.02 | BY32: {=XLOOKUP(C32,'PL TOTAL D0'!$A$3:$A$1991,'PL TOTAL D0'!$C$3:$C$1991,"")}
A33: BTG | B33: Alessandro Luis Almeida Bacelar Gama | C33: 004252768 | D33: Altum | E33: DF | F33: João Victor de Moura Beze | G33: =IFS($BS$4:$BS$1280<=250000,"David",$BS$4:$BS$1280<=800000,"Gabriel", $BS$4:$BS$1280>800000,"Marcus") -> David | H33: Encerrado | I33: ------ | J33: =IF(Q33=0,"Não","Sim") -> Não | K33: 44958 | L33: 45775 | M33: INC | N33: 0.012 | O33: ------ | P33: 0 | S33: PF | T33: 030.523.481-16 | X33: DF | Y33: =IFS(H:H="Encerrado","Encerrado",COUNTBLANK(AZ33:BK33)>0,"Ativo",SUM(AZ33:BK33)=0,"Inativo",SUM(AZ33:BK33)>0,"Ativo") -> Encerrado | AB33: Qualificado | AD33: 44958 | AE33: 49075100010242 | AK33: 53545.8 | AL33: 54182.77 | AM33: 288087.22 | AN33: 344984.05 | AO33: 347862.28 | AP33: 400633.57 | AQ33: 262688.84 | AR33: 405398.15 | AS33: 408413 | AT33: 411553.44 | AU33: 415212.78 | AV33: 418571.1 | AW33: 238572.2 | AX33: 239496.64 | AY33: 241378.1 | AZ33: 242844.8 | BA33: 244871.4 | BB33: 246300.96 | BC33: 247154.56 | BD33: 249300.04 | BE33: 251095.83 | BF33: 252850.55 | BG33: 0 | BH33: 0 | BI33: 0 | BJ33: 0 | BK33: 0 | BL33: 0 | BM33: 0 | BN33: 0 | BO33: 0 | BP33: 0 | BQ33: 0 | BR33: 0 | BS33: 0 | BT33: 0 | BU33: 0 | BV33: 0 | BW33: 0 | BX33: 0 | BY33: {=XLOOKUP(C33,'PL TOTAL D0'!$A$3:$A$1991,'PL TOTAL D0'!$C$3:$C$1991,"")}
A34: BTG | B34: Alessandro Pasqualinotti | C34: 022511372 | D34: Miura | E34: SUL | F34: Lucas Zambrin | G34: =IFS($BS$4:$BS$1280<=250000,"David",$BS$4:$BS$1280<=800000,"Gabriel", $BS$4:$BS$1280>800000,"Marcus") -> David | H34: Ativo | I34: ------ | J34: =IF(Q34=0,"Não","Sim") -> Não | K34: 46083 | M34: MOD | N34: 0.015 | O34: CDI | P34: 0.1 | S34: PF | T34: 865.989.029-91 | U34: 43 99149-0648 | V34: comercial@jplembalagens.com.br | W34: 26604 | X34: PR | Y34: =IFS(H:H="Encerrado","Encerrado",COUNTBLANK(AZ34:BK34)>0,"Ativo",SUM(AZ34:BK34)=0,"Inativo",SUM(AZ34:BK34)>0,"Ativo") -> Ativo | AA34: Moderado | AD34: 46203 | BU34: 0 | BV34: 0 | BW34: 489347.2 | BX34: 495711.5 | BY34: {=XLOOKUP(C34,'PL TOTAL D0'!$A$3:$A$1991,'PL TOTAL D0'!$C$3:$C$1991,"")} -> 534945.84
A35: BTG | B35: Alexandre Cardoso Barreto Santana | C35: 005823200 | D35: Investeseg | E35: BA | F35: Murilo Silva | G35: =IFS($BS$4:$BS$1280<=250000,"David",$BS$4:$BS$1280<=800000,"Gabriel", $BS$4:$BS$1280>800000,"Marcus") -> David | H35: Ativo | I35: ------ | J35: =IF(Q35=0,"Não","Sim") -> Não | K35: 46212 | M35: MOD | N35: 0.015 | O35: CDI | P35: 0.1 | S35: PF | T35: 784.038.805-10 | U35: 71 98884-7559 | V35: alexandre.ucsal@hotmail.com | W35: 29918 | X35: BA | Y35: =IFS(H:H="Encerrado","Encerrado",COUNTBLANK(AZ35:BK35)>0,"Ativo",SUM(AZ35:BK35)=0,"Inativo",SUM(AZ35:BK35)>0,"Ativo") -> Ativo | AA35: Moderado | BX35: 0 | BY35: {=XLOOKUP(C35,'PL TOTAL D0'!$A$3:$A$1991,'PL TOTAL D0'!$C$3:$C$1991,"")} -> 150923.26
A36: BTG | B36: Alexandre De Paula Trindade | C36: 026366781 | D36: Miura | E36: SUL | F36: Lucas Zambrin | G36: =IFS($BS$4:$BS$1280<=250000,"David",$BS$4:$BS$1280<=800000,"Gabriel", $BS$4:$BS$1280>800000,"Marcus") -> David | H36: Ativo | I36: ------ | J36: =IF(Q36=0,"Não","Sim") -> Não | K36: 46216 | M36: MOD | N36: 0.015 | O36: CDI | P36: 0.1 | S36: PF | T36: 551.349.399-34 | U36: 43 99614-0505 | V36: alexpt.uniware@gmail.com | W36: 23797 | X36: PR | Y36: =IFS(H:H="Encerrado","Encerrado",COUNTBLANK(AZ36:BK36)>0,"Ativo",SUM(AZ36:BK36)=0,"Inativo",SUM(AZ36:BK36)>0,"Ativo") -> Ativo | AA36: Arrojado | BX36: 0 | BY36: {=XLOOKUP(C36,'PL TOTAL D0'!$A$3:$A$1991,'PL TOTAL D0'!$C$3:$C$1991,"")} -> 452141.01
A37: BTG | B37: Alexandre Lopes Figueiredo | C37: 004520100 | D37: Miura | E37: SUL | F37: Rodrigo Milanez | G37: =IFS($BS$4:$BS$1280<=250000,"David",$BS$4:$BS$1280<=800000,"Gabriel", $BS$4:$BS$1280>800000,"Marcus") -> David | H37: Ativo | I37: ------ | J37: =IF(Q37=0,"Não","Sim") -> Não | K37: 45982 | M37: INC | N37: 0.012 | O37: ------ | P37: 0 | R37: STVM de entrada da Guide finalizada (10/09/2023) | S37: PF | T37: 841.104.149-20 | U37: 43 98828-1735 | V37: alfgf22@gmail.com | W37: 25802 | X37: PR | Y37: =IFS(H:H="Encerrado","Encerrado",COUNTBLANK(AZ37:BK37)>0,"Ativo",SUM(AZ37:BK37)=0,"Inativo",SUM(AZ37:BK37)>0,"Ativo") -> Ativo | AA37: Moderado | AB37: Qualificado | AD37: 45166 | AE37: 49075100011052 | AL37: 0 | AM37: 0 | AN37: 0 | AO37: 0 | AP37: 0 | AQ37: 238854.55 | AR37: 237988.82 | AS37: 243644.48 | AT37: 248581.27 | AU37: 243901.96 | AV37: 22702.09 | AW37: 22583.51 | AX37: 22731.6 | AY37: 22870.18 | AZ37: 23007.81 | BA37: 23185.59 | BB37: 23352.68 | BC37: 23514.39 | BD37: 0 | BE37: 0 | BF37: 0 | BG37: 0 | BH37: 0 | BI37: 0 | BJ37: 0 | BK37: 0 | BL37: 0 | BM37: 0 | BN37: 0 | BO37: 0 | BP37: 0 | BQ37: 113570.4 | BR37: 114815.4 | BS37: 115959.86 | BT37: 116980.1 | BU37: 118349.3 | BV37: 119638.5 | BW37: 120916.8 | BX37: 121652.51 | BY37: {=XLOOKUP(C37,'PL TOTAL D0'!$A$3:$A$1991,'PL TOTAL D0'!$C$3:$C$1991,"")} -> 122978.6
A38: BTG | B38: Alexandre Ramos Vieira | C38: 005558076 | D38: Altum | E38: DF | F38: Paula Lemos | G38: =IFS($BS$4:$BS$1280<=250000,"David",$BS$4:$BS$1280<=800000,"Gabriel", $BS$4:$BS$1280>800000,"Marcus") -> David | H38: Inativo | I38: Sem Saldo | J38: =IF(Q38=0,"Não","Sim") -> Não | K38: 45426 | M38: INC | N38: 0.012 | O38: ------ | P38: 0 | S38: PF | T38: 120.779.681-68 | U38: 5561995360707 | V38: alexvieira22071@gmail.com | W38: 20606 | X38: DF | Y38: =IFS(H:H="Encerrado","Encerrado",COUNTBLANK(AZ38:BK38)>0,"Ativo",SUM(AZ38:BK38)=0,"Inativo",SUM(AZ38:BK38)>0,"Ativo") -> Ativo | AA38: Conservador | AB38: Qualificado | AD38: 45426 | AE38: 49075100014401 | AY38: 100500.8 | AZ38: 101325.3 | BA38: 102220.7 | BB38: 103033.35 | BC38: 103776.92 | BD38: 104644.94 | BE38: 105385.27 | BF38: 105970.95 | BG38: 106908.07 | BH38: 107768.52 | BI38: 104640.99 | BJ38: 105788.83 | BK38: 0 | BL38: 46.08 | BM38: 46.08 | BN38: 46.08 | BO38: 46.08 | BP38: 46.08 | BQ38: 46.08 | BR38: 46.08 | BS38: 46.08 | BT38: 46.08 | BU38: 46.08 | BV38: 46.08 | BW38: 46.08 | BX38: 46.08 | BY38: {=XLOOKUP(C38,'PL TOTAL D0'!$A$3:$A$1991,'PL TOTAL D0'!$C$3:$C$1991,"")}
A39: BTG | B39: Alexandre Strauch Pereira Coutinho | C39: 005022526 | D39: Bluemetrix | E39: DF | F39: Matheus Vilar | G39: =IFS($BS$4:$BS$1280<=250000,"David",$BS$4:$BS$1280<=800000,"Gabriel", $BS$4:$BS$1280>800000,"Marcus") -> David | H39: Encerrado | I39: ------ | J39: =IF(Q39=0,"Não","Sim") -> Não | K39: 45201 | L39: 45414 | M39: INC | N39: 0.01 | O39: ------ | P39: 0 | R39: Cliente vai resgatar sozinho/ Troca de Assessoria de Thiago Canbrava para Matheus Vilar | S39: PF | T39: 028.189.781-65 | X39: DF | Y39: =IFS(H:H="Encerrado","Encerrado",COUNTBLANK(AZ39:BK39)>0,"Ativo",SUM(AZ39:BK39)=0,"Inativo",SUM(AZ39:BK39)>0,"Ativo") -> Encerrado | AB39: Não Qualificado | AD39: 45201 | AE39: 49075100011079 | AQ39: 0 | AR39: 56301.66 | AS39: 56710.28 | AT39: 57141.5 | AU39: 57124.59 | AV39: 57677.35 | AW39: 58076.04 | AX39: 0 | AY39: 0 | AZ39: 1.7 | BA39: 1.7 | BB39: 1.7 | BC39: 1.7 | BD39: 1.7 | BE39: 1.7 | BF39: 1.7 | BG39: 1.7 | BH39: 1.7 | BI39: 1.7 | BJ39: 0 | BK39: 0 | BL39: 0 | BM39: 0 | BN39: 0 | BO39: 0 | BP39: 0 | BQ39: 0 | BR39: 0 | BS39: 0 | BT39: 0 | BU39: 0 | BV39: 0 | BW39: 0 | BX39: 0 | BY39: {=XLOOKUP(C39,'PL TOTAL D0'!$A$3:$A$1991,'PL TOTAL D0'!$C$3:$C$1991,"")}
A40: BTG | B40: Alexandre Strauch Pereira Coutinho | C40: 005019925 | D40: Bluemetrix | E40: DF | F40: Matheus Vilar | G40: =IFS($BS$4:$BS$1280<=250000,"David",$BS$4:$BS$1280<=800000,"Gabriel", $BS$4:$BS$1280>800000,"Marcus") -> David | H40: Encerrado | I40: ------ | J40: =IF(Q40=0,"Não","Sim") -> Não | K40: 45196 | L40: 45414 | M40: EQT | N40: 0.02 | O40: IBOVESPA | P40: 0.2 | R40: Aguardando resposta do FA / Troca de Assessoria de Thiago Canbrava para Matheus Vilar | S40: PF | T40: 028.189.781-65 | U40: 5561981567737 | V40: alexandre.strauch@hotmail.com | W40: 32257 | X40: DF | Y40: =IFS(H:H="Encerrado","Encerrado",COUNTBLANK(AZ40:BK40)>0,"Ativo",SUM(AZ40:BK40)=0,"Inativo",SUM(AZ40:BK40)>0,"Ativo") -> Encerrado | AB40: Não Qualificado | AD40: 45196 | AE40: 49075100011060 | AQ40: 0 | AR40: 0 | AS40: 0 | AT40: 0 | AU40: 0 | AV40: 1.06 | AW40: 1.06 | AX40: 0 | AY40: 0 | AZ40: 0 | BA40: 0 | BB40: 0 | BC40: 0 | BD40: 0 | BE40: 0 | BF40: 0 | BG40: 0 | BH40: 0 | BI40: 0 | BJ40: 1.7 | BK40: 1.7 | BL40: 1.7 | BM40: 1.7 | BN40: 1.7 | BO40: 1.7 | BP40: 1.7 | BQ40: 1.7 | BR40: 1.7 | BS40: 1.7 | BT40: 1.7 | BU40: 1.7 | BV40: 1.7 | BW40: 1.7 | BX40: 1.7 | BY40: {=XLOOKUP(C40,'PL TOTAL D0'!$A$3:$A$1991,'PL TOTAL D0'!$C$3:$C$1991,"")}
A41: BTG | B41: Alexandre Strauch Pereira Coutinho | C41: 005028018 | D41: Bluemetrix | E41: DF | F41: Matheus Vilar | G41: =IFS($BS$4:$BS$1280<=250000,"David",$BS$4:$BS$1280<=800000,"Gabriel", $BS$4:$BS$1280>800000,"Marcus") -> David | H41: Encerrado | I41: ------ | J41: =IF(Q41=0,"Não","Sim") -> Não | K41: 45202 | L41: 45414 | M41: FII | N41: 0.008 | O41: IFIX | P41: 0.1 | R41: Troca de Assessoria de Thiago Canbrava para Matheus Vilar | S41: PF | T41: 028.189.781-65 | U41: 5561981567737 | V41: alexandre.strauch@hotmail.com | W41: 32257 | X41: DF | Y41: =IFS(H:H="Encerrado","Encerrado",COUNTBLANK(AZ41:BK41)>0,"Ativo",SUM(AZ41:BK41)=0,"Inativo",SUM(AZ41:BK41)>0,"Ativo") -> Encerrado | AB41: Não Qualificado | AD41: 45202 | AE41: 49075100011087 | AQ41: 0 | AR41: 50.92 | AS41: 33.05 | AT41: 33.05 | AU41: 33.05 | AV41: 33.05 | AW41: 33.05 | AX41: 0 | AY41: 0 | AZ41: 0 | BA41: 0 | BB41: 0 | BC41: 0 | BD41: 0 | BE41: 0 | BF41: 0 | BG41: 0 | BH41: 0 | BI41: 0 | BJ41: 0 | BK41: 0 | BL41: 0 | BM41: 0 | BN41: 0 | BO41: 0 | BP41: 0 | BQ41: 0 | BR41: 0 | BS41: 0 | BT41: 0 | BU41: 0 | BV41: 0 | BW41: 0 | BX41: 0 | BY41: {=XLOOKUP(C41,'PL TOTAL D0'!$A$3:$A$1991,'PL TOTAL D0'!$C$3:$C$1991,"")}
A42: BTG | B42: Alexandre Zanin Neto | C42: 005024046 | D42: Miura | E42: SUL | F42: Lucas Zambrin | G42: =IFS($BS$4:$BS$1280<=250000,"David",$BS$4:$BS$1280<=800000,"Gabriel", $BS$4:$BS$1280>800000,"Marcus") -> David | H42: Ativo | I42: ------ | J42: =IF(Q42=0,"Não","Sim") -> Não | K42: 45198 | M42: MOD | N42: 0.015 | O42: CDI | P42: 0.1 | R42: STVM de entrada da Guide finalizada (06/11/2023) / Alteração de carteira finalizada (05/08/2024) | S42: PF | T42: 020.252.419-17 | U42: 5543999889697 | V42: nin00@trf4.jus.br | W42: 28486 | X42: PR | Y42: =IFS(H:H="Encerrado","Encerrado",COUNTBLANK(AZ42:BK42)>0,"Ativo",SUM(AZ42:BK42)=0,"Inativo",SUM(AZ42:BK42)>0,"Ativo") -> Ativo | AB42: Qualificado | AD42: 45198 | AE42: 49075100011095 | AQ42: 0 | AR42: 123194.03 | AS42: 125199.64 | AT42: 127045.25 | AU42: 126759.44 | AV42: 127792.29 | AW42: 129147.26 | AX42: 129298.77 | AY42: 129527.5 | AZ42: 130473.4 | BA42: 131745.5 | BB42: 147881.88 | BC42: 147535.75 | BD42: 147662.89 | BE42: 146495.06 | BF42: 146538.08 | BG42: 148280.4 | BH42: 149336.18 | BI42: 206800.92 | BJ42: 211550.33 | BK42: 214903.22 | BL42: 216333.09 | BM42: 161830.94 | BN42: 163644.7 | BO42: 165660 | BP42: 167783.5 | BQ42: 170397.8 | BR42: 172105.6 | BS42: 158687.63 | BT42: 160528.9 | BU42: 162330.8 | BV42: 163851.4 | BW42: 162103.9 | BX42: 169805.87 | BY42: {=XLOOKUP(C42,'PL TOTAL D0'!$A$3:$A$1991,'PL TOTAL D0'!$C$3:$C$1991,"")} -> 165457.44
A43: BTG | B43: Alexandre Zanin Neto | C43: 004890599 | D43: Miura | E43: SUL | F43: Lucas Zambrin | G43: =IFS($BS$4:$BS$1280<=250000,"David",$BS$4:$BS$1280<=800000,"Gabriel", $BS$4:$BS$1280>800000,"Marcus") -> David | H43: Encerrado | I43: ------ | J43: =IF(Q43=0,"Não","Sim") -> Não | K43: 45131 | L43: 45163 | M43: INC | N43: 0.012 | O43: ------ | P43: 0 | S43: PF | T43: 020.252.419-17 | X43: PR | Y43: =IFS(H:H="Encerrado","Encerrado",COUNTBLANK(AZ43:BK43)>0,"Ativo",SUM(AZ43:BK43)=0,"Inativo",SUM(AZ43:BK43)>0,"Ativo") -> Encerrado | AD43: 45131 | AO43: 0 | AP43: 0 | AQ43: 0 | AR43: 0 | AS43: 0 | AT43: 0 | AU43: 0 | AV43: 0 | AW43: 0 | AX43: 0 | AY43: 0 | AZ43: 0 | BA43: 0 | BB43: 0 | BC43: 0 | BD43: 0 | BE43: 0 | BF43: 0 | BG43: 0 | BH43: 0 | BI43: 0 | BJ43: 0 | BK43: 0 | BL43: 0 | BM43: 0 | BN43: 0 | BO43: 0 | BP43: 0 | BQ43: 0 | BR43: 0 | BS43: 0 | BT43: 0 | BU43: 0 | BV43: 0 | BW43: 0 | BX43: 0 | BY43: {=XLOOKUP(C43,'PL TOTAL D0'!$A$3:$A$1991,'PL TOTAL D0'!$C$3:$C$1991,"")}
A44: BTG | B44: Alexia Satyro Sá Ribeiro Fritzsche | C44: 008227566 | D44: Bluemetrix | E44: DF | F44: Norton Fritzsche | G44: =IFS($BS$4:$BS$1280<=250000,"David",$BS$4:$BS$1280<=800000,"Gabriel", $BS$4:$BS$1280>800000,"Marcus") -> David | H44: Inativo | I44: Sem Saldo | J44: =IF(Q44=0,"Não","Sim") -> Não | K44: 45639 | M44: INC | N44: 0 | O44: ------ | P44: 0 | S44: PF | T44: 058.796.871-04 | U44: 5561982353200 | V44: alexiasatyrof@gmail.com | W44: 37106 | X44: DF | Y44: =IFS(H:H="Encerrado","Encerrado",COUNTBLANK(AZ44:BK44)>0,"Ativo",SUM(AZ44:BK44)=0,"Inativo",SUM(AZ44:BK44)>0,"Ativo") -> Ativo | AA44: Conservador | AD44: 45649 | AE44: 49075100016402 | BF44: 30100.23 | BG44: 30408.97 | BH44: 30705 | BI44: 30997.13 | BJ44: 11032.22 | BK44: 11070.08 | BL44: 0 | BM44: 0.52 | BN44: 0.52 | BO44: 0.52 | BP44: 0.52 | BQ44: 0.52 | BR44: 17095.46 | BS44: 17293.17 | BT44: 17464.83 | BU44: 17677.66 | BV44: 25903.7 | BW44: 38054.81 | BX44: 38447.78 | BY44: {=XLOOKUP(C44,'PL TOTAL D0'!$A$3:$A$1991,'PL TOTAL D0'!$C$3:$C$1991,"")} -> 46637.66
A45: BTG | B45: Alice Barros De Souza | C45: 005374394 | D45: Miura | E45: SUL | F45: Rodrigo Milanez | G45: =IFS($BS$4:$BS$1280<=250000,"David",$BS$4:$BS$1280<=800000,"Gabriel", $BS$4:$BS$1280>800000,"Marcus") -> David | H45: Encerrado | I45: ------ | J45: =IF(Q45=0,"Não","Sim") -> Não | K45: 46007 | L45: 46213 | M45: INC | N45: 0.012 | O45: ------ | P45: 0 | R45: Distrato unilateral | S45: PF | T45: 093.777.699-81 | U45: 43 99846-0540 | V45: alicebarrossouza@icloud.com | W45: 34674 | X45: PR | Y45: =IFS(H:H="Encerrado","Encerrado",COUNTBLANK(AZ45:BK45)>0,"Ativo",SUM(AZ45:BK45)=0,"Inativo",SUM(AZ45:BK45)>0,"Ativo") -> Encerrado | AA45: Moderado | AD45: 00/01/1900 | BR45: 56946.98 | BS45: 57596.63 | BT45: 58060.13 | BU45: 58703.67 | BV45: 69773.57 | BW45: 0 | BX45: 0 | BY45: {=XLOOKUP(C45,'PL TOTAL D0'!$A$3:$A$1991,'PL TOTAL D0'!$C$3:$C$1991,"")}
A46: BTG | B46: Alice Daia Naves | C46: 005370995 | D46: M Wealth | E46: DF | F46: M Wealth | G46: =IFS($BS$4:$BS$1280<=250000,"David",$BS$4:$BS$1280<=800000,"Gabriel", $BS$4:$BS$1280>800000,"Marcus") -> David | H46: Ativo | I46: ------ | J46: =IF(Q46=0,"Não","Sim") -> Não | K46: 46139 | M46: CONSUL M Wealth | O46: ------ | P46: 0 | S46: PF | T46: 168.574.596-22 | U46: (34)99937-3775 | V46: fabriciofnaves@yahoo.com.br | W46: 40009 | Y46: =IFS(H:H="Encerrado","Encerrado",COUNTBLANK(AZ46:BK46)>0,"Ativo",SUM(AZ46:BK46)=0,"Inativo",SUM(AZ46:BK46)>0,"Ativo") -> Ativo | AA46: Moderado | AD46: 46203 | BV46: 19117.56 | BW46: 19212.31 | BX46: 19423.15 | BY46: {=XLOOKUP(C46,'PL TOTAL D0'!$A$3:$A$1991,'PL TOTAL D0'!$C$3:$C$1991,"")} -> 19663.05
A47: BTG | B47: Alice Lunardelli Canavezi | C47: 008671097 | D47: Miura | E47: SUL | F47: Lucas Zambrin | G47: =IFS($BS$4:$BS$1280<=250000,"David",$BS$4:$BS$1280<=800000,"Gabriel", $BS$4:$BS$1280>800000,"Marcus") -> David | H47: Ativo | I47: ------ | J47: =IF(Q47=0,"Não","Sim") -> Não | K47: 46014 | M47: INC | N47: 0.012 | O47: ------ | P47: 0 | S47: PF | T47: 147.825.949-33 | U47: 43 99156-1938 | V47: drelunardelli@hotmail.com | W47: 43508 | X47: PR | Y47: =IFS(H:H="Encerrado","Encerrado",COUNTBLANK(AZ47:BK47)>0,"Ativo",SUM(AZ47:BK47)=0,"Inativo",SUM(AZ47:BK47)>0,"Ativo") -> Ativo | AA47: Conservador | AD47: 46203 | BR47: 200914.8 | BS47: 202990.9 | BT47: 204741.5 | BU47: 207299.3 | BV47: 209622.1 | BW47: 211510.6 | BX47: 213615.04 | BY47: {=XLOOKUP(C47,'PL TOTAL D0'!$A$3:$A$1991,'PL TOTAL D0'!$C$3:$C$1991,"")} -> 215733.94
A48: BTG | B48: Alina Coimbra Castelo Branco Vasconcelos Stoenica | C48: 005596494 | D48: Bluemetrix | E48: DF | F48: Caroline Facó Ehlers | G48: =IFS($BS$4:$BS$1280<=250000,"David",$BS$4:$BS$1280<=800000,"Gabriel", $BS$4:$BS$1280>800000,"Marcus") -> David | H48: Inativo | I48: Sem Saldo | J48: =IF(Q48=0,"Não","Sim") -> Não | K48: 45421 | M48: INC | N48: 0.012 | O48: ------ | P48: 0 | S48: PF | T48: 065.969.811-00 | U48: 5561999557063 | V48: alinavasconcelos@hotmail.com | W48: 35786 | X48: SP | Y48: =IFS(H:H="Encerrado","Encerrado",COUNTBLANK(AZ48:BK48)>0,"Ativo",SUM(AZ48:BK48)=0,"Inativo",SUM(AZ48:BK48)>0,"Ativo") -> Inativo | AA48: Moderado | AB48: Qualificado | AD48: 45421 | AE48: 49075100014418 | AY48: 0 | AZ48: 0 | BA48: 0 | BB48: 0 | BC48: 0 | BD48: 0 | BE48: 0 | BF48: 0 | BG48: 0 | BH48: 0 | BI48: 0 | BJ48: 0 | BK48: 0 | BL48: 0 | BM48: 0 | BN48: 0 | BO48: 0 | BP48: 0 | BQ48: 0 | BR48: 0 | BS48: 0 | BT48: 0 | BU48: 0 | BV48: 0 | BW48: 0 | BX48: 0 | BY48: {=XLOOKUP(C48,'PL TOTAL D0'!$A$3:$A$1991,'PL TOTAL D0'!$C$3:$C$1991,"")}
A49: BTG | B49: Aline Cristina de Souza Reis | C49: 001669540 | D49: Expert | E49: GO | F49: Alcivana Marques | G49: =IFS($BS$4:$BS$1280<=250000,"David",$BS$4:$BS$1280<=800000,"Gabriel", $BS$4:$BS$1280>800000,"Marcus") -> David | H49: Ativo | I49: ------ | J49: =IF(Q49=0,"Não","Sim") -> Não | K49: 46063 | M49: EQT | N49: 0.025 | O49: IBOVESPA | P49: 0.2 | S49: PF | T49: 033.032.517-54 | U49: 62 98111-8766 | V49: alinecsr3@gmail.com | W49: 25913 | X49: GO | Y49: =IFS(H:H="Encerrado","Encerrado",COUNTBLANK(AZ49:BK49)>0,"Ativo",SUM(AZ49:BK49)=0,"Inativo",SUM(AZ49:BK49)>0,"Ativo") -> Ativo | AA49: Arrojado | AD49: 46203 | BT49: 98473.03 | BU49: 97392.07 | BV49: 97514.27 | BW49: 92516.98 | BX49: 94100.79 | BY49: {=XLOOKUP(C49,'PL TOTAL D0'!$A$3:$A$1991,'PL TOTAL D0'!$C$3:$C$1991,"")} -> 93462.28
A50: BTG | B50: Aline Lordes Saliba | C50: 005009992 | D50: Voga | E50: DF | F50: Yasmin Maia Muniz Xavier | G50: =IFS($BS$4:$BS$1280<=250000,"David",$BS$4:$BS$1280<=800000,"Gabriel", $BS$4:$BS$1280>800000,"Marcus") -> Gabriel | H50: Ativo | I50: ------ | J50: =IF(Q50=0,"Não","Sim") -> Não | K50: 45208 | M50: EQT | N50: 0.025 | O50: IBOVESPA | P50: 0.2 | S50: PF | T50: 015.243.891-29 | U50: 61981288180 | V50: dra.saliba@gmail.com | W50: 31384 | X50: DF | Y50: =IFS(H:H="Encerrado","Encerrado",COUNTBLANK(AZ50:BK50)>0,"Ativo",SUM(AZ50:BK50)=0,"Inativo",SUM(AZ50:BK50)>0,"Ativo") -> Ativo | AB50: Qualificado | AD50: 45208 | AE50: 49075100011109 | AQ50: 300618.08 | AR50: 330730.58 | AS50: 374414.13 | AT50: 391992.13 | AU50: 367539.74 | AV50: 373189.29 | AW50: 378431.57 | AX50: 356940.29 | AY50: 345480.6 | AZ50: 346058.8 | BA50: 354935.5 | BB50: 363207.4 | BC50: 356007.5 | BD50: 340611.3 | BE50: 327526.99 | BF50: 318070.97 | BG50: 327732.07 | BH50: 330646.43 | BI50: 338416.11 | BJ50: 328764.76 | BK50: 342146.63 | BL50: 347143.03 | BM50: 339310.03 | BN50: 349552.7 | BO50: 358027.37 | BP50: 363755.9 | BQ50: 382861.3 | BR50: 392681.4 | BS50: 427745.78 | BT50: 443423.5 | BU50: 438294.9 | BV50: 438537.6 | BW50: 415434.5 | BX50: 420711.81 | BY50: {=XLOOKUP(C50,'PL TOTAL D0'!$A$3:$A$1991,'PL TOTAL D0'!$C$3:$C$1991,"")} -> 420484.85
A51: BTG | B51: Alinne Bezerra Campos do Vale | C51: 004381194 | D51: Bluemetrix | E51: GO | F51: Hugo Motta | G51: =IFS($BS$4:$BS$1280<=250000,"David",$BS$4:$BS$1280<=800000,"Gabriel", $BS$4:$BS$1280>800000,"Marcus") -> David | H51: Inativo | I51: Sem Saldo | J51: =IF(Q51=0,"Não","Sim") -> Não | K51: 45013 | M51: INC | N51: 0.012 | O51: ------ | P51: 0 | S51: PF | T51: 009.571.921-00 | U51: 61999879817 | V51: jpaulo.mv@gmail.com | W51: 32279 | X51: DF | Y51: =IFS(H:H="Encerrado","Encerrado",COUNTBLANK(AZ51:BK51)>0,"Ativo",SUM(AZ51:BK51)=0,"Inativo",SUM(AZ51:BK51)>0,"Ativo") -> Ativo | AB51: Qualificado | AD51: 45013 | AE51: 49075100007136 | AK51: 82017.27 | AL51: 82865.36 | AM51: 83869.63 | AN51: 83223.64 | AO51: 84064.34 | AP51: 85059.73 | AQ51: 85685.59 | AR51: 86280.89 | AS51: 66767.77 | AT51: 67319.42 | AU51: 67963.36 | AV51: 68519.33 | AW51: 69098.44 | AX51: 69719.36 | AY51: 70283.63 | AZ51: 69800.56 | BA51: 70388.91 | BB51: 70945.45 | BC51: 30169.58 | BD51: 30086.72 | BE51: 30207.47 | BF51: 30401.47 | BG51: 30690.18 | BH51: 0 | BI51: 0.76 | BJ51: 0.76 | BK51: 0.76 | BL51: 0.76 | BM51: 0.76 | BN51: 0.76 | BO51: 0.76 | BP51: 0.76 | BQ51: 0.76 | BR51: 0.76 | BS51: 0.76 | BT51: 0.76 | BU51: 0.76 | BV51: 0.76 | BW51: 0.76 | BX51: 0.76 | BY51: {=XLOOKUP(C51,'PL TOTAL D0'!$A$3:$A$1991,'PL TOTAL D0'!$C$3:$C$1991,"")}
A52: BTG | B52: Aloisio Oliveira Nassau | C52: 005870700 | D52: Bluemetrix | E52: DF | F52: Matheus Vilar | G52: =IFS($BS$4:$BS$1280<=250000,"David",$BS$4:$BS$1280<=800000,"Gabriel", $BS$4:$BS$1280>800000,"Marcus") -> David | H52: Encerrado | I52: ------ | J52: =IF(Q52=0,"Não","Sim") -> Não | K52: 45498 | L52: 45771 | M52: INC | N52: 0.012 | O52: ------ | P52: 0 | S52: PF | T52: 369.493.536-34 | X52: DF | Y52: =IFS(H:H="Encerrado","Encerrado",COUNTBLANK(AZ52:BK52)>0,"Ativo",SUM(AZ52:BK52)=0,"Inativo",SUM(AZ52:BK52)>0,"Ativo") -> Encerrado | AA52: Conservador | AB52: Qualificado | AD52: 45498 | AE52: 49075100015465 | BA52: 100133.4 | BB52: 131281.05 | BC52: 151363.49 | BD52: 152846.4 | BE52: 0 | BF52: 0 | BG52: 0 | BH52: 0 | BI52: 0 | BJ52: 0 | BK52: 0 | BL52: 0 | BM52: 0 | BN52: 0 | BO52: 0 | BP52: 0 | BQ52: 0 | BR52: 0 | BS52: 0 | BT52: 0 | BU52: 0 | BV52: 0 | BW52: 0 | BX52: 0 | BY52: {=XLOOKUP(C52,'PL TOTAL D0'!$A$3:$A$1991,'PL TOTAL D0'!$C$3:$C$1991,"")}
A53: BTG | B53: Alphasitio Incorporacoes Ltda | C53: 005305448 | D53: Voga | E53: DF | F53: Theo Ramos Moutinho | G53: =IFS($BS$4:$BS$1280<=250000,"David",$BS$4:$BS$1280<=800000,"Gabriel", $BS$4:$BS$1280>800000,"Marcus") -> David | H53: Encerrado | I53: ------ | J53: Não | K53: 45355 | L53: 45513 | M53: CON/ COADM | N53: 0.01 | O53: CDI | P53: 0.1 | R53: Cliente solicitou troca de assessoria | S53: PJ | T53: 04.229.856/0001-94 | X53: SP | Y53: =IFS(H:H="Encerrado","Encerrado",COUNTBLANK(AZ53:BK53)>0,"Ativo",SUM(AZ53:BK53)=0,"Inativo",SUM(AZ53:BK53)>0,"Ativo") -> Encerrado | AD53: 45355 | AE53: 49075100013942 | AX53: 3006379.4 | AY53: 3019379 | AZ53: 7063776 | BA53: 0 | BB53: 0 | BC53: 0 | BD53: 0 | BE53: 0 | BF53: 0 | BG53: 0 | BH53: 0 | BI53: 0 | BJ53: 0 | BK53: 0 | BL53: 0 | BM53: 0 | BN53: 0 | BO53: 0 | BP53: 0 | BQ53: 0 | BR53: 0 | BS53: 0 | BT53: 0 | BU53: 0 | BV53: 0 | BW53: 0 | BX53: 0 | BY53: {=XLOOKUP(C53,'PL TOTAL D0'!$A$3:$A$1991,'PL TOTAL D0'!$C$3:$C$1991,"")}
A54: BTG | B54: Alraha Alhanna | C54: 022322002 | D54: Bluemetrix | E54: DF | F54: Thiago Canabrava | G54: =IFS($BS$4:$BS$1280<=250000,"David",$BS$4:$BS$1280<=800000,"Gabriel", $BS$4:$BS$1280>800000,"Marcus") -> David | H54: Ativo | I54: ------ | J54: Não | K54: 46077 | M54: INC | N54: 0.012 | O54: ------ | P54: 0 | S54: PF | T54: 705.476.741-12 | U54: 61 98144-3230 | V54: alraha.gov.uae@gmail.com | W54: 38746 | X54: DF | Y54: =IFS(H:H="Encerrado","Encerrado",COUNTBLANK(AZ54:BK54)>0,"Ativo",SUM(AZ54:BK54)=0,"Inativo",SUM(AZ54:BK54)>0,"Ativo") -> Ativo | AA54: Conservador | BT54: 0 | BU54: 0 | BV54: 0 | BW54: 0 | BX54: 0 | BY54: {=XLOOKUP(C54,'PL TOTAL D0'!$A$3:$A$1991,'PL TOTAL D0'!$C$3:$C$1991,"")}
A55: BTG | B55: Aluisio Ferreira Coelho | C55: 008510608 | D55: Expert | E55: GO | F55: André de Queiroz Coelho | G55: =IFS($BS$4:$BS$1280<=250000,"David",$BS$4:$BS$1280<=800000,"Gabriel", $BS$4:$BS$1280>800000,"Marcus") -> Gabriel | H55: Ativo | I55: ------ | J55: Não | K55: 45728 | M55: MOD | N55: 0.015 | O55: CDI | P55: 0.1 | S55: PF | T55: 153.689.041-34 | U55: 5562984052232 | V55: aluisiofcoelho@yahoo.com.br | W55: 20384 | X55: GO | Y55: =IFS(H:H="Encerrado","Encerrado",COUNTBLANK(AZ55:BK55)>0,"Ativo",SUM(AZ55:BK55)=0,"Inativo",SUM(AZ55:BK55)>0,"Ativo") -> Ativo | AA55: Arrojado | AD55: 45729 | AE55: 49075100018383 | BI55: 276112.88 | BJ55: 292854.18 | BK55: 308138.27 | BL55: 311388.02 | BM55: 313977.77 | BN55: 316957.4 | BO55: 321034.28 | BP55: 325050.1 | BQ55: 330790.5 | BR55: 333754.1 | BS55: 339825.33 | BT55: 443486.1 | BU55: 446225.3 | BV55: 449531.8 | BW55: 444030.9 | BX55: 459224.23 | BY55: {=XLOOKUP(C55,'PL TOTAL D0'!$A$3:$A$1991,'PL TOTAL D0'!$C$3:$C$1991,"")} -> 453657.36
A56: BTG | B56: Ama Patrimonial Ltda | C56: 022854384 | D56: Bluemetrix | E56: DF | F56: Gustavo Amorim | G56: =IFS($BS$4:$BS$1280<=250000,"David",$BS$4:$BS$1280<=800000,"Gabriel", $BS$4:$BS$1280>800000,"Marcus") -> David | H56: Ativo | I56: ------ | J56: Não | K56: 46093 | M56: CORP | N56: 0.003 | O56: ------ | P56: 0 | S56: PF | T56: 64.019.118/0001-44 | U56: 61 98220-7887 | V56: ama.patrimonial@hotmail.com | W56: 46001 | X56: DF | Y56: =IFS(H:H="Encerrado","Encerrado",COUNTBLANK(AZ56:BK56)>0,"Ativo",SUM(AZ56:BK56)=0,"Inativo",SUM(AZ56:BK56)>0,"Ativo") -> Ativo | AA56: Conservador | AD56: 46203 | BU56: 50000 | BV56: 50000 | BW56: 50313.46 | BX56: 101035.81 | BY56: {=XLOOKUP(C56,'PL TOTAL D0'!$A$3:$A$1991,'PL TOTAL D0'!$C$3:$C$1991,"")} -> 132469.35
A57: BTG | B57: Amado da Costa e Silva e/ou Helena Maria Machado da Costa e Silva | C57: 004204255 | D57: Voga | E57: DF | F57: Lucio Guimaraes Moscareli | G57: =IFS($BS$4:$BS$1280<=250000,"David",$BS$4:$BS$1280<=800000,"Gabriel", $BS$4:$BS$1280>800000,"Marcus") -> David | H57: Inativo | I57: Sem Saldo | J57: =IF(Q57=0,"Não","Sim") -> Não | K57: 44973 | M57: MOD | N57: 0.02 | O57: CDI | P57: 0.2 | S57: PF | T57: 377.012.237-20 | U57: 5561996624638 | V57: acossil51@gmail.com | W57: 18708 | X57: DF | Y57: =IFS(H:H="Encerrado","Encerrado",COUNTBLANK(AZ57:BK57)>0,"Ativo",SUM(AZ57:BK57)=0,"Inativo",SUM(AZ57:BK57)>0,"Ativo") -> Ativo | AB57: Qualificado | AD57: 44973 | AE57: 49075100011117 | AI57: 0 | AJ57: 40303.5 | AK57: 68939.38 | AL57: 69815.35 | AM57: 107537.03 | AN57: 108917.8 | AO57: 109573.66 | AP57: 109854.09 | AQ57: 17.86 | AR57: 17.86 | AS57: 17.86 | AT57: 17.86 | AU57: 17.86 | AV57: 18.77 | AW57: 18.77 | AX57: 18.77 | AY57: 18.77 | AZ57: 18.77 | BA57: 18.77 | BB57: 18.77 | BC57: 18.77 | BD57: 18.77 | BE57: 18.77 | BF57: 18.77 | BG57: 18.77 | BH57: 18.77 | BI57: 18.77 | BJ57: 0 | BK57: 0 | BL57: 0 | BM57: 0 | BN57: 0 | BO57: 0 | BP57: 0 | BQ57: 0 | BR57: 0 | BS57: 0 | BT57: 0 | BU57: 0 | BV57: 0 | BW57: 0 | BX57: 0 | BY57: {=XLOOKUP(C57,'PL TOTAL D0'!$A$3:$A$1991,'PL TOTAL D0'!$C$3:$C$1991,"")}
A58: BTG | B58: Ana Beatriz Dupré Silva | C58: 005198093 | D58: Bluemetrix | E58: DF | F58: Thiago Canabrava | G58: =IFS($BS$4:$BS$1280<=250000,"David",$BS$4:$BS$1280<=800000,"Gabriel", $BS$4:$BS$1280>800000,"Marcus") -> Marcus | H58: Ativo | I58: ------ | J58: =IF(Q58=0,"Não","Sim") -> Não | K58: 45301 | M58: MOD | N58: 0.015 | O58: ------ | P58: 0 | S58: PF | T58: 316.535.961-04 | U58: 61999115995 | V58: beatriz.dupre@gmail.com | W58: 23776 | X58: TO | Y58: =IFS(H:H="Encerrado","Encerrado",COUNTBLANK(AZ58:BK58)>0,"Ativo",SUM(AZ58:BK58)=0,"Inativo",SUM(AZ58:BK58)>0,"Ativo") -> Ativo | AB58: Qualificado | AD58: 45301 | AE58: 49075100013128 | AU58: 852917.92 | AV58: 861609.97 | AW58: 870146.9 | AX58: 855001.44 | AY58: 853811.2 | AZ58: 858755.8 | BA58: 871451.1 | BB58: 892575.51 | BC58: 910861.8 | BD58: 925960.25 | BE58: 922974.08 | BF58: 923486.93 | BG58: 951864.95 | BH58: 971076.46 | BI58: 963330.2 | BJ58: 974803.05 | BK58: 986144.42 | BL58: 995083.5 | BM58: 1010554.4 | BN58: 1030410 | BO58: 1064711.3 | BP58: 1072171 | BQ58: 1097177 | BR58: 1109546 | BS58: 1127391.5 | BT58: 1126197 | BU58: 1122897 | BV58: 1123286 | BW58: 1099666 | BX58: 1173971.3 | BY58: {=XLOOKUP(C58,'PL TOTAL D0'!$A$3:$A$1991,'PL TOTAL D0'!$C$3:$C$1991,"")} -> 1111750.8
A59: BTG | B59: Ana Beatriz Eloi Placido | C59: 005612639 | D59: Bluemetrix | E59: DF | F59: Vitor Pedrazzi | G59: =IFS($BS$4:$BS$1280<=250000,"David",$BS$4:$BS$1280<=800000,"Gabriel", $BS$4:$BS$1280>800000,"Marcus") -> David | H59: Inativo | I59: Monitoramento | J59: =IF(Q59=0,"Não","Sim") -> Não | K59: 45848 | M59: MONT | N59: 0 | O59: ------ | P59: 0 | S59: PF | T59: 041.544.081-51 | U59: 5561999477010 | V59: anabplacido2002@gmail.com | W59: 37507 | X59: DF | Y59: =IFS(H:H="Encerrado","Encerrado",COUNTBLANK(AZ59:BK59)>0,"Ativo",SUM(AZ59:BK59)=0,"Inativo",SUM(AZ59:BK59)>0,"Ativo") -> Ativo | AA59: Conservador | AD59: 45848 | AE59: 49075100019045 | BM59: 12170.8 | BN59: 12429.12 | BO59: 12569.8 | BP59: 12732.52 | BQ59: 12853.33 | BR59: 12996.9 | BS59: 0.86 | BT59: 1.73 | BU59: 1.73 | BV59: 1.73 | BW59: 1.73 | BX59: 0 | BY59: {=XLOOKUP(C59,'PL TOTAL D0'!$A$3:$A$1991,'PL TOTAL D0'!$C$3:$C$1991,"")}
A60: BTG | B60: Ana Carolina Domingues Vieira | C60: 008043885 | D60: Miura | E60: SUL | F60: Lucas Zambrin | G60: =IFS($BS$4:$BS$1280<=250000,"David",$BS$4:$BS$1280<=800000,"Gabriel", $BS$4:$BS$1280>800000,"Marcus") -> David | H60: Ativo | I60: ------ | J60: =IF(Q60=0,"Não","Sim") -> Sim | K60: 45736 | M60: CON | N60: 0.012 | O60: CDI | P60: 0.1 | Q60: Não comprar RV (09/06/2026) | S60: PF | T60: 367.484.628-43 | U60: 5514991285902 | V60: anadominguesadv@hotmail.com | W60: 32785 | X60: SP | Y60: =IFS(H:H="Encerrado","Encerrado",COUNTBLANK(AZ60:BK60)>0,"Ativo",SUM(AZ60:BK60)=0,"Inativo",SUM(AZ60:BK60)>0,"Ativo") -> Ativo | AA60: Conservador | AD60: 45736 | AE60: 49075100018391 | BI60: 52414.72 | BJ60: 52511.57 | BK60: 53508.2 | BL60: 53833.45 | BM60: 54372.97 | BN60: 54801.94 | BO60: 55299.27 | BP60: 55910.69 | BQ60: 71333.97 | BR60: 72017.57 | BS60: 72638.6 | BT60: 73473.6 | BU60: 74245.16 | BV60: 74969.66 | BW60: 75187.59 | BX60: 75882.18 | BY60: {=XLOOKUP(C60,'PL TOTAL D0'!$A$3:$A$1991,'PL TOTAL D0'!$C$3:$C$1991,"")} -> 76620.54
A61: BTG | B61: Ana Carolina Peixoto de Castro Martins e/ou Marcos Barroso Martins | C61: 019711183 | D61: Bluemetrix | E61: DF | F61: Thiago Canabrava | G61: =IFS($BS$4:$BS$1280<=250000,"David",$BS$4:$BS$1280<=800000,"Gabriel", $BS$4:$BS$1280>800000,"Marcus") -> David | H61: Ativo | I61: ------ | J61: =IF(Q61=0,"Não","Sim") -> Não | K61: 46014 | M61: CON | N61: 0.012 | O61: CDI | P61: 0.1 | S61: PF | T61: 809.511.121-04 | U61: 61 99282-0344 | V61: carol.castro76@gmail.com | W61: 27818 | X61: DF | Y61: =IFS(H:H="Encerrado","Encerrado",COUNTBLANK(AZ61:BK61)>0,"Ativo",SUM(AZ61:BK61)=0,"Inativo",SUM(AZ61:BK61)>0,"Ativo") -> Ativo | AA61: Moderado | AD61: 46203 | BR61: 0 | BS61: 64454.01 | BT61: 551037.5 | BU61: 577237.5 | BV61: 616809.6 | BW61: 913467.3 | BX61: 1002519.5 | BY61: {=XLOOKUP(C61,'PL TOTAL D0'!$A$3:$A$1991,'PL TOTAL D0'!$C$3:$C$1991,"")} -> 1015435.1
A62: BTG | B62: Ana Carolina Rabelo Soares | C62: 018962431 | D62: Bluemetrix | E62: DF | F62: Alexia Satyro | G62: =IFS($BS$4:$BS$1280<=250000,"David",$BS$4:$BS$1280<=800000,"Gabriel", $BS$4:$BS$1280>800000,"Marcus") -> David | H62: Ativo | I62: ------ | J62: =IF(Q62=0,"Não","Sim") -> Não | K62: 45995 | M62: FUND | N62: 0.007 | O62: ------ | P62: 0 | S62: PF | T62: 053.361.071-07 | U62: 61 98510-1821 | V62: carolinarabelotv@gmail.com | W62: 34834 | X62: DF | Y62: =IFS(H:H="Encerrado","Encerrado",COUNTBLANK(AZ62:BK62)>0,"Ativo",SUM(AZ62:BK62)=0,"Inativo",SUM(AZ62:BK62)>0,"Ativo") -> Ativo | AA62: Moderado | AD62: 46203 | BR62: 0 | BS62: 1000 | BT62: 4017.4 | BU62: 5078.04 | BV62: 48317.39 | BW62: 50835.14 | BX62: 51359.33 | BY62: {=XLOOKUP(C62,'PL TOTAL D0'!$A$3:$A$1991,'PL TOTAL D0'!$C$3:$C$1991,"")} -> 51676.5
A63: BTG | B63: Ana Carolina Rodeguer Ruiz | C63: 003107135 | D63: Solution For Life | E63: GO | F63: Marcelo Franciscon | G63: =IFS($BS$4:$BS$1280<=250000,"David",$BS$4:$BS$1280<=800000,"Gabriel", $BS$4:$BS$1280>800000,"Marcus") -> David | H63: Encerrado | I63: ------ | J63: =IF(Q63=0,"Não","Sim") -> Não | K63: 45652 | L63: 45937 | M63: INC | N63: 0.012 | O63: ------ | P63: 0 | S63: PF | T63: 293.652.378-82 | X63: SP | Y63: =IFS(H:H="Encerrado","Encerrado",COUNTBLANK(AZ63:BK63)>0,"Ativo",SUM(AZ63:BK63)=0,"Inativo",SUM(AZ63:BK63)>0,"Ativo") -> Encerrado | AA63: Conservador | AD63: 45652 | AE63: 49075100016445 | BF63: 820.03 | BG63: 204261.72 | BH63: 206021.05 | BI63: 155957.66 | BJ63: 157524.62 | BK63: 159184.81 | BL63: 140354.69 | BM63: 0 | BN63: 0 | BO63: 0 | BP63: 0 | BQ63: 0 | BR63: 0 | BS63: 0 | BT63: 0 | BU63: 0 | BV63: 0 | BW63: 0 | BX63: 0 | BY63: {=XLOOKUP(C63,'PL TOTAL D0'!$A$3:$A$1991,'PL TOTAL D0'!$C$3:$C$1991,"")}
A64: BTG | B64: Ana Clara Costa Alves | C64: 004267119 | D64: Bluemetrix | E64: GO | F64: Vivian | G64: =IFS($BS$4:$BS$1280<=250000,"David",$BS$4:$BS$1280<=800000,"Gabriel", $BS$4:$BS$1280>800000,"Marcus") -> David | H64: Encerrado | I64: ------ | J64: =IF(Q64=0,"Não","Sim") -> Não | K64: 44938 | L64: 45980 | M64: INC | N64: 0.012 | O64: ------ | P64: 0 | R64: Distrato unilatera | S64: PF | T64: 039.630.741-83 | X64: GO | Y64: =IFS(H:H="Encerrado","Encerrado",COUNTBLANK(AZ64:BK64)>0,"Ativo",SUM(AZ64:BK64)=0,"Inativo",SUM(AZ64:BK64)>0,"Ativo") -> Encerrado | AB64: Não Qualificado | AD64: 44938 | AE64: 49075100003661 | AI64: 108567.08 | AJ64: 109412.19 | AK64: 110591.27 | AL64: 131524.98 | AM64: 117722.06 | AN64: 118731.32 | AO64: 139849.87 | AP64: 141196.37 | AQ64: 162330.96 | AR64: 163717.89 | AS64: 154515.38 | AT64: 155660.59 | AU64: 156763.01 | AV64: 167964.34 | AW64: 169309.23 | AX64: 170521.51 | AY64: 171729.8 | AZ64: 162558.9 | BA64: 163460 | BB64: 164847.32 | BC64: 165531.13 | BD64: 166964.72 | BE64: 158116.79 | BF64: 117889.01 | BG64: 46451.27 | BH64: 31386.27 | BI64: 31665.17 | BJ64: 11569.32 | BK64: 11679.92 | BL64: 16812.41 | BM64: 0 | BN64: 0 | BO64: 0 | BP64: 0 | BQ64: 0 | BR64: 0 | BS64: 0 | BT64: 0 | BU64: 0 | BV64: 0 | BW64: 0 | BX64: 0 | BY64: {=XLOOKUP(C64,'PL TOTAL D0'!$A$3:$A$1991,'PL TOTAL D0'!$C$3:$C$1991,"")}
A65: BTG | B65: Ana Clara Montanini Rezende | C65: 005110894 | D65: Bluemetrix | E65: GO | F65: Felipe Rios | G65: =IFS($BS$4:$BS$1280<=250000,"David",$BS$4:$BS$1280<=800000,"Gabriel", $BS$4:$BS$1280>800000,"Marcus") -> David | H65: Inativo | I65: Sem Saldo | J65: =IF(Q65=0,"Não","Sim") -> Não | K65: 45247 | M65: INC | N65: 0.012 | O65: ------ | P65: 0 | S65: PF | T65: 026.399.361-23 | U65: 5562999982702 | V65: claramontanini@hotmail.com | W65: 35632 | X65: GO | Y65: =IFS(H:H="Encerrado","Encerrado",COUNTBLANK(AZ65:BK65)>0,"Ativo",SUM(AZ65:BK65)=0,"Inativo",SUM(AZ65:BK65)>0,"Ativo") -> Ativo | AB65: Qualificado | AD65: 45247 | AE65: 49075100012164 | AS65: 0 | AT65: 0 | AU65: 0 | AV65: 0 | AW65: 0 | AX65: 0 | AY65: 0 | AZ65: 0 | BA65: 0 | BB65: 0 | BC65: 0 | BD65: 0 | BE65: 0 | BF65: 60026.7 | BG65: 110840.99 | BH65: 172477.54 | BI65: 174186.57 | BJ65: 185648.17 | BK65: 187144.73 | BL65: 0 | BM65: 1.56 | BN65: 1.56 | BO65: 1.56 | BP65: 1.56 | BQ65: 30033.52 | BR65: 30397.46 | BS65: 1.64 | BT65: 0.6 | BU65: 0.6 | BV65: 0.6 | BW65: 0.6 | BX65: 0.6 | BY65: {=XLOOKUP(C65,'PL TOTAL D0'!$A$3:$A$1991,'PL TOTAL D0'!$C$3:$C$1991,"")}
A66: BTG | B66: Ana Clara Ramos Fischer | C66: 005340051 | D66: Voga | E66: DF | F66: Theo Ramos Moutinho | G66: =IFS($BS$4:$BS$1280<=250000,"David",$BS$4:$BS$1280<=800000,"Gabriel", $BS$4:$BS$1280>800000,"Marcus") -> David | H66: Encerrado | I66: ------ | J66: =IF(Q66=0,"Não","Sim") -> Não | K66: 45383 | L66: 45527 | M66: MONT | N66: 0 | O66: ------ | P66: 0 | S66: PF | T66: 196.586.447-32 | X66: DF | Y66: =IFS(H:H="Encerrado","Encerrado",COUNTBLANK(AZ66:BK66)>0,"Ativo",SUM(AZ66:BK66)=0,"Inativo",SUM(AZ66:BK66)>0,"Ativo") -> Encerrado | AD66: 45383 | AE66: 49075100014000 | AW66: 450.54 | AX66: 454.49 | AY66: 457.01 | AZ66: 460.58 | BA66: 0 | BB66: 0 | BC66: 0 | BD66: 0 | BE66: 0 | BF66: 0 | BG66: 0 | BH66: 0 | BI66: 0 | BJ66: 0 | BK66: 0 | BL66: 0 | BM66: 0 | BN66: 0 | BO66: 0 | BP66: 0 | BQ66: 0 | BR66: 0 | BS66: 0 | BT66: 0 | BU66: 0 | BV66: 0 | BW66: 0 | BX66: 0 | BY66: {=XLOOKUP(C66,'PL TOTAL D0'!$A$3:$A$1991,'PL TOTAL D0'!$C$3:$C$1991,"")}
A67: BTG | B67: Ana Claudia de Souza Morais | C67: 011319423 | D67: Expert | E67: GO | F67: Paula Bonfim | G67: =IFS($BS$4:$BS$1280<=250000,"David",$BS$4:$BS$1280<=800000,"Gabriel", $BS$4:$BS$1280>800000,"Marcus") -> David | H67: Ativo | I67: ------ | J67: =IF(Q67=0,"Não","Sim") -> Sim | K67: 46083 | M67: INC | N67: 0.012 | O67: ------ | P67: 0 | Q67: 100k D+0, Venc. Máx 02/2028 (05/03/2026) | S67: PF | T67: 730.464.421-49 | U67: 62 99298-0004 | V67: anaclaudiamorais@outlook.com | W67: 31613 | X67: GO | Y67: =IFS(H:H="Encerrado","Encerrado",COUNTBLANK(AZ67:BK67)>0,"Ativo",SUM(AZ67:BK67)=0,"Inativo",SUM(AZ67:BK67)>0,"Ativo") -> Ativo | AA67: Conservador | AD67: 46203 | BT67: #N/D | BU67: 353606.5 | BV67: 357585.8 | BW67: 360739.9 | BX67: 364205.47 | BY67: {=XLOOKUP(C67,'PL TOTAL D0'!$A$3:$A$1991,'PL TOTAL D0'!$C$3:$C$1991,"")} -> 368310.4
A68: BTG | B68: Ana Cristina Cardeal Pereira | C68: 005032151 | D68: Miura | E68: SUL | F68: Lucas Zambrin | G68: =IFS($BS$4:$BS$1280<=250000,"David",$BS$4:$BS$1280<=800000,"Gabriel", $BS$4:$BS$1280>800000,"Marcus") -> David | H68: Encerrado | I68: ------ | J68: =IF(Q68=0,"Não","Sim") -> Não | K68: 45203 | L68: 45764 | M68: INC | N68: 0.012 | O68: ------ | P68: 0 | S68: PF | T68: 072.640.228-11 | X68: PR | Y68: =IFS(H:H="Encerrado","Encerrado",COUNTBLANK(AZ68:BK68)>0,"Ativo",SUM(AZ68:BK68)=0,"Inativo",SUM(AZ68:BK68)>0,"Ativo") -> Encerrado | AB68: Qualificado | AD68: 45203 | AE68: 49075100011125 | AQ68: 0 | AR68: 0 | AS68: 10072.32 | AT68: 20154.5 | AU68: 20328.42 | AV68: 20490.56 | AW68: 20653.07 | AX68: 20796.53 | AY68: 20931.7 | AZ68: 21081.77 | BA68: 21242.82 | BB68: 21395.16 | BC68: 21534.01 | BD68: 0 | BE68: 0 | BF68: 0 | BG68: 0 | BH68: 0 | BI68: 0 | BJ68: 0 | BK68: 0 | BL68: 0 | BM68: 0 | BN68: 0 | BO68: 0 | BP68: 0 | BQ68: 0 | BR68: 0 | BS68: 0 | BT68: 0 | BU68: 0 | BV68: 0 | BW68: 0 | BX68: 0 | BY68: {=XLOOKUP(C68,'PL TOTAL D0'!$A$3:$A$1991,'PL TOTAL D0'!$C$3:$C$1991,"")}
A69: BTG | B69: Ana de Moura Jorge | C69: 002480985 | D69: Bluemetrix | E69: DF | F69: Matheus Vilar | G69: =IFS($BS$4:$BS$1280<=250000,"David",$BS$4:$BS$1280<=800000,"Gabriel", $BS$4:$BS$1280>800000,"Marcus") -> David | H69: Encerrado | I69: ------ | J69: =IF(R69=0,"Não","Sim") -> Sim | K69: 45042 | L69: 45449 | M69: INC | N69: 0.01 | O69: ------ | P69: 0 | R69: Cliente sumiu da base | S69: PF | T69: 053.492.086-16 | X69: DF | Y69: =IFS(H:H="Encerrado","Encerrado",COUNTBLANK(AZ69:BK69)>0,"Ativo",SUM(AZ69:BK69)=0,"Inativo",SUM(AZ69:BK69)>0,"Ativo") -> Encerrado | AB69: Qualificado | AD69: 45042 | AE69: 49075100011133 | AL69: 1684755.3 | AM69: 1644341.4 | AN69: 1637940.5 | AO69: 0 | AP69: 0 | AQ69: 0 | AR69: 0 | AS69: 0 | AT69: 0 | AU69: 0 | AV69: 0 | AW69: 0 | AX69: 0 | AY69: 0 | AZ69: 0 | BA69: 0 | BB69: 0 | BC69: 0 | BD69: 0 | BE69: 0 | BF69: 0 | BG69: 0 | BH69: 0 | BI69: 0 | BJ69: 0 | BK69: 0 | BL69: 0 | BM69: 0 | BN69: 0 | BO69: 0 | BP69: 0 | BQ69: 0 | BR69: 0 | BS69: 0 | BT69: 0 | BU69: 0 | BV69: 0 | BW69: 0 | BX69: 0 | BY69: {=XLOOKUP(C69,'PL TOTAL D0'!$A$3:$A$1991,'PL TOTAL D0'!$C$3:$C$1991,"")}
A70: BTG | B70: Ana Ferreira dos Santos Correia | C70: 008012870 | D70: Bluemetrix | E70: DF | F70: Bruno Henrique | G70: =IFS($BS$4:$BS$1280<=250000,"David",$BS$4:$BS$1280<=800000,"Gabriel", $BS$4:$BS$1280>800000,"Marcus") -> David | H70: Inativo | I70: Monitoramento | J70: =IF(R70=0,"Não","Sim") -> Não | K70: 45580 | M70: MONT | N70: 0.003 | O70: ------ | P70: 0 | Q70: Carteira Monitoramento Especial para Fundos (SPMG II FII criado pelo cliente) | S70: PF | T70: 852.587.336-53 | U70: 31999447575 | V70: anaferreirasantoscorreia@gmail.com | W70: 20859 | X70: MG | Y70: =IFS(H:H="Encerrado","Encerrado",COUNTBLANK(AZ70:BK70)>0,"Ativo",SUM(AZ70:BK70)=0,"Inativo",SUM(AZ70:BK70)>0,"Ativo") -> Ativo | AA70: Moderado | AD70: 45580 | AE70: 49075100016003 | BD70: 4.3 | BE70: 63754.61 | BF70: 7.74 | BG70: 0.92 | BH70: 0.83 | BI70: 0.9 | BJ70: 0.92 | BK70: 1.32 | BL70: 1.32 | BM70: 1.35 | BN70: 1.36 | BO70: 1.36 | BP70: 1.36 | BQ70: 1.36 | BR70: 1.36 | BS70: 1.36 | BT70: 1.36 | BU70: 1.36 | BV70: 1.36 | BW70: 1.36 | BX70: 1.36 | BY70: {=XLOOKUP(C70,'PL TOTAL D0'!$A$3:$A$1991,'PL TOTAL D0'!$C$3:$C$1991,"")}
A71: BTG | B71: Ana Lucia Dos Santos Nakadomari | C71: 005165116 | D71: Miura | E71: SUL | F71: Rodrigo Milanez | G71: =IFS($BS$4:$BS$1280<=250000,"David",$BS$4:$BS$1280<=800000,"Gabriel", $BS$4:$BS$1280>800000,"Marcus") -> David | H71: Ativo | I71: ------ | J71: =IF(Q71=0,"Não","Sim") -> Sim | K71: 45279 | M71: INC | N71: 0.012 | O71: CDI | P71: 0.1 | Q71: 19k D+0 (15/12/2025) | R71: STVM de entrada da Guide finalizada (03/01/2024) | S71: PF | T71: 572.215.459-87 | U71: 5543999985851 | V71: analucia.sn73@gmail.com | W71: 23808 | X71: PR | Y71: =IFS(H:H="Encerrado","Encerrado",COUNTBLANK(AZ71:BK71)>0,"Ativo",SUM(AZ71:BK71)=0,"Inativo",SUM(AZ71:BK71)>0,"Ativo") -> Ativo | AB71: Qualificado | AD71: 45279 | AE71: 49075100012911 | AT71: 0 | AU71: 157121.73 | AV71: 158173.05 | AW71: 158825.91 | AX71: 160025.75 | AY71: 161160.4 | AZ71: 162345.4 | BA71: 163296.8 | BB71: 164602.91 | BC71: 165708.53 | BD71: 167128.36 | BE71: 168293.65 | BF71: 169173.05 | BG71: 165006.43 | BH71: 161193.94 | BI71: 162468.97 | BJ71: 161793.22 | BK71: 163520.17 | BL71: 164584.73 | BM71: 166330.99 | BN71: 167954.9 | BO71: 163437.36 | BP71: 157562.3 | BQ71: 155815.6 | BR71: 174346.6 | BS71: 173483.02 | BT71: 169882.5 | BU71: 171454.6 | BV71: 173359.5 | BW71: 171935.9 | BX71: 173549.83 | BY71: {=XLOOKUP(C71,'PL TOTAL D0'!$A$3:$A$1991,'PL TOTAL D0'!$C$3:$C$1991,"")} -> 174724.2
A72: BTG | B72: Ana Lucia Falavigna Guilherme | C72: 004479287 | D72: Miura | E72: SUL | F72: Rodrigo Milanez | G72: =IFS($BS$4:$BS$1280<=250000,"David",$BS$4:$BS$1280<=800000,"Gabriel", $BS$4:$BS$1280>800000,"Marcus") -> Gabriel | H72: Ativo | I72: ------ | J72: =IF(Q72=0,"Não","Sim") -> Não | K72: 45027 | M72: INC CP | N72: 0.012 | O72: ------ | P72: 0 | S72: PF | T72: 530.206.939-34 | U72: 5544999926511 | V72: alfalavignauem@gmail.com | W72: 22196 | X72: PR | Y72: =IFS(H:H="Encerrado","Encerrado",COUNTBLANK(AZ72:BK72)>0,"Ativo",SUM(AZ72:BK72)=0,"Inativo",SUM(AZ72:BK72)>0,"Ativo") -> Ativo | AA72: Moderado | AB72: Qualificado | AD72: 45027 | AE72: 49075100012172 | AK72: 0 | AL72: 194185.85 | AM72: 461665.96 | AN72: 473644.04 | AO72: 276192.79 | AP72: 274251.9 | AQ72: 276050.98 | AR72: 276097.3 | AS72: 282389.02 | AT72: 287907.38 | AU72: 283734.05 | AV72: 286191.43 | AW72: 540494.52 | AX72: 465561.03 | AY72: 704252.2 | AZ72: 708956.3 | BA72: 717389.2 | BB72: 724415.59 | BC72: 744957.57 | BD72: 711517.98 | BE72: 726221.86 | BF72: 705318.2 | BG72: 715298.64 | BH72: 733245.12 | BI72: 741997.66 | BJ72: 714657.39 | BK72: 722202.06 | BL72: 728303.57 | BM72: 747775.16 | BN72: 755172.7 | BO72: 249766.71 | BP72: 321812.9 | BQ72: 324848.5 | BR72: 328278.1 | BS72: 331631.37 | BT72: 334461.5 | BU72: 338465.7 | BV72: 137973.9 | BW72: 139575.4 | BX72: 140924.1 | BY72: {=XLOOKUP(C72,'PL TOTAL D0'!$A$3:$A$1991,'PL TOTAL D0'!$C$3:$C$1991,"")} -> 142790.17
A73: BTG | B73: Ana Lucia Falavigna Guilherme | C73: 004444164 | D73: Miura | E73: SUL | F73: Rodrigo Milanez | G73: =IFS($BS$4:$BS$1280<=250000,"David",$BS$4:$BS$1280<=800000,"Gabriel", $BS$4:$BS$1280>800000,"Marcus") -> David | H73: Encerrado | I73: ------ | J73: =IF(Q73=0,"Não","Sim") -> Não | K73: 44998 | L73: 45980 | M73: INC | N73: 0.012 | O73: ------ | P73: 0 | S73: PF | T73: 530.206.939-34 | U73: 5544999926511 | V73: alfalavignauem@gmail.com | W73: 22196 | X73: PR | Y73: =IFS(H:H="Encerrado","Encerrado",COUNTBLANK(AZ73:BK73)>0,"Ativo",SUM(AZ73:BK73)=0,"Inativo",SUM(AZ73:BK73)>0,"Ativo") -> Encerrado | AB73: Qualificado | AD73: 44998 | AE73: 49075100008647 | AK73: 3571441.6 | AL73: 3908519.5 | AM73: 3182425.3 | AN73: 2082493.5 | AO73: 1015957.6 | AP73: 657075.8 | AQ73: 296915.45 | AR73: 299398.27 | AS73: 99133.3 | AT73: 99661.46 | AU73: 100730.48 | AV73: 101401.17 | AW73: 0 | AX73: 0 | AY73: 0 | AZ73: 1.61 | BA73: 1.61 | BB73: 1.61 | BC73: 0 | BD73: 0 | BE73: 0 | BF73: 0 | BG73: 0 | BH73: 0 | BI73: 0 | BJ73: 0 | BK73: 0 | BL73: 0 | BM73: 0 | BN73: 0 | BO73: 0 | BP73: 0 | BQ73: 0 | BR73: 0 | BS73: 0 | BT73: 0 | BU73: 0 | BV73: 0 | BW73: 0 | BX73: 0 | BY73: {=XLOOKUP(C73,'PL TOTAL D0'!$A$3:$A$1991,'PL TOTAL D0'!$C$3:$C$1991,"")}
A74: BTG | B74: Ana Lucia Garcia Spironelli Quintiliano | C74: 004467884 | D74: Miura | E74: SUL | F74: Rodrigo Milanez | G74: =IFS($BS$4:$BS$1280<=250000,"David",$BS$4:$BS$1280<=800000,"Gabriel", $BS$4:$BS$1280>800000,"Marcus") -> David | H74: Ativo | I74: ------ | J74: =IF(Q74=0,"Não","Sim") -> Não | K74: 45020 | M74: CON | N74: 0.012 | O74: CDI | P74: 0.1 | R74: Alteração de carteira finalizada (17/01/2024) | S74: PF | T74: 274.136.108-84 | U74: 43999259245 | V74: analucia@spironelli.com.br | W74: 28881 | X74: PR | Y74: =IFS(H:H="Encerrado","Encerrado",COUNTBLANK(AZ74:BK74)>0,"Ativo",SUM(AZ74:BK74)=0,"Inativo",SUM(AZ74:BK74)>0,"Ativo") -> Ativo | AB74: Qualificado | AD74: 45020 | AE74: 49075100004544 | AK74: 0 | AL74: 60428.36 | AM74: 81126.58 | AN74: 101955.21 | AO74: 102832.14 | AP74: 103894.93 | AQ74: 104759.85 | AR74: 105447.51 | AS74: 106231.64 | AT74: 156714.47 | AU74: 158148.68 | AV74: 159430.74 | AW74: 160710.31 | AX74: 161769.12 | AY74: 161921.1 | AZ74: 162917.4 | BA74: 164692.1 | BB74: 166315.49 | BC74: 166798.85 | BD74: 166621.6 | BE74: 166830.58 | BF74: 166706.45 | BG74: 168416.58 | BH74: 169921.32 | BI74: 171748.02 | BJ74: 173593.07 | BK74: 175441.27 | BL74: 176557.9 | BM74: 178421.88 | BN74: 179998.8 | BO74: 181959.7 | BP74: 183497.1 | BQ74: 185055.1 | BR74: 186643.1 | BS74: 188726.82 | BT74: 190255.8 | BU74: 192763.3 | BV74: 194166.3 | BW74: 194867.7 | BX74: 203618.02 | BY74: {=XLOOKUP(C74,'PL TOTAL D0'!$A$3:$A$1991,'PL TOTAL D0'!$C$3:$C$1991,"")} -> 198974.48
A75: BTG | B75: Ana Luisa Araújo Barbosa | C75: 004346742 | D75: Bluemetrix | E75: GO | F75: Rafael Vilela | G75: =IFS($BS$4:$BS$1280<=250000,"David",$BS$4:$BS$1280<=800000,"Gabriel", $BS$4:$BS$1280>800000,"Marcus") -> David | H75: Inativo | I75: Sem Saldo | J75: =IF(Q75=0,"Não","Sim") -> Não | K75: 45166 | M75: INC | N75: 0.012 | O75: ------ | P75: 0 | R75: Possivel retorno futuro. | S75: PF | T75: 026.116.221-75 | U75: 5537991732003 | V75: ana.bia.barbosa@hotmail.com | W75: 32648 | X75: GO | Y75: =IFS(H:H="Encerrado","Encerrado",COUNTBLANK(AZ75:BK75)>0,"Ativo",SUM(AZ75:BK75)=0,"Inativo",SUM(AZ75:BK75)>0,"Ativo") -> Inativo | AB75: Qualificado | AD75: 45166 | AE75: 49075100011141 | AI75: 0 | AJ75: 0 | AK75: 0 | AL75: 0 | AM75: 0 | AN75: 0 | AO75: 0 | AP75: 0 | AQ75: 0 | AR75: 0 | AS75: 0 | AT75: 0 | AU75: 0 | AV75: 0 | AW75: 0 | AX75: 0 | AY75: 0 | AZ75: 0 | BA75: 0 | BB75: 0 | BC75: 0 | BD75: 0 | BE75: 0 | BF75: 0 | BG75: 0 | BH75: 0 | BI75: 0 | BJ75: 0 | BK75: 0 | BL75: 0 | BM75: 0 | BN75: 0 | BO75: 0 | BP75: 0 | BQ75: 0 | BR75: 0 | BS75: 0 | BT75: 0 | BU75: 0 | BV75: 0 | BW75: 0 | BX75: 0 | BY75: {=XLOOKUP(C75,'PL TOTAL D0'!$A$3:$A$1991,'PL TOTAL D0'!$C$3:$C$1991,"")}
A76: BTG | B76: Ana Maria Costa Campos | C76: 005009922 | D76: Miura | E76: SUL | F76: Lucas Zambrin | G76: =IFS($BS$4:$BS$1280<=250000,"David",$BS$4:$BS$1280<=800000,"Gabriel", $BS$4:$BS$1280>800000,"Marcus") -> David | H76: Ativo | I76: ------ | J76: =IF(Q76=0,"Não","Sim") -> Não | K76: 45190 | M76: INC | N76: 0.012 | O76: ------ | P76: 0 | R76: STVM de entrada da Guide finalizada (10/10/2023) | S76: PF | T76: 548.566.399-00 | U76: 43996462444 | V76: 31costacampos@gmail.com | W76: 22847 | X76: PR | Y76: =IFS(H:H="Encerrado","Encerrado",COUNTBLANK(AZ76:BK76)>0,"Ativo",SUM(AZ76:BK76)=0,"Inativo",SUM(AZ76:BK76)>0,"Ativo") -> Ativo | AB76: Qualificado | AD76: 45190 | AE76: 49075100011151 | AQ76: 0 | AR76: 67426.7 | AS76: 68192.13 | AT76: 68851.25 | AU76: 75391.26 | AV76: 75875.32 | AW76: 76475.19 | AX76: 76884.54 | AY76: 76922.19 | AZ76: 77386.57 | BA76: 77924.93 | BB76: 78469.18 | BC76: 79054.89 | BD76: 98748.6 | BE76: 99466.66 | BF76: 150430.48 | BG76: 152275.59 | BH76: 153157.24 | BI76: 175377.67 | BJ76: 52039.64 | BK76: 52543 | BL76: 53048.14 | BM76: 53617.44 | BN76: 54151.82 | BO76: 54679.43 | BP76: 55135.06 | BQ76: 55652.04 | BR76: 56174.06 | BS76: 56684.76 | BT76: 57156.15 | BU76: 57837.6 | BV76: 58507.44 | BW76: 59213.18 | BX76: 59793.77 | BY76: {=XLOOKUP(C76,'PL TOTAL D0'!$A$3:$A$1991,'PL TOTAL D0'!$C$3:$C$1991,"")} -> 64774.65
A77: BTG | B77: Ana Maria De Araujo Gouveia | C77: 004261201 | D77: Altum | E77: DF | F77: Alexandre Xavier | G77: =IFS($BS$4:$BS$1280<=250000,"David",$BS$4:$BS$1280<=800000,"Gabriel", $BS$4:$BS$1280>800000,"Marcus") -> Gabriel | H77: Ativo | I77: ------ | J77: =IF(Q77=0,"Não","Sim") -> Sim | K77: 45523 | M77: INC | N77: 0.009 | O77: ------ | P77: 0 | Q77: 10% D+0 (08/11/2024) | S77: PF | T77: 530.235.448-91 | U77: 5561999896470 | V77: anamaria.gouveia28@gmail.com | W77: 17376 | X77: DF | Y77: =IFS(H:H="Encerrado","Encerrado",COUNTBLANK(AZ77:BK77)>0,"Ativo",SUM(AZ77:BK77)=0,"Inativo",SUM(AZ77:BK77)>0,"Ativo") -> Ativo | AA77: Moderado | AB77: Qualificado | AD77: 45523 | AE77: 49075100015562 | BB77: 697441.25 | BC77: 679986.27 | BD77: 683673.45 | BE77: 689007.14 | BF77: 693620.11 | BG77: 699642.44 | BH77: 688295.02 | BI77: 694586.76 | BJ77: 720703.77 | BK77: 266750.29 | BL77: 268964.28 | BM77: 276569.97 | BN77: 279037.6 | BO77: 274475.09 | BP77: 277447.4 | BQ77: 279739.3 | BR77: 282426.1 | BS77: 285587.62 | BT77: 287742.7 | BU77: 290322.8 | BV77: 293516.2 | BW77: 296740.1 | BX77: 299967.45 | BY77: {=XLOOKUP(C77,'PL TOTAL D0'!$A$3:$A$1991,'PL TOTAL D0'!$C$3:$C$1991,"")} -> 303185.9
A78: BTG | B78: Ana Maria Falavigna Silva | C78: 004432579 | D78: Miura | E78: SUL | F78: Rodrigo Milanez | G78: =IFS($BS$4:$BS$1280<=250000,"David",$BS$4:$BS$1280<=800000,"Gabriel", $BS$4:$BS$1280>800000,"Marcus") -> Gabriel | H78: Ativo | I78: ------ | J78: =IF(Q78=0,"Não","Sim") -> Sim | K78: 45034 | M78: INC CP | N78: 0.012 | O78: ------ | P78: 0 | Q78: 300K D+0 (27/09/2024) | S78: PF | T78: 445.239.639-91 | U78: 5543999353031 | V78: manoana@sercomtel.com.br | W78: 19914 | X78: PR | Y78: =IFS(H:H="Encerrado","Encerrado",COUNTBLANK(AZ78:BK78)>0,"Ativo",SUM(AZ78:BK78)=0,"Inativo",SUM(AZ78:BK78)>0,"Ativo") -> Ativo | AA78: Moderado | AB78: Qualificado | AD78: 45034 | AE78: 49075100008345 | AK78: 0 | AL78: 2005947.4 | AM78: 2027949.5 | AN78: 1913063.2 | AO78: 1929869.9 | AP78: 1948995.5 | AQ78: 1965765.2 | AR78: 1984304.2 | AS78: 1999758.9 | AT78: 1812508.6 | AU78: 1828516.6 | AV78: 1513471 | AW78: 1485219.2 | AX78: 1439637.5 | AY78: 1449978 | AZ78: 1459640 | BA78: 1471903 | BB78: 1475210.6 | BC78: 1484970.8 | BD78: 1490495.6 | BE78: 1500780.4 | BF78: 1511084.6 | BG78: 1525920.2 | BH78: 1540477.4 | BI78: 1555980.1 | BJ78: 1573192.7 | BK78: 1603180.3 | BL78: 1615112.3 | BM78: 1632570.5 | BN78: 1648711 | BO78: 586810.07 | BP78: 508384.9 | BQ78: 512056.3 | BR78: 501161.8 | BS78: 506728.74 | BT78: 510303.4 | BU78: 515865.6 | BV78: 521223 | BW78: 524781.8 | BX78: 528595.9 | BY78: {=XLOOKUP(C78,'PL TOTAL D0'!$A$3:$A$1991,'PL TOTAL D0'!$C$3:$C$1991,"")} -> 526492.11
A79: BTG | B79: Ana Maria Pacheco Keremian | C79: 000989247 | D79: Voga | E79: DF | F79: Theo Ramos Moutinho | G79: =IFS($BS$4:$BS$1280<=250000,"David",$BS$4:$BS$1280<=800000,"Gabriel", $BS$4:$BS$1280>800000,"Marcus") -> David | H79: Encerrado | I79: ------ | J79: =IF(Q79=0,"Não","Sim") -> Não | K79: 45098 | L79: 45525 | M79: ARR | N79: 0.006 | O79: ------ | P79: 0 | R79: STVM interna finalizada (08/01/2024) / Conta será encerrada após valor em trânsito cair | S79: PF | T79: 410.422.128-72 | X79: SP | Y79: =IFS(H:H="Encerrado","Encerrado",COUNTBLANK(AZ79:BK79)>0,"Ativo",SUM(AZ79:BK79)=0,"Inativo",SUM(AZ79:BK79)>0,"Ativo") -> Encerrado | AB79: Qualificado | AD79: 45098 | AE79: 49075100003114 | AN79: 175858.96 | AO79: 394420.72 | AP79: 674215.24 | AQ79: 706487.76 | AR79: 737416.96 | AS79: 779564.59 | AT79: 791423.31 | AU79: 4701.33 | AV79: 4888.27 | AW79: 171.31 | AX79: 171.31 | AY79: 171.31 | AZ79: 171.31 | BA79: 0 | BB79: 0 | BC79: 0 | BD79: 0 | BE79: 0 | BF79: 0 | BG79: 0 | BH79: 0 | BI79: 0 | BJ79: 0 | BK79: 0 | BL79: 0 | BM79: 0 | BN79: 0 | BO79: 0 | BP79: 0 | BQ79: 0 | BR79: 0 | BS79: 0 | BT79: 0 | BU79: 0 | BV79: 0 | BW79: 0 | BX79: 0 | BY79: {=XLOOKUP(C79,'PL TOTAL D0'!$A$3:$A$1991,'PL TOTAL D0'!$C$3:$C$1991,"")}
A80: BTG | B80: Ana Maria Pacheco Keremian e/ou Theo Keremian | C80: 005190138 | D80: Voga | E80: DF | F80: Theo Ramos Moutinho | G80: =IFS($BS$4:$BS$1280<=250000,"David",$BS$4:$BS$1280<=800000,"Gabriel", $BS$4:$BS$1280>800000,"Marcus") -> David | H80: Encerrado | I80: ------ | J80: Não | K80: 45296 | L80: 45492 | M80: INC/ COADM | N80: 0.006 | O80: ------ | P80: 0 | R80: Cliente solicitou troca de assessoria (17/07/2024) | S80: PF | T80: 410.422.128-72 | X80: SP | Y80: =IFS(H:H="Encerrado","Encerrado",COUNTBLANK(AZ80:BK80)>0,"Ativo",SUM(AZ80:BK80)=0,"Inativo",SUM(AZ80:BK80)>0,"Ativo") -> Encerrado | AD80: 45296 | AE80: 49075100013551 | AU80: 788851.1 | AV80: 795557.28 | AW80: 807149.98 | AX80: 812679.39 | AY80: 826075.4 | AZ80: 832664.4 | BA80: 0 | BB80: 0 | BC80: 0 | BD80: 0 | BE80: 0 | BF80: 0 | BG80: 0 | BH80: 0 | BI80: 0 | BJ80: 0 | BK80: 0 | BL80: 0 | BM80: 0 | BN80: 0 | BO80: 0 | BP80: 0 | BQ80: 0 | BR80: 0 | BS80: 0 | BT80: 0 | BU80: 0 | BV80: 0 | BW80: 0 | BX80: 0 | BY80: {=XLOOKUP(C80,'PL TOTAL D0'!$A$3:$A$1991,'PL TOTAL D0'!$C$3:$C$1991,"")}
A81: BTG | B81: Ana Paula Herrero | C81: 008475532 | D81: Miura | E81: SUL | F81: Victor Hugo Laurentino | G81: =IFS($BS$4:$BS$1280<=250000,"David",$BS$4:$BS$1280<=800000,"Gabriel", $BS$4:$BS$1280>800000,"Marcus") -> David | H81: Inativo | I81: Alteração de C.A | J81: Não | K81: 45716 | M81: MOD | N81: 0.015 | O81: CDI | P81: 0.1 | Q81: Não comprar papeis do varejo e agro (06/03/2025) | S81: PF | T81: 066.346.839-64 | U81: 5543999226163 | V81: anapaula_herrero@hotmail.com | W81: 32365 | X81: PR | Y81: =IFS(H:H="Encerrado","Encerrado",COUNTBLANK(AZ81:BK81)>0,"Ativo",SUM(AZ81:BK81)=0,"Inativo",SUM(AZ81:BK81)>0,"Ativo") -> Ativo | AA81: Moderado | AD81: 45722 | AE81: 49075100018235 | BH81: 0 | BI81: 82908.14 | BJ81: 82110.56 | BK81: 84039.62 | BL81: 126901.85 | BM81: 128107.48 | BN81: 129475.8 | BO81: 131428.55 | BP81: 134096.2 | BQ81: 136512.9 | BR81: 139230 | BS81: 141703.06 | BT81: 143472.7 | BU81: 160978 | BV81: 156065.6 | BW81: 156135.1 | BX81: 157805.33 | BY81: {=XLOOKUP(C81,'PL TOTAL D0'!$A$3:$A$1991,'PL TOTAL D0'!$C$3:$C$1991,"")} -> 159237.64
A82: BTG | B82: Ana Paula Liogi Fidell | C82: 013773494 | D82: Miura | E82: SUL | F82: Rodrigo Milanez | G82: =IFS($BS$4:$BS$1280<=250000,"David",$BS$4:$BS$1280<=800000,"Gabriel", $BS$4:$BS$1280>800000,"Marcus") -> David | H82: Inativo | I82: Sem Saldo | J82: Não | K82: 45924 | M82: MOD | N82: 0.015 | O82: CDI | P82: 0.1 | S82: PF | T82: 020.705.179-85 | U82: 1 310-569-2236 | V82: analiogi@hotmail.com | W82: 28372 | X82: PR | Y82: =IFS(H:H="Encerrado","Encerrado",COUNTBLANK(AZ82:BK82)>0,"Ativo",SUM(AZ82:BK82)=0,"Inativo",SUM(AZ82:BK82)>0,"Ativo") -> Ativo | AA82: Moderado | BO82: 0 | BP82: 0 | BQ82: 0 | BR82: 0 | BS82: 0 | BT82: 0 | BU82: 0 | BV82: 0 | BW82: 0 | BX82: 0 | BY82: {=XLOOKUP(C82,'PL TOTAL D0'!$A$3:$A$1991,'PL TOTAL D0'!$C$3:$C$1991,"")}
A83: BTG | B83: Ana Paula Villas Boas | C83: 004210959 | D83: Altum | E83: DF | F83: Alexandre Xavier | G83: =IFS($BS$4:$BS$1280<=250000,"David",$BS$4:$BS$1280<=800000,"Gabriel", $BS$4:$BS$1280>800000,"Marcus") -> David | H83: Ativo | I83: Sem Saldo | J83: =IF(Q83=0,"Não","Sim") -> Sim | K83: 45383 | M83: INC | N83: 0.012 | O83: ------ | P83: 0 | Q83: 60K D+0 (29/11/2024) | S83: PF | T83: 700.200.191-49 | U83: 5561982203222 | V83: anapaulavb@gmail.com | W83: 29716 | X83: DF | Y83: =IFS(H:H="Encerrado","Encerrado",COUNTBLANK(AZ83:BK83)>0,"Ativo",SUM(AZ83:BK83)=0,"Inativo",SUM(AZ83:BK83)>0,"Ativo") -> Ativo | AB83: Qualificado | AD83: 45383 | AE83: 49075100014019 | AX83: 452720.26 | AY83: 737235.4 | AZ83: 742704.6 | BA83: 859814.5 | BB83: 864957.49 | BC83: 869391.93 | BD83: 876861.15 | BE83: 865305.82 | BF83: 870553.4 | BG83: 878733.9 | BH83: 881770.39 | BI83: 891056.32 | BJ83: 1150583.7 | BK83: 1230746.4 | BL83: 1241524 | BM83: 17433.61 | BN83: 0 | BO83: 0 | BP83: 0 | BQ83: 0 | BR83: 0 | BS83: 0 | BT83: 0 | BU83: 0 | BV83: 0 | BW83: 0 | BX83: 0 | BY83: {=XLOOKUP(C83,'PL TOTAL D0'!$A$3:$A$1991,'PL TOTAL D0'!$C$3:$C$1991,"")}
A84: BTG | B84: Anderson Costa Parra | C84: 005195353 | D84: Bluemetrix | E84: GO | F84: Fabrício Bonfim | G84: =IFS($BS$4:$BS$1280<=250000,"David",$BS$4:$BS$1280<=800000,"Gabriel", $BS$4:$BS$1280>800000,"Marcus") -> David | H84: Ativo | I84: ------ | J84: =IF(Q84=0,"Não","Sim") -> Não | K84: 46160 | M84: INC | N84: 0.012 | O84: ------ | P84: 0 | S84: PF | T84: 357.986.318-50 | U84: 64 99997-6003 | V84: andersoncparra@gmail.com | W84: 32641 | X84: GO | Y84: =IFS(H:H="Encerrado","Encerrado",COUNTBLANK(AZ84:BK84)>0,"Ativo",SUM(AZ84:BK84)=0,"Inativo",SUM(AZ84:BK84)>0,"Ativo") -> Ativo | AA84: Conservador | AD84: 46203 | BW84: 0 | BX84: 25013.32 | BY84: {=XLOOKUP(C84,'PL TOTAL D0'!$A$3:$A$1991,'PL TOTAL D0'!$C$3:$C$1991,"")} -> 151954.71
A85: BTG | B85: André Airton de Macedo Rebouças | C85: 005192625 | D85: Bluemetrix | E85: DF | F85: Bluemetrix Asset | G85: =IFS($BS$4:$BS$1280<=250000,"David",$BS$4:$BS$1280<=800000,"Gabriel", $BS$4:$BS$1280>800000,"Marcus") -> David | H85: Inativo | I85: Sem Saldo | J85: =IF(Q85=0,"Não","Sim") -> Não | K85: 45296 | M85: PREV CON | N85: 0.007 | O85: ------ | P85: 0 | S85: PF | T85: 504.683.671-87 | U85: 5561999330992 | V85: aamreboucas@gmail.com | W85: 25617 | X85: DF | Y85: =IFS(H:H="Encerrado","Encerrado",COUNTBLANK(AZ85:BK85)>0,"Ativo",SUM(AZ85:BK85)=0,"Inativo",SUM(AZ85:BK85)>0,"Ativo") -> Inativo | AB85: Qualificado | AD85: 45296 | AE85: 49075100013276 | AU85: 0 | AV85: 0 | AW85: 0 | AX85: 0 | AY85: 0 | AZ85: 0 | BA85: 0 | BB85: 0 | BC85: 0 | BD85: 0 | BE85: 0 | BF85: 0 | BG85: 0 | BH85: 0 | BI85: 0 | BJ85: 0 | BK85: 0 | BL85: 0 | BM85: 0 | BN85: 0 | BO85: 0 | BP85: 0 | BQ85: 0 | BR85: 0 | BS85: 0 | BT85: 0 | BU85: 0 | BV85: 0 | BW85: 0 | BX85: 0 | BY85: {=XLOOKUP(C85,'PL TOTAL D0'!$A$3:$A$1991,'PL TOTAL D0'!$C$3:$C$1991,"")}
A86: BTG | B86: André Augusto Gastaldon Rios | C86: 005040864 | D86: Bluemetrix | E86: GO | F86: Felipe Rios | G86: =IFS($BS$4:$BS$1280<=250000,"David",$BS$4:$BS$1280<=800000,"Gabriel", $BS$4:$BS$1280>800000,"Marcus") -> David | H86: Ativo | I86: ------ | J86: =IF(Q86=0,"Não","Sim") -> Não | K86: 45208 | M86: INC | N86: 0.012 | O86: ------ | P86: 0 | S86: PF | T86: 017.317.371-30 | U86: 5593992243003 | V86: andreriosadv@gmail.com | W86: 32424 | X86: PA | Y86: =IFS(H:H="Encerrado","Encerrado",COUNTBLANK(AZ86:BK86)>0,"Ativo",SUM(AZ86:BK86)=0,"Inativo",SUM(AZ86:BK86)>0,"Ativo") -> Ativo | AB86: Qualificado | AD86: 45208 | AE86: 49075100011168 | AQ86: 0 | AR86: 100000 | AS86: 100890.32 | AT86: 101746.1 | AU86: 172788.35 | AV86: 160874.86 | AW86: 134780.95 | AX86: 109895.79 | AY86: 81373.72 | AZ86: 81892.74 | BA86: 52354.03 | BB86: 52685.32 | BC86: 53036.9 | BD86: 22366.05 | BE86: 5034.87 | BF86: 5083.65 | BG86: 5129.64 | BH86: 5173.13 | BI86: 5222.35 | BJ86: 5276.75 | BK86: 5290.6 | BL86: 5341.59 | BM86: 5403.21 | BN86: 5458.75 | BO86: 5515.46 | BP86: 5581.15 | BQ86: 5576.16 | BR86: 5638.08 | BS86: 5697.14 | BT86: 5747.45 | BU86: 5816.84 | BV86: 5870.96 | BW86: 5869.16 | BX86: 5921.45 | BY86: {=XLOOKUP(C86,'PL TOTAL D0'!$A$3:$A$1991,'PL TOTAL D0'!$C$3:$C$1991,"")}
A87: BTG | B87: Andre Bobroff Canavezi | C87: 008670974 | D87: Miura | E87: SUL | F87: Lucas Zambrin | G87: =IFS($BS$4:$BS$1280<=250000,"David",$BS$4:$BS$1280<=800000,"Gabriel", $BS$4:$BS$1280>800000,"Marcus") -> Gabriel | H87: Ativo | I87: ------ | J87: =IF(Q87=0,"Não","Sim") -> Sim | K87: 46028 | M87: INC | N87: 0.012 | O87: ------ | P87: 0 | Q87: 200k para novembro (08/05/2026). | S87: PF | T87: 030.014.379-60 | U87: 43 99156-1938 | V87: drelunardelli@hotmail.com | W87: 29325 | X87: PR | Y87: =IFS(H:H="Encerrado","Encerrado",COUNTBLANK(AZ87:BK87)>0,"Ativo",SUM(AZ87:BK87)=0,"Inativo",SUM(AZ87:BK87)>0,"Ativo") -> Ativo | AA87: Conservador | AD87: 46203 | BS87: 403435.17 | BT87: 406724.4 | BU87: 562607.3 | BV87: 573355.1 | BW87: 780475.9 | BX87: 787688.6 | BY87: {=XLOOKUP(C87,'PL TOTAL D0'!$A$3:$A$1991,'PL TOTAL D0'!$C$3:$C$1991,"")} -> 896977.05
A88: BTG | B88: Andre Luis Macedo Pinheiro | C88: 035479708 | D88: Investeseg | E88: BA | F88: Murilo Silva | G88: =IFS($BS$4:$BS$1280<=250000,"David",$BS$4:$BS$1280<=800000,"Gabriel", $BS$4:$BS$1280>800000,"Marcus") -> David | H88: Ativo | I88: ------ | J88: =IF(Q88=0,"Não","Sim") -> Não | K88: 46218 | M88: CON/ GR | N88: 0.013 | O88: ------ | P88: 0 | S88: PF | T88: 015.701.435-52 | U88: 71 99222-0181 | V88: andrefte@hotmail.com | W88: 31365 | X88: BA | Y88: =IFS(H:H="Encerrado","Encerrado",COUNTBLANK(AZ88:BK88)>0,"Ativo",SUM(AZ88:BK88)=0,"Inativo",SUM(AZ88:BK88)>0,"Ativo") -> Ativo | AA88: Moderado | BX88: 0 | BY88: {=XLOOKUP(C88,'PL TOTAL D0'!$A$3:$A$1991,'PL TOTAL D0'!$C$3:$C$1991,"")} -> 335441.31
A89: BTG | B89: André Reichert da Silva Godoy | C89: 005003629 | D89: Miura | E89: SUL | F89: Rodrigo Milanez | G89: =IFS($BS$4:$BS$1280<=250000,"David",$BS$4:$BS$1280<=800000,"Gabriel", $BS$4:$BS$1280>800000,"Marcus") -> David | H89: Encerrado | I89: ------ | J89: =IF(Q89=0,"Não","Sim") -> Não | K89: 44970 | L89: 45799 | M89: MULT PRIV/ CO ADM | N89: 0.009 | O89: ------ | P89: 0 | R89: Distrato unilateral | S89: PF | T89: 086.938.327-27 | X89: PR | Y89: =IFS(H:H="Encerrado","Encerrado",COUNTBLANK(AZ89:BK89)>0,"Ativo",SUM(AZ89:BK89)=0,"Inativo",SUM(AZ89:BK89)>0,"Ativo") -> Encerrado | AA89: Arrojado | AB89: Qualificado | AD89: 44970 | AE89: 49075100005443 | AI89: 1222961 | AJ89: 1391813 | AK89: 1394564.2 | AL89: 1263788.5 | AM89: 1307731.7 | AN89: 1320623.2 | AO89: 1332024 | AP89: 1360027 | AQ89: 1371280.2 | AR89: 1366216 | AS89: 1370110.4 | AT89: 1377123.7 | AU89: 1285051.9 | AV89: 1295132.7 | AW89: 1303972.4 | AX89: 1615482 | AY89: 1602822 | AZ89: 1613280 | BA89: 1635665 | BB89: 1656213.5 | BC89: 1655185 | BD89: 1640352.4 | BE89: 1628985.8 | BF89: 1639040.6 | BG89: 1671679.6 | BH89: 0 | BI89: 0 | BJ89: 0 | BK89: 0 | BL89: 0 | BM89: 0 | BN89: 0 | BO89: 0 | BP89: 0 | BQ89: 0 | BR89: 0 | BS89: 0 | BT89: 0 | BU89: 0 | BV89: 0 | BW89: 0 | BX89: 0 | BY89: {=XLOOKUP(C89,'PL TOTAL D0'!$A$3:$A$1991,'PL TOTAL D0'!$C$3:$C$1991,"")}
A90: BTG | B90: André Reichert da Silva Godoy | C90: 004392055 | D90: Miura | E90: SUL | F90: Rodrigo Milanez | G90: =IFS($BS$4:$BS$1280<=250000,"David",$BS$4:$BS$1280<=800000,"Gabriel", $BS$4:$BS$1280>800000,"Marcus") -> David | H90: Encerrado | I90: ------ | J90: =IF(Q90=0,"Não","Sim") -> Não | K90: 44970 | L90: 44661 | M90: FII | N90: 0.008 | O90: IFIX | P90: 0.1 | S90: PF | T90: 086.938.327-27 | X90: PR | Y90: =IFS(H:H="Encerrado","Encerrado",COUNTBLANK(AZ90:BK90)>0,"Ativo",SUM(AZ90:BK90)=0,"Inativo",SUM(AZ90:BK90)>0,"Ativo") -> Encerrado | AD90: 44970 | AJ90: 0 | AK90: 0 | AL90: 0 | AM90: 0 | AN90: 0 | AO90: 0 | AP90: 0 | AQ90: 0 | AR90: 0 | AS90: 0 | AT90: 0 | AU90: 0 | AV90: 0 | AW90: 0 | AX90: 0 | AY90: 0 | AZ90: 0 | BA90: 0 | BB90: 0 | BC90: 0 | BD90: 0 | BE90: 0 | BF90: 0 | BG90: 0 | BH90: 0 | BI90: 0 | BJ90: 0 | BK90: 0 | BL90: 0 | BM90: 0 | BN90: 0 | BO90: 0 | BP90: 0 | BQ90: 0 | BR90: 0 | BS90: 0 | BT90: 0 | BU90: 0 | BV90: 0 | BW90: 0 | BX90: 0 | BY90: {=XLOOKUP(C90,'PL TOTAL D0'!$A$3:$A$1991,'PL TOTAL D0'!$C$3:$C$1991,"")}
A91: BTG | B91: André Reichert da Silva Godoy | C91: 004384131 | D91: Miura | E91: SUL | F91: Rodrigo Milanez | G91: =IFS($BS$4:$BS$1280<=250000,"David",$BS$4:$BS$1280<=800000,"Gabriel", $BS$4:$BS$1280>800000,"Marcus") -> David | H91: Inativo | I91: Sem Saldo | J91: =IF(Q91=0,"Não","Sim") -> Não | K91: 45020 | M91: EQT | N91: 0.025 | O91: IBOVESPA | P91: 0.2 | R91: Cliente sofreu tentativa de fraude - qualquer alteração em seu cadastro ou movimentação na conta entrar em contato com o FA/Cliente para confirmação. | S91: PF | T91: 086.938.327-27 | X91: PR | Y91: =IFS(H:H="Encerrado","Encerrado",COUNTBLANK(AZ91:BK91)>0,"Ativo",SUM(AZ91:BK91)=0,"Inativo",SUM(AZ91:BK91)>0,"Ativo") -> Ativo | AA91: Arrojado | AB91: Qualificado | AD91: 45020 | AE91: 49075100003246 | AI91: 0 | AJ91: 0 | AK91: 0 | AL91: 155956.48 | AM91: 171559.12 | AN91: 185313.16 | AO91: 195637.75 | AP91: 205565.4 | AQ91: 204852.83 | AR91: 196248.7 | AS91: 211119.27 | AT91: 221616.84 | AU91: 303272.69 | AV91: 307694.41 | AW91: 313646.34 | AX91: 907.07 | AY91: 907.07 | AZ91: 910.15 | BA91: 910.15 | BB91: 910.15 | BC91: 910.46 | BD91: 911.65 | BE91: 912.38 | BF91: 915.12 | BG91: 229.74 | BH91: 229.74 | BI91: 229.74 | BJ91: 0 | BK91: 0 | BL91: 0 | BM91: 0 | BN91: 0 | BO91: 0 | BP91: 0 | BQ91: 0 | BR91: 0 | BS91: 0 | BT91: 0 | BU91: 0 | BV91: 0 | BW91: 0 | BX91: 0 | BY91: {=XLOOKUP(C91,'PL TOTAL D0'!$A$3:$A$1991,'PL TOTAL D0'!$C$3:$C$1991,"")}
A92: BTG | B92: André Terra Mendonça | C92: 005639781 | D92: Bluemetrix | E92: DF | F92: Luca Bueno | G92: =IFS($BS$4:$BS$1280<=250000,"David",$BS$4:$BS$1280<=800000,"Gabriel", $BS$4:$BS$1280>800000,"Marcus") -> David | H92: Encerrado | I92: ------ | J92: =IF(Q92=0,"Não","Sim") -> Não | K92: 45447 | L92: 45562 | M92: INC | N92: 0.011 | O92: ------ | P92: 0 | S92: PF | T92: 005.729.521-20 | X92: DF | Y92: =IFS(H:H="Encerrado","Encerrado",COUNTBLANK(AZ92:BK92)>0,"Ativo",SUM(AZ92:BK92)=0,"Inativo",SUM(AZ92:BK92)>0,"Ativo") -> Encerrado | AA92: Moderado | AB92: Qualificado | AD92: 45447 | AE92: 49075100015007 | AZ92: 334241.8 | BA92: 337347.5 | BB92: 340143.86 | BC92: 347758.49 | BD92: 0 | BE92: 0 | BF92: 0 | BG92: 0 | BH92: 0 | BI92: 0 | BJ92: 0 | BK92: 0 | BL92: 0 | BM92: 0 | BN92: 0 | BO92: 0 | BP92: 0 | BQ92: 0 | BR92: 0 | BS92: 0 | BT92: 0 | BU92: 0 | BV92: 0 | BW92: 0 | BX92: 0 | BY92: {=XLOOKUP(C92,'PL TOTAL D0'!$A$3:$A$1991,'PL TOTAL D0'!$C$3:$C$1991,"")}
A93: BTG | B93: Andre Yoshio Itiyama | C93: 004514241 | D93: Miura | E93: SUL | F93: Lucas Zambrin | G93: =IFS($BS$4:$BS$1280<=250000,"David",$BS$4:$BS$1280<=800000,"Gabriel", $BS$4:$BS$1280>800000,"Marcus") -> David | H93: Inativo | I93: Sem Saldo | J93: =IF(Q93=0,"Não","Sim") -> Não | K93: 45166 | M93: MOD | N93: 0.015 | O93: CDI | P93: 0.1 | R93: STVM de entrada da Guide finalizada (30/08/2023) | S93: PF | T93: 880.001.339-20 | U93: 5543988161543 | V93: andreitiyamalda@gmail.com | W93: 26264 | X93: PR | Y93: =IFS(H:H="Encerrado","Encerrado",COUNTBLANK(AZ93:BK93)>0,"Ativo",SUM(AZ93:BK93)=0,"Inativo",SUM(AZ93:BK93)>0,"Ativo") -> Ativo | AB93: Qualificado | AD93: 45166 | AE93: 49075100006830 | AL93: 0 | AM93: 0 | AN93: 0 | AO93: 0 | AP93: 95343.18 | AQ93: 103773.77 | AR93: 103586.63 | AS93: 105703.53 | AT93: 107753.21 | AU93: 106220.49 | AV93: 107091.21 | AW93: 108303.4 | AX93: 107556.65 | AY93: 107101.3 | AZ93: 107674 | BA93: 109133.6 | BB93: 110448.89 | BC93: 110362.14 | BD93: 109689.94 | BE93: 109122.3 | BF93: 109103.31 | BG93: 57423.12 | BH93: 58001.36 | BI93: 58631.61 | BJ93: 528.63 | BK93: 749.86 | BL93: 754.63 | BM93: 762.14 | BN93: 769.07 | BO93: 776.07 | BP93: 784.12 | BQ93: 784.52 | BR93: 792.07 | BS93: 800.39 | BT93: 808.26 | BU93: 818.03 | BV93: 826.77 | BW93: 827.91 | BX93: 836.54 | BY93: {=XLOOKUP(C93,'PL TOTAL D0'!$A$3:$A$1991,'PL TOTAL D0'!$C$3:$C$1991,"")}
A94: BTG | B94: Andrea Aparecida Borges Silva | C94: 003894173 | D94: Bluemetrix | E94: DF | F94: Bruno Henrique | G94: =IFS($BS$4:$BS$1280<=250000,"David",$BS$4:$BS$1280<=800000,"Gabriel", $BS$4:$BS$1280>800000,"Marcus") -> David | H94: Inativo | I94: Monitoramento | J94: =IF(Q94=0,"Não","Sim") -> Não | K94: 45222 | M94: MONT | N94: 0 | O94: ------ | P94: 0 | R94: Alteração de carteira finalizada (17/07/2025) | S94: PF | T94: 505.182.241-04 | U94: 5561996549735 | V94: andrea.borges38@gmail.com | W94: 26364 | X94: DF | Y94: =IFS(H:H="Encerrado","Encerrado",COUNTBLANK(AZ94:BK94)>0,"Ativo",SUM(AZ94:BK94)=0,"Inativo",SUM(AZ94:BK94)>0,"Ativo") -> Ativo | AB94: Qualificado | AD94: 45222 | AE94: 49075100012180 | AR94: 48822.53 | AS94: 75424.98 | AT94: 81632.83 | AU94: 75566.95 | AV94: 72113.04 | AW94: 79278.76 | AX94: 82893.79 | AY94: 4132.46 | AZ94: 4165.21 | BA94: 4191.55 | BB94: 4221.83 | BC94: 4236.21 | BD94: 4273.2 | BE94: 4308.06 | BF94: 4340.73 | BG94: 0 | BH94: 0 | BI94: 0 | BJ94: 0 | BK94: 0 | BL94: 0 | BM94: 7450.71 | BN94: 7641 | BO94: 8041.76 | BP94: 8147.94 | BQ94: 8713.81 | BR94: 8930.75 | BS94: 9478.68 | BT94: 9760.85 | BU94: 9728.94 | BV94: 9743.55 | BW94: 9653.21 | BX94: 117914.75 | BY94: {=XLOOKUP(C94,'PL TOTAL D0'!$A$3:$A$1991,'PL TOTAL D0'!$C$3:$C$1991,"")} -> 120270.81
A95: BTG | B95: Andrea Aparecida Borges Silva | C95: 005186167 | D95: Bluemetrix | E95: DF | F95: Bruno Henrique | G95: =IFS($BS$4:$BS$1280<=250000,"David",$BS$4:$BS$1280<=800000,"Gabriel", $BS$4:$BS$1280>800000,"Marcus") -> David | H95: Inativo | I95: Monitoramento | J95: =IF(Q95=0,"Não","Sim") -> Não | K95: 45293 | M95: MONT | N95: 0 | O95: ------ | P95: 0 | R95: Monitoramento p/ envio de ativos da conta principal que estão fora da estrategia | S95: PF | T95: 505.182.241-04 | U95: 5561996549735 | V95: andrea.borges38@gmail.com | W95: 26364 | X95: DF | Y95: =IFS(H:H="Encerrado","Encerrado",COUNTBLANK(AZ95:BK95)>0,"Ativo",SUM(AZ95:BK95)=0,"Inativo",SUM(AZ95:BK95)>0,"Ativo") -> Ativo | AB95: Qualificado | AD95: 45293 | AE95: 49075100013284 | AT95: 0 | AU95: 16116.88 | AV95: 21365.67 | AW95: 28193.34 | AX95: 30082.51 | AY95: 21100.83 | AZ95: 27090.56 | BA95: 27951.61 | BB95: 28896.18 | BC95: 27203.09 | BD95: 29966.53 | BE95: 32741.68 | BF95: 39507.11 | BG95: 47163.15 | BH95: 50124.31 | BI95: 52126.29 | BJ95: 55531.99 | BK95: 62212.66 | BL95: 65675 | BM95: 66270.84 | BN95: 71124.49 | BO95: 129033.16 | BP95: 133872.2 | BQ95: 141002.8 | BR95: 147587.5 | BS95: 157318.27 | BT95: 166176.5 | BU95: 176376.4 | BV95: 181411.9 | BW95: 182778.8 | BX95: 451691.06 | BY95: {=XLOOKUP(C95,'PL TOTAL D0'!$A$3:$A$1991,'PL TOTAL D0'!$C$3:$C$1991,"")} -> 462782.67
A96: BTG | B96: Andrea de Moura Ferrandini e/ou Walter Germano de Oliveira | C96: 005719200 | D96: Altum | E96: DF | F96: Guilherme Marques | G96: =IFS($BS$4:$BS$1280<=250000,"David",$BS$4:$BS$1280<=800000,"Gabriel", $BS$4:$BS$1280>800000,"Marcus") -> David | H96: Inativo | I96: Bloqueado | J96: =IF(Q96=0,"Não","Sim") -> Sim | K96: 45475 | M96: INC | N96: 0.012 | O96: ------ | P96: 0 | Q96: 50K D+0 (08/11/2024) | S96: PF | T96: 351.864.531-53 | U96: 5561999720222 | V96: andreaferrandini@gmail.com | W96: 24789 | X96: DF | Y96: =IFS(H:H="Encerrado","Encerrado",COUNTBLANK(AZ96:BK96)>0,"Ativo",SUM(AZ96:BK96)=0,"Inativo",SUM(AZ96:BK96)>0,"Ativo") -> Ativo | AA96: Conservador | AB96: Qualificado | AD96: 45475 | AE96: 49075100015511 | BA96: 0 | BB96: 0 | BC96: 0 | BD96: 0 | BE96: 0 | BF96: 0 | BG96: 0 | BH96: 0 | BI96: 0 | BJ96: 0 | BK96: 0 | BL96: 0 | BM96: 0 | BN96: 0 | BO96: 0 | BP96: 0 | BQ96: 0 | BR96: 0 | BS96: 0 | BT96: 0 | BU96: 0 | BV96: 0 | BW96: 0 | BX96: 0 | BY96: {=XLOOKUP(C96,'PL TOTAL D0'!$A$3:$A$1991,'PL TOTAL D0'!$C$3:$C$1991,"")}
A97: BTG | B97: Andrea Moreira Minossi | C97: 014307003 | D97: VcInvest | E97: GO | F97: Bruno Ribeiro | G97: =IFS($BS$4:$BS$1280<=250000,"David",$BS$4:$BS$1280<=800000,"Gabriel", $BS$4:$BS$1280>800000,"Marcus") -> David | H97: Ativo | I97: Sem Saldo | J97: =IF(Q97=0,"Não","Sim") -> Não | K97: 46190 | M97: INC | N97: 0.012 | O97: ------ | P97: 0 | S97: PF | T97: 419.697.901-72 | U97: 65 99981-5371 | V97: andrea.minossi@gmail.com | W97: 25165 | X97: MT | Y97: =IFS(H:H="Encerrado","Encerrado",COUNTBLANK(AZ97:BK97)>0,"Ativo",SUM(AZ97:BK97)=0,"Inativo",SUM(AZ97:BK97)>0,"Ativo") -> Ativo | AA97: Moderado | BX97: 0 | BY97: {=XLOOKUP(C97,'PL TOTAL D0'!$A$3:$A$1991,'PL TOTAL D0'!$C$3:$C$1991,"")}
A98: BTG | B98: Andrea Ribas Silva de Azevedo | C98: 004272577 | D98: Bluemetrix | E98: DF | F98: Jorge Luiz Braga de Carvalho | G98: =IFS($BS$4:$BS$1280<=250000,"David",$BS$4:$BS$1280<=800000,"Gabriel", $BS$4:$BS$1280>800000,"Marcus") -> David | H98: Ativo | I98: ------ | J98: =IF(Q98=0,"Não","Sim") -> Sim | K98: 46157 | M98: INC | N98: 0.012 | O98: ------ | P98: 0 | Q98: Aplicar em D+0 aportes e vencimentos. (17/07/2026) | S98: PF | T98: 368.891.801-00 | U98: 61 98150-0383 | V98: ribas.andrea@gmail.com | W98: 24058 | X98: DF | Y98: =IFS(H:H="Encerrado","Encerrado",COUNTBLANK(AZ98:BK98)>0,"Ativo",SUM(AZ98:BK98)=0,"Inativo",SUM(AZ98:BK98)>0,"Ativo") -> Ativo | AA98: Moderado | AD98: 46203 | BW98: 564693.5 | BX98: 628401.32 | BY98: {=XLOOKUP(C98,'PL TOTAL D0'!$A$3:$A$1991,'PL TOTAL D0'!$C$3:$C$1991,"")} -> 628577.51
A99: BTG | B99: Andrea Satyro Sa Ribeiro Fritzsche | C99: 004181486 | D99: Bluemetrix | E99: DF | F99: Thiago Canabrava | G99: =IFS($BS$4:$BS$1280<=250000,"David",$BS$4:$BS$1280<=800000,"Gabriel", $BS$4:$BS$1280>800000,"Marcus") -> Gabriel | H99: Ativo | I99: ------ | J99: =IF(Q99=0,"Não","Sim") -> Não | K99: 45202 | M99: INC | N99: 0 | O99: ------ | P99: 0 | S99: PF | T99: 875.628.047-53 | U99: 5561981155555 | V99: asatyrof@gmail.com | W99: 23623 | X99: DF | Y99: =IFS(H:H="Encerrado","Encerrado",COUNTBLANK(AZ99:BK99)>0,"Ativo",SUM(AZ99:BK99)=0,"Inativo",SUM(AZ99:BK99)>0,"Ativo") -> Ativo | AB99: Qualificado | AD99: 45202 | AE99: 49075100011176 | AQ99: 0 | AR99: 194378.52 | AS99: 674378.81 | AT99: 681890.11 | AU99: 677840.76 | AV99: 682786.1 | AW99: 688196.81 | AX99: 682735.49 | AY99: 682566.4 | AZ99: 687302.1 | BA99: 693824.3 | BB99: 700759.12 | BC99: 705618.56 | BD99: 710881.27 | BE99: 717301.09 | BF99: 515967.06 | BG99: 730483.91 | BH99: 735459.94 | BI99: 741364.76 | BJ99: 750882.36 | BK99: 761657.08 | BL99: 639144.82 | BM99: 646181.58 | BN99: 652846.3 | BO99: 660292.41 | BP99: 669872.3 | BQ99: 675299.7 | BR99: 682408.8 | BS99: 690188.83 | BT99: 695157.3 | BU99: 697812.2 | BV99: 709658.3 | BW99: 717331.3 | BX99: 725166.4 | BY99: {=XLOOKUP(C99,'PL TOTAL D0'!$A$3:$A$1991,'PL TOTAL D0'!$C$3:$C$1991,"")} -> 734516.7
A100: BTG | B100: Angela Chopard Bonilauri | C100: 025897992 | D100: VcInvest | E100: GO | F100: Bruno Ribeiro | G100: =IFS($BS$4:$BS$1280<=250000,"David",$BS$4:$BS$1280<=800000,"Gabriel", $BS$4:$BS$1280>800000,"Marcus") -> David | H100: Ativo | I100: ------ | J100: =IF(Q100=0,"Não","Sim") -> Não | K100: 46170 | M100: INC | N100: 0.012 | O100: ------ | P100: 0 | S100: PF | T100: 075.644.627-95 | U100: 61 99655-9211 | V100: angelcbonilauri@gmail.com | W100: 27667 | X100: DF | Y100: =IFS(H:H="Encerrado","Encerrado",COUNTBLANK(AZ100:BK100)>0,"Ativo",SUM(AZ100:BK100)=0,"Inativo",SUM(AZ100:BK100)>0,"Ativo") -> Ativo | AA100: Moderado | AD100: 46203 | BW100: 0 | BX100: 100574.66 | BY100: {=XLOOKUP(C100,'PL TOTAL D0'!$A$3:$A$1991,'PL TOTAL D0'!$C$3:$C$1991,"")} -> 132694.62
...

Sheet XP
A1: Backoffice | G1: Mesa de Operação | H1: Backoffice/ Mesa | J1: Backoffice | Q1: Mesa de Operação | R1: Backoffice | S1: Anbima | AF1: Financeiro | AG1: Financeiro | AH1: Financeiro | AI1: Financeiro | AJ1: Financeiro | AK1: Financeiro | AL1: Financeiro | AM1: Financeiro | AN1: Financeiro | AO1: Financeiro | AP1: Financeiro | AQ1: Financeiro | AR1: Financeiro | AS1: Financeiro | AT1: Financeiro | AU1: Financeiro | AV1: Financeiro | AW1: Financeiro | AX1: Financeiro | AY1: Financeiro | AZ1: Financeiro
A2: Corretora | B2: Cliente | C2: Conta | D2: Escritório | E2: UF | F2: Assessor | G2: Operador | H2: Status | I2: Situação | J2: Exceção | K2: Início da Gestão | L2: Data distrato | M2: Carteira | N2: Taxa de Gestão | O2: Benchmark TX. Perf. | P2: TX. Perf. | Q2: Observações | R2: Observações Backoffice | S2: PF/ PJ | T2: CPF/CNPJ | U2: Telefone | V2: E-mail | W2: Aniversário | X2: UF cliente | Y2: Status Anbima | Z2: Perfil de risco da carteira | AA2: Perfil de risco do investidor | AB2: Classificação do Investidor | AC2: Grupo Econômico (Região) | AD2: Data Primeiro Aporte | AE2: Código Anbima | AF2: 29/11/2024 | AG2: 31/12/2024 | AH2: 31/01/2025 | AI2: 28/02/2025 | AJ2: 31/03/2025 | AK2: 30/04/2025 | AL2: 30/05/2025 | AM2: 30/06/2025 | AN2: 31/07/2025 | AO2: 31/08/2025 | AP2: 30/09/2025 | AQ2: 31/10/2025 | AR2: 30/11/2025 | AS2: 31/12/2025 | AT2: 31/01/2026 | AU2: 28/02/2026 | AV2: 31/03/2026 | AW2: 30/04/2026 | AX2: 31/05/2026 | AY2: 30/06/2026 | AZ2: Julho (D-1)
A3: XP | B3: Adilton Jose Nunes | C3: 3757672 | D3: VcInvest | E3: GO | F3: Bruno Ribeiro | G3: =IFS($AZ$3:$AZ$993<=250000,"David",$AZ$3:$AZ$993<=800000,"Gabriel", $AZ$3:$AZ$993>800000,"Marcus") -> Gabriel | H3: Ativo | I3: ------ | J3: =IF(Q3=0,"Não","Sim") -> Não | K3: 45840 | M3: INC | N3: 0.012 | O3: ------ | P3: 0 | S3: PF | T3: 291.691.191-04 | U3: (62) - 996986126 | V3: adiltonj2010@hotmail.com | W3: 23179 | X3: GO | Y3: =IFS(H:H="Encerrado","Encerrado",COUNTBLANK(AF3:AN3)>0,"Ativo",SUM(AF3:AN3)=0,"Inativo",SUM(AF3:AN3)>0,"Ativo") -> Ativo | AA3: Arrojado | AD3: 45840 | AE3: 49075100019258 | AN3: 144331.95 | AO3: 142905.94 | AP3: 144341.88 | AQ3: 146055.67 | AR3: 147170.09 | AS3: 148443.65 | AT3: 260339.53 | AU3: 262739.38 | AV3: 265297.43 | AW3: 268181.36 | AX3: 270597.74 | AY3: 273498.9 | AZ3: {=XLOOKUP(C3,'PL TOTAL D0'!K:K,'PL TOTAL D0'!L:L,"")} -> 276308.66
A4: XP | B4: Adilton Jose Nunes | C4: 18408485 | D4: VcInvest | E4: GO | F4: Bruno Ribeiro | G4: =IFS($AZ$3:$AZ$993<=250000,"David",$AZ$3:$AZ$993<=800000,"Gabriel", $AZ$3:$AZ$993>800000,"Marcus") -> David | H4: Ativo | I4: ------ | J4: =IF(Q4=0,"Não","Sim") -> Não | K4: 45866 | M4: EQT | N4: 0.025 | O4: IBOVESPA | P4: 0.2 | S4: PF | T4: 291.691.191-04 | U4: (62) - 996986126 | V4: adiltonj2010@hotmail.com | W4: 23179 | X4: GO | Y4: =IFS(H:H="Encerrado","Encerrado",COUNTBLANK(AF4:AN4)>0,"Ativo",SUM(AF4:AN4)=0,"Inativo",SUM(AF4:AN4)>0,"Ativo") -> Ativo | AA4: Arrojado | AD4: 45881 | AE4: 49075100019355 | AN4: 100 | AO4: 53659.64 | AP4: 62438.8 | AQ4: 63293.59 | AR4: 65878.76 | AS4: 67022.39 | AT4: 73515.96 | AU4: 76142 | AV4: 75570.13 | AW4: 75868.5 | AX4: 71064.05 | AY4: 73223.4 | AZ4: {=XLOOKUP(C4,'PL TOTAL D0'!K:K,'PL TOTAL D0'!L:L,"")} -> 72629.59
A5: XP | B5: Adriana Princhak Teixeira Pinto | C5: 19584661 | D5: Poupinvista | E5: DF | F5: Bruno Rodrigues | G5: =IFS($AZ$3:$AZ$993<=250000,"David",$AZ$3:$AZ$993<=800000,"Gabriel", $AZ$3:$AZ$993>800000,"Marcus") -> David | H5: Ativo | I5: ------ | J5: =IF(Q5=0,"Não","Sim") -> Sim | K5: 46169 | M5: INC | N5: 0.012 | O5: ------ | P5: 0 | Q5: 40k PGBL (27/05/2026). | S5: PF | T5: 016.900.761-86 | U5: 61 98121-7104 | V5: adrianaprinchak@gmail.com | W5: 31348 | X5: DF | Y5: =IFS(H:H="Encerrado","Encerrado",COUNTBLANK(AF5:AN5)>0,"Ativo",SUM(AF5:AN5)=0,"Inativo",SUM(AF5:AN5)>0,"Ativo") -> Ativo | AA5: Moderado | AX5: 0 | AY5: 0 | AZ5: {=XLOOKUP(C5,'PL TOTAL D0'!K:K,'PL TOTAL D0'!L:L,"")} -> 0
A6: XP | B6: A & R Sinalização E Comunicação Visual Eireli | C6: 3227135 | D6: MI Smart | E6: DF | F6: Mariana Rocha | G6: =IFS($AZ$3:$AZ$993<=250000,"David",$AZ$3:$AZ$993<=800000,"Gabriel", $AZ$3:$AZ$993>800000,"Marcus") -> Gabriel | H6: Ativo | I6: ------ | J6: =IF(Q6=0,"Não","Sim") -> Não | K6: 45716 | M6: INC | N6: 0.012 | O6: ------ | P6: 0 | S6: PJ | T6: 10.909.603/0001-64 | U6: (61) - 33997458 | V6: renato@lasersign.com.br | W6: PJ | X6: DF | Y6: =IFS(H:H="Encerrado","Encerrado",COUNTBLANK(AF6:AN6)>0,"Ativo",SUM(AF6:AN6)=0,"Inativo",SUM(AF6:AN6)>0,"Ativo") -> Ativo | AA6: Conservador | AD6: 45716 | AE6: 49075100017883 | AI6: 842201.12 | AJ6: 820350.4 | AK6: 832914.4 | AL6: 840525.35 | AM6: 840554.62 | AN6: 731771.97 | AO6: 678081.35 | AP6: 650393.33 | AQ6: 656400.56 | AR6: 628389.07 | AS6: 631304.17 | AT6: 631089.14 | AU6: 632622.02 | AV6: 499988.42 | AW6: 467612.11 | AX6: 378002.9 | AY6: 303308.58 | AZ6: {=XLOOKUP(C6,'PL TOTAL D0'!K:K,'PL TOTAL D0'!L:L,"")} -> 334477.35
A7: XP | B7: Afrisio de Souza Vieira Lima Filho | C7: 3345620 | D7: Bluemetrix | E7: DF | F7: Thiago Canabrava | G7: =IFS($AZ$3:$AZ$993<=250000,"David",$AZ$3:$AZ$993<=800000,"Gabriel", $AZ$3:$AZ$993>800000,"Marcus") -> David | H7: Ativo | I7: ------ | J7: =IF(Q7=0,"Não","Sim") -> Não | K7: 45693 | M7: INC | N7: 0.01 | O7: ------ | P7: 0 | S7: PF | T7: 152.774.535-04 | U7: (61) - 999811812 | V7: afrisio.lima@gmail.com | W7: 22296 | X7: DF | Y7: =IFS(H:H="Encerrado","Encerrado",COUNTBLANK(AF7:AN7)>0,"Ativo",SUM(AF7:AN7)=0,"Inativo",SUM(AF7:AN7)>0,"Ativo") -> Ativo | AA7: Moderado | AD7: 45693 | AE7: 49075100017786 | AH7: 0 | AI7: 220942.88 | AJ7: 222804.23 | AK7: 222781.11 | AL7: 223578.53 | AM7: 225342 | AN7: 228033.33 | AO7: 229031.43 | AP7: 231975.33 | AQ7: 233960.2 | AR7: 234330.74 | AS7: 235902.95 | AT7: 234990.11 | AU7: 232989.07 | AV7: 233605.17 | AW7: 226088.08 | AX7: 224469.08 | AY7: 220949.48 | AZ7: {=XLOOKUP(C7,'PL TOTAL D0'!K:K,'PL TOTAL D0'!L:L,"")} -> 217332.28
A8: XP | B8: Ailton Cabral Moraes | C8: 6853541 | D8: MI Smart | E8: DF | F8: Mariana Rocha | G8: =IFS($AZ$3:$AZ$993<=250000,"David",$AZ$3:$AZ$993<=800000,"Gabriel", $AZ$3:$AZ$993>800000,"Marcus") -> Marcus | H8: Ativo | I8: ------ | J8: =IF(Q8=0,"Não","Sim") -> Sim | K8: 45706 | M8: INC | N8: 0.012 | O8: ------ | P8: 0 | Q8: 200K D+0 (28/03/2025) | S8: PF | T8: 797.611.191-49 | U8: (61) - 999803078 | V8: ailtoncabral.moraes@gmail.com | W8: 28224 | X8: DF | Y8: =IFS(H:H="Encerrado","Encerrado",COUNTBLANK(AF8:AN8)>0,"Ativo",SUM(AF8:AN8)=0,"Inativo",SUM(AF8:AN8)>0,"Ativo") -> Ativo | AA8: Conservador | AD8: 45706 | AE8: 49075100018049 | AI8: 1308459.3 | AJ8: 1310131.3 | AK8: 1257958.1 | AL8: 1244862 | AM8: 1250582.3 | AN8: 1194830.3 | AO8: 1215000.1 | AP8: 1247894.5 | AQ8: 1265149.5 | AR8: 1271935.1 | AS8: 1099430.7 | AT8: 1112984.4 | AU8: 1260354.6 | AV8: 1127073.8 | AW8: 1152364.5 | AX8: 1062329.7 | AY8: 1030096.6 | AZ8: {=XLOOKUP(C8,'PL TOTAL D0'!K:K,'PL TOTAL D0'!L:L,"")} -> 1027647.2
A9: XP | B9: Alden Mangueira De Oliveira | C9: 15466228 | D9: MI Smart | E9: DF | F9: Mariana Rocha | G9: =IFS($AZ$3:$AZ$993<=250000,"David",$AZ$3:$AZ$993<=800000,"Gabriel", $AZ$3:$AZ$993>800000,"Marcus") -> Marcus | H9: Encerrado | I9: ------ | J9: =IF(Q9=0,"Não","Sim") -> Sim | K9: 45706 | L9: 45937 | M9: INC | N9: 0.012 | O9: ------ | P9: 0 | Q9: 100K D+0 (28/03/2025) | S9: PF | T9: 843.999.297-15 | U9: (61) - 992745523 | V9: alden.mangueira@gmail.com | W9: 24514 | X9: DF | Y9: =IFS(H:H="Encerrado","Encerrado",COUNTBLANK(AF9:AN9)>0,"Ativo",SUM(AF9:AN9)=0,"Inativo",SUM(AF9:AN9)>0,"Ativo") -> Encerrado | AA9: Conservador | AD9: 45706 | AE9: 49075100017964 | AI9: 419338.34 | AJ9: 421363.69 | AK9: 425205.32 | AL9: 428284.15 | AM9: 432502.22 | AN9: 437551.12 | AO9: 442424.09 | AP9: 447047.46 | AQ9: 0 | AR9: 0 | AS9: 0 | AT9: 0 | AU9: 0 | AV9: 0 | AW9: 0 | AX9: 0 | AY9: 0 | AZ9: {=XLOOKUP(C9,'PL TOTAL D0'!K:K,'PL TOTAL D0'!L:L,"")}
A10: XP | B10: Alessandra Carneiro Macedo | C10: 19806802 | D10: Investeseg | E10: BA | F10: Murilo Silva | G10: =IFS($AZ$3:$AZ$993<=250000,"David",$AZ$3:$AZ$993<=800000,"Gabriel", $AZ$3:$AZ$993>800000,"Marcus") -> David | H10: Pode Operar | I10: ------ | J10: =IF(Q10=0,"Não","Sim") -> Sim | K10: 46237 | M10: CON | N10: 0.012 | O10: ------ | P10: 0 | Q10: Mínimo 80% em RF, até 10% em Ações e até 10% em FIIs (04/08/2026) | S10: PF | T10: 873.300.835-34 | U10: 71 99139-1066 | V10: sanmacedo@hotmail.com | W10: 27502 | X10: BA | Y10: =IFS(H:H="Encerrado","Encerrado",COUNTBLANK(AF10:AN10)>0,"Ativo",SUM(AF10:AN10)=0,"Inativo",SUM(AF10:AN10)>0,"Ativo") -> Ativo | AA10: Moderado
A11: XP | B11: Alessandra Sado | C11: 3437690 | D11: VcInvest | E11: GO | F11: Bruno Ribeiro | G11: =IFS($AZ$3:$AZ$993<=250000,"David",$AZ$3:$AZ$993<=800000,"Gabriel", $AZ$3:$AZ$993>800000,"Marcus") -> David | H11: Inativo | I11: STVM Saída | J11: =IF(Q11=0,"Não","Sim") -> Sim | K11: 45784 | M11: INC | N11: 0.012 | O11: ------ | P11: 0 | Q11: 100K D+0 (25/09/2025) | S11: PF | T11: 788.043.611-15 | U11: (62) - 981390612 | V11: alessandrasado@gmail.com | W11: 27672 | X11: GO | Y11: =IFS(H:H="Encerrado","Encerrado",COUNTBLANK(AF11:AN11)>0,"Ativo",SUM(AF11:AN11)=0,"Inativo",SUM(AF11:AN11)>0,"Ativo") -> Ativo | AA11: Moderado | AD11: 45784 | AE11: 49075100018881 | AL11: 296761.76 | AM11: 381929.51 | AN11: 387089.81 | AO11: 463084.67 | AP11: 764733.3 | AQ11: 998361.6 | AR11: 1017662.9 | AS11: 1063337.8 | AT11: 1187509.4 | AU11: 1226246.6 | AV11: 1231186.8 | AW11: 1254526.1 | AX11: 309501.7 | AY11: 84.71 | AZ11: {=XLOOKUP(C11,'PL TOTAL D0'!K:K,'PL TOTAL D0'!L:L,"")} -> 84.71
A12: XP | B12: Alessandra Gomes Moreira | C12: 17005019 | D12: Bluemetrix | E12: GO | F12: Felipe Rios | G12: =IFS($AZ$3:$AZ$993<=250000,"David",$AZ$3:$AZ$993<=800000,"Gabriel", $AZ$3:$AZ$993>800000,"Marcus") -> David | H12: Ativo | I12: ------ | J12: =IF(Q12=0,"Não","Sim") -> Não | K12: 45883 | M12: INC | N12: 0.012 | O12: ------ | P12: 0 | S12: PF | T12: 017.663.181-00 | U12: (62) - 98114-3812 | V12: ales232009@hotmail.com | W12: 31485 | X12: GO | Y12: =IFS(H:H="Encerrado","Encerrado",COUNTBLANK(AF12:AN12)>0,"Ativo",SUM(AF12:AN12)=0,"Inativo",SUM(AF12:AN12)>0,"Ativo") -> Ativo | AD12: 45883 | AE12: 49075100019312 | AN12: 46050.75 | AO12: 46603.716 | AP12: 47377.363 | AQ12: 42288.847 | AR12: 46492.169 | AS12: 45078.08 | AT12: 62809.19 | AU12: 61457.708 | AV12: 59178.075 | AW12: 60048.97 | AX12: 57448.968 | AY12: 51003.349 | AZ12: {=XLOOKUP(C12,'PL TOTAL D0'!K:K,'PL TOTAL D0'!L:L,"")} -> 51878.17
A13: XP | B13: Alisson Juliani | C13: 4427733 | D13: MI Smart | E13: DF | F13: Mariana Rocha | G13: =IFS($AZ$3:$AZ$993<=250000,"David",$AZ$3:$AZ$993<=800000,"Gabriel", $AZ$3:$AZ$993>800000,"Marcus") -> Gabriel | H13: Ativo | I13: ------ | J13: =IF(Q13=0,"Não","Sim") -> Sim | K13: 45712 | M13: INC | N13: 0.012 | O13: ------ | P13: 0 | Q13: 80K D+0 (28/03/2025) | S13: PF | T13: 047.370.621-03 | U13: (61) - 999885741 | V13: alissonjuliani@yahoo.com.br | W13: 35352 | X13: DF | Y13: =IFS(H:H="Encerrado","Encerrado",COUNTBLANK(AF13:AN13)>0,"Ativo",SUM(AF13:AN13)=0,"Inativo",SUM(AF13:AN13)>0,"Ativo") -> Ativo | AA13: Conservador | AD13: 45712 | AE13: 49075100017948 | AI13: 369727.53 | AJ13: 371726.17 | AK13: 376066.13 | AL13: 379733.97 | AM13: 383596.6 | AN13: 388142.84 | AO13: 392144.77 | AP13: 396575.13 | AQ13: 400608 | AR13: 381042.68 | AS13: 385209.41 | AT13: 389350.51 | AU13: 342128.48 | AV13: 266280.9 | AW13: 260939.47 | AX13: 263765.29 | AY13: 266577.03 | AZ13: {=XLOOKUP(C13,'PL TOTAL D0'!K:K,'PL TOTAL D0'!L:L,"")} -> 269505.74
A14: XP | B14: Amanda Borges Campos | C14: 5568034 | D14: Bluemetrix | E14: GO | F14: Rafael Vilela | G14: =IFS($AZ$3:$AZ$993<=250000,"David",$AZ$3:$AZ$993<=800000,"Gabriel", $AZ$3:$AZ$993>800000,"Marcus") -> David | H14: Ativo | I14: ------ | J14: =IF(Q14=0,"Não","Sim") -> Não | K14: 45730 | M14: INC | N14: 0.012 | O14: ------ | P14: 0 | S14: PF | T14: 044.333.031-00 | X14: GO | Y14: =IFS(H:H="Encerrado","Encerrado",COUNTBLANK(AF14:AN14)>0,"Ativo",SUM(AF14:AN14)=0,"Inativo",SUM(AF14:AN14)>0,"Ativo") -> Ativo | AA14: Conservador | AD14: 45730 | AE14: 49075100018502 | AJ14: 9515.3716 | AK14: 25798.926 | AL14: 25908.216 | AM14: 26142.896 | AN14: 26351.775 | AO14: 26578.131 | AP14: 27402.458 | AQ14: 27701.615 | AR14: 27774.748 | AS14: 27551.138 | AT14: 27851.822 | AU14: 28065.402 | AV14: 28175.53 | AW14: 28529.51 | AX14: 28754.057 | AY14: 29046.359 | AZ14: {=XLOOKUP(C14,'PL TOTAL D0'!K:K,'PL TOTAL D0'!L:L,"")} -> 29674.06
A15: XP | B15: Amanda Costa Da Silva Vitorino | C15: 15705827 | D15: MI Smart | E15: DF | F15: Mariana Rocha | G15: =IFS($AZ$3:$AZ$993<=250000,"David",$AZ$3:$AZ$993<=800000,"Gabriel", $AZ$3:$AZ$993>800000,"Marcus") -> Marcus | H15: Encerrado | I15: ------ | J15: =IF(Q15=0,"Não","Sim") -> Sim | K15: 45726 | L15: 46084 | M15: FUND | N15: 0.005 | O15: ------ | P15: 0 | Q15: Alocar vencimentos em LIQUIDEZ DIÁRIA (30/01/2026) | S15: PF | T15: 074.060.546-10 | U15: (0)0 | V15: amandacsv14@gmail.com | W15: 31273 | X15: DF | Y15: =IFS(H:H="Encerrado","Encerrado",COUNTBLANK(AF15:AN15)>0,"Ativo",SUM(AF15:AN15)=0,"Inativo",SUM(AF15:AN15)>0,"Ativo") -> Encerrado | AA15: Conservador | AD15: 45726 | AE15: 49075100018456 | AJ15: 444403.44 | AK15: 454393.62 | AL15: 468314.8 | AM15: 473379.6 | AN15: 497421.85 | AO15: 503047.76 | AP15: 508694.18 | AQ15: 537212.04 | AR15: 541065.04 | AS15: 544818.23 | AT15: 348066.09 | AU15: 543226.83 | AV15: 0 | AW15: 0 | AX15: 0 | AY15: 0 | AZ15: {=XLOOKUP(C15,'PL TOTAL D0'!K:K,'PL TOTAL D0'!L:L,"")}
A16: XP | B16: Ana Lydia De Araujo Nabuth | C16: 7656240 | D16: Expert | E16: GO | F16: Paula Bonfim | G16: =IFS($AZ$3:$AZ$993<=250000,"David",$AZ$3:$AZ$993<=800000,"Gabriel", $AZ$3:$AZ$993>800000,"Marcus") -> Gabriel | H16: Ativo | I16: ------ | J16: =IF(Q16=0,"Não","Sim") -> Não | K16: 45833 | M16: INC | N16: 0.012 | O16: ------ | P16: 0 | S16: PF | T16: 030.604.661-06 | U16: (62) - 981794495 | V16: analydianabuth@gmail.com | W16: 34957 | X16: GO | Y16: =IFS(H:H="Encerrado","Encerrado",COUNTBLANK(AF16:AN16)>0,"Ativo",SUM(AF16:AN16)=0,"Inativo",SUM(AF16:AN16)>0,"Ativo") -> Ativo | AA16: Conservador | AD16: 45833 | AE16: 49075100019207 | AM16: 500044.62 | AN16: 501498.4 | AO16: 502594.46 | AP16: 508375.14 | AQ16: 520906.1 | AR16: 519396.16 | AS16: 524547.48 | AT16: 533645.15 | AU16: 547787.14 | AV16: 441454.22 | AW16: 456203.25 | AX16: 465304.37 | AY16: 466459.86 | AZ16: {=XLOOKUP(C16,'PL TOTAL D0'!K:K,'PL TOTAL D0'!L:L,"")} -> 469544.14
A17: XP | B17: Andre Gustavo Fleury de Melo | C17: 8580102 | D17: Expert | E17: GO | F17: Paula Bonfim | G17: =IFS($AZ$3:$AZ$993<=250000,"David",$AZ$3:$AZ$993<=800000,"Gabriel", $AZ$3:$AZ$993>800000,"Marcus") -> Marcus | H17: Ativo | I17: ------ | J17: =IF(Q17=0,"Não","Sim") -> Sim | K17: 45821 | M17: INC | N17: 0.012 | O17: ------ | P17: 0 | Q17: Vencimentos em D+0 (05/12/2025) | S17: PF | T17: 607.434.331-49 | U17: (62) - 984118004 | V17: andrefleury2@hotmail.com | W17: 25956 | X17: GO | Y17: =IFS(H:H="Encerrado","Encerrado",COUNTBLANK(AF17:AN17)>0,"Ativo",SUM(AF17:AN17)=0,"Inativo",SUM(AF17:AN17)>0,"Ativo") -> Ativo | AA17: Moderado | AD17: 45821 | AE17: 49075100019169 | AM17: 710643.4 | AN17: 714304.59 | AO17: 720627.4 | AP17: 706241.39 | AQ17: 713850.84 | AR17: 718900.67 | AS17: 719862.35 | AT17: 724552.07 | AU17: 927511.88 | AV17: 937286.99 | AW17: 844835.34 | AX17: 852704.83 | AY17: 838943.39 | AZ17: {=XLOOKUP(C17,'PL TOTAL D0'!K:K,'PL TOTAL D0'!L:L,"")} -> 848212.88
A18: XP | B18: Anselmo Jose Guimaraes da Silva | C18: 17850264 | D18: Bluemetrix | E18: GO | F18: Vivian | G18: =IFS($AZ$3:$AZ$993<=250000,"David",$AZ$3:$AZ$993<=800000,"Gabriel", $AZ$3:$AZ$993>800000,"Marcus") -> Marcus | H18: Encerrado | I18: ------ | J18: =IF(Q18=0,"Não","Sim") -> Não | K18: 45756 | L18: 45847 | M18: INC | N18: 0.012 | O18: ------ | P18: 0 | S18: PF | T18: 030.307.477-94 | X18: RJ | Y18: =IFS(H:H="Encerrado","Encerrado",COUNTBLANK(AF18:AN18)>0,"Ativo",SUM(AF18:AN18)=0,"Inativo",SUM(AF18:AN18)>0,"Ativo") -> Encerrado | AA18: Conservador | AD18: 45769 | AE18: 49075100018928 | AK18: 110273.54 | AL18: 285604.78 | AM18: 288658.57 | AN18: 0 | AO18: 0 | AP18: 0 | AQ18: 0 | AR18: 0 | AS18: 0 | AT18: 0 | AU18: 0 | AV18: 0 | AW18: 0 | AX18: 0 | AY18: 0 | AZ18: {=XLOOKUP(C18,'PL TOTAL D0'!K:K,'PL TOTAL D0'!L:L,"")}
A19: XP | B19: Augusto Rolim Da Silva Neto | C19: 9023091 | D19: MI Smart | E19: DF | F19: Mariana Rocha | G19: =IFS($AZ$3:$AZ$993<=250000,"David",$AZ$3:$AZ$993<=800000,"Gabriel", $AZ$3:$AZ$993>800000,"Marcus") -> David | H19: Inativo | I19: Resgate Total | J19: =IF(Q19=0,"Não","Sim") -> Sim | K19: 45702 | M19: INC | N19: 0.011 | O19: ------ | P19: 0 | Q19: 50K D+0 (08/05/2026) | S19: PF | T19: 055.220.961-95 | U19: (0)0 | V19: augusto95.rolim@gmail.com | W19: 35046 | X19: DF | Y19: =IFS(H:H="Encerrado","Encerrado",COUNTBLANK(AF19:AN19)>0,"Ativo",SUM(AF19:AN19)=0,"Inativo",SUM(AF19:AN19)>0,"Ativo") -> Ativo | AA19: Conservador | AD19: 45702 | AE19: 49075100018091 | AI19: 396885.81 | AJ19: 405833.04 | AK19: 393951.33 | AL19: 437187.24 | AM19: 410841.05 | AN19: 41173.086 | AO19: 132763.93 | AP19: 64315.29 | AQ19: 65499.14 | AR19: 65726.35 | AS19: 66548.77 | AT19: 168332.99 | AU19: 169570.08 | AV19: 169380.12 | AW19: 173620.7 | AX19: 175402.46 | AY19: 176538.8 | AZ19: {=XLOOKUP(C19,'PL TOTAL D0'!K:K,'PL TOTAL D0'!L:L,"")} -> 178591.12
A20: XP | B20: Bruna Satyro Sa Ribeiro Fritzsche | C20: 3525456 | D20: Bluemetrix | E20: DF | F20: Bluemetrix Asset | G20: =IFS($AZ$3:$AZ$993<=250000,"David",$AZ$3:$AZ$993<=800000,"Gabriel", $AZ$3:$AZ$993>800000,"Marcus") -> David | H20: Encerrado | I20: ------ | J20: =IF(Q20=0,"Não","Sim") -> Não | K20: 45840 | L20: 46232 | M20: INC | N20: 0.007 | O20: ------ | P20: 0 | S20: PF | T20: 058.788.991-83 | U20: (61) - 986025150 | V20: brunasatyro@gmail.com | W20: 36203 | X20: RJ | Y20: =IFS(H:H="Encerrado","Encerrado",COUNTBLANK(AF20:AN20)>0,"Ativo",SUM(AF20:AN20)=0,"Inativo",SUM(AF20:AN20)>0,"Ativo") -> Encerrado | AA20: Moderado | AD20: 45840 | AE20: 49075100019029 | AN20: 59296.059 | AO20: 59157.312 | AP20: 59682.38 | AQ20: 60484.884 | AR20: 61114.798 | AS20: 61777.745 | AT20: 56259.231 | AU20: 56041.043 | AV20: 19269.567 | AW20: 0 | AX20: 0 | AY20: 0 | AZ20: {=XLOOKUP(C20,'PL TOTAL D0'!K:K,'PL TOTAL D0'!L:L,"")} -> 0
A21: XP | B21: Bruno Henrique Borges Silva | C21: 13606804 | D21: Bluemetrix | E21: DF | F21: Bruno Henrique | G21: =IFS($AZ$3:$AZ$993<=250000,"David",$AZ$3:$AZ$993<=800000,"Gabriel", $AZ$3:$AZ$993>800000,"Marcus") -> David | H21: Inativo | I21: Monitoramento | J21: =IF(Q21=0,"Não","Sim") -> Não | K21: 45695 | M21: MONT | N21: 0 | O21: ------ | P21: 0 | S21: PF | T21: 052.062.741-51 | U21: (61) - 982666915 | V21: brunoh.borgess@gmail.com | W21: 34915 | X21: DF | Y21: =IFS(H:H="Encerrado","Encerrado",COUNTBLANK(AF21:AN21)>0,"Ativo",SUM(AF21:AN21)=0,"Inativo",SUM(AF21:AN21)>0,"Ativo") -> Ativo | AA21: Arrojado | AJ21: 0 | AK21: 0 | AL21: 0 | AM21: 0 | AN21: 0 | AO21: 0 | AP21: 0.71 | AQ21: 0.71 | AR21: 0.71 | AS21: 0.71 | AT21: 0 | AU21: 0.71 | AV21: 0.71 | AW21: 0.71 | AX21: 0.71 | AY21: 0.71 | AZ21: {=XLOOKUP(C21,'PL TOTAL D0'!K:K,'PL TOTAL D0'!L:L,"")} -> 0
A22: XP | B22: Bruno Ribeiro Abreu | C22: 8424641 | D22: VcInvest | E22: GO | F22: Bruno Ribeiro | G22: =IFS($AZ$3:$AZ$993<=250000,"David",$AZ$3:$AZ$993<=800000,"Gabriel", $AZ$3:$AZ$993>800000,"Marcus") -> Gabriel | H22: Ativo | I22: ------ | J22: =IF(Q22=0,"Não","Sim") -> Sim | K22: 45623 | M22: INC | N22: 0.012 | O22: ------ | P22: 0 | Q22: Máx 10% CrPr (29/11/2024) | S22: PF | T22: 804.326.701-49 | U22: (62) - 34348150 | V22: bruno@voceinvest.com.br | W22: 27960 | X22: GO | Y22: =IFS(H:H="Encerrado","Encerrado",COUNTBLANK(AF22:AN22)>0,"Ativo",SUM(AF22:AN22)=0,"Inativo",SUM(AF22:AN22)>0,"Ativo") -> Ativo | AA22: Arrojado | AD22: 45660 | AE22: 49075100016534 | AF22: 311435.22 | AG22: 409519.53 | AH22: 413586.91 | AI22: 417045.68 | AJ22: 421731.13 | AK22: 415740.18 | AL22: 419576.75 | AM22: 423366.34 | AN22: 427853.49 | AO22: 431884.16 | AP22: 408357.02 | AQ22: 412864.18 | AR22: 415940.87 | AS22: 416328.48 | AT22: 420729.22 | AU22: 424134.05 | AV22: 429294.41 | AW22: 413808.52 | AX22: 312476.2 | AY22: 315732.36 | AZ22: {=XLOOKUP(C22,'PL TOTAL D0'!K:K,'PL TOTAL D0'!L:L,"")} -> 319256.74
A23: XP | B23: Camila Amanda Barboza Taveira | C23: 5637768 | D23: Bluemetrix | E23: DF | F23: Bluemetrix Asset | G23: =IFS($AZ$3:$AZ$993<=250000,"David",$AZ$3:$AZ$993<=800000,"Gabriel", $AZ$3:$AZ$993>800000,"Marcus") -> Marcus | H23: Ativo | I23: ------ | J23: =IF(Q23=0,"Não","Sim") -> Sim | K23: 45622 | M23: CON | N23: 0.008 | O23: CDI | P23: 0.1 | Q23: Não vender ações do Itaú. (Qnt: 70.000), migrar vencimentos para o BTG (25/07/2025) | S23: PF | T23: 347.172.368-40 | U23: (12) - 981173842 | V23: fabioecamilataveira@gmail.com | W23: 31531 | X23: SP | Y23: =IFS(H:H="Encerrado","Encerrado",COUNTBLANK(AF23:AN23)>0,"Ativo",SUM(AF23:AN23)=0,"Inativo",SUM(AF23:AN23)>0,"Ativo") -> Ativo | AA23: Moderado | AD23: 45663 | AE23: 49075100016585 | AF23: 6107837.4 | AG23: 6077950.2 | AH23: 6240279.7 | AI23: 6774562.8 | AJ23: 6316051.3 | AK23: 6577010.7 | AL23: 6674417.3 | AM23: 6639839.8 | AN23: 6446945.7 | AO23: 6665966.4 | AP23: 1941447.2 | AQ23: 1949539 | AR23: 1978211.6 | AS23: 1973461.3 | AT23: 1932433.6 | AU23: 1937534.1 | AV23: 1956460.6 | AW23: 1959308.4 | AX23: 1964940.2 | AY23: 1964100.1 | AZ23: {=XLOOKUP(C23,'PL TOTAL D0'!K:K,'PL TOTAL D0'!L:L,"")} -> 1970547.8
A24: XP | B24: Camila Silva Fracalacci | C24: 11451861 | D24: Poupinvista | E24: DF | F24: Bruno Rodrigues | G24: =IFS($AZ$3:$AZ$993<=250000,"David",$AZ$3:$AZ$993<=800000,"Gabriel", $AZ$3:$AZ$993>800000,"Marcus") -> David | H24: Ativo | I24: ------ | J24: =IF(Q24=0,"Não","Sim") -> Não | K24: 45870 | M24: INC | N24: 0.012 | O24: ------ | P24: 0 | S24: PF | T24: 383.515.408-70 | U24: (11) - 993845423 | V24: camilasfracalacci@gmail.com | W24: 33821 | X24: DF | Y24: =IFS(H:H="Encerrado","Encerrado",COUNTBLANK(AF24:AN24)>0,"Ativo",SUM(AF24:AN24)=0,"Inativo",SUM(AF24:AN24)>0,"Ativo") -> Ativo | AA24: Moderado | AD24: 45870 | AE24: 49075100019339 | AN24: 43941.934 | AO24: 44302.523 | AP24: 46176.054 | AQ24: 46661.658 | AR24: 46718.792 | AS24: 44975.25 | AT24: 64124.562 | AU24: 35990.576 | AV24: 36219.214 | AW24: 36508.55 | AX24: 37508.292 | AY24: 37641.45 | AZ24: {=XLOOKUP(C24,'PL TOTAL D0'!K:K,'PL TOTAL D0'!L:L,"")} -> 39998.325
A25: XP | B25: Cecilia Brasseiro Moreira Bove | C25: 19492633 | D25: Expert | E25: GO | F25: Thanira Moreira | G25: =IFS($AZ$3:$AZ$993<=250000,"David",$AZ$3:$AZ$993<=800000,"Gabriel", $AZ$3:$AZ$993>800000,"Marcus") -> David | H25: Ativo | I25: ------ | J25: =IF(Q25=0,"Não","Sim") -> Não | K25: 46149 | M25: CON | N25: 0.012 | O25: CDI | P25: 0.1 | S25: PF | T25: 995.073.401-06 | U25: 61 98140-0320 | V25: cissabrasseiro@hotmail.com | W25: 30563 | X25: DF | Y25: =IFS(H:H="Encerrado","Encerrado",COUNTBLANK(AF25:AN25)>0,"Ativo",SUM(AF25:AN25)=0,"Inativo",SUM(AF25:AN25)>0,"Ativo") -> Ativo | AA25: Moderado | AW25: 0 | AX25: 0 | AY25: 0 | AZ25: {=XLOOKUP(C25,'PL TOTAL D0'!K:K,'PL TOTAL D0'!L:L,"")} -> 0
A26: XP | B26: Cesar Augusto Angeli de Lima | C26: 3732278 | D26: Expert | E26: GO | F26: André de Queiroz Coelho | G26: =IFS($AZ$3:$AZ$993<=250000,"David",$AZ$3:$AZ$993<=800000,"Gabriel", $AZ$3:$AZ$993>800000,"Marcus") -> Gabriel | H26: Ativo | I26: ------ | J26: =IF(Q26=0,"Não","Sim") -> Não | K26: 45734 | M26: MOD | N26: 0.015 | O26: CDI | P26: 0.1 | R26: Alteração de carteira finalizada (18/12/2025) | S26: PF | T26: 422.256.202-53 | U26: (69) - 992252325 | V26: cesar.angeli@yahoo.com.br | W26: 27814 | X26: RO | Y26: =IFS(H:H="Encerrado","Encerrado",COUNTBLANK(AF26:AN26)>0,"Ativo",SUM(AF26:AN26)=0,"Inativo",SUM(AF26:AN26)>0,"Ativo") -> Ativo | AA26: Moderado | AD26: 45734 | AE26: 49075100018510 | AJ26: 210598.88 | AK26: 313319.99 | AL26: 321608.3 | AM26: 324799.95 | AN26: 333577.18 | AO26: 336652.59 | AP26: 340201.69 | AQ26: 344117.81 | AR26: 326576.75 | AS26: 314783.41 | AT26: 319503.8 | AU26: 301912.14 | AV26: 284214.94 | AW26: 285115.24 | AX26: 326013.13 | AY26: 329772.68 | AZ26: {=XLOOKUP(C26,'PL TOTAL D0'!K:K,'PL TOTAL D0'!L:L,"")} -> 308967.77
A27: XP | B27: Claudio Lima Camara | C27: 3144426 | D27: MI Smart | E27: DF | F27: Mariana Rocha | G27: =IFS($AZ$3:$AZ$993<=250000,"David",$AZ$3:$AZ$993<=800000,"Gabriel", $AZ$3:$AZ$993>800000,"Marcus") -> David | H27: Inativo | I27: Resgate Total | J27: =IF(Q27=0,"Não","Sim") -> Sim | K27: 45757 | M27: INC | N27: 0.012 | O27: ------ | P27: 0 | Q27: 300K D+0 (10/04/2025) | S27: PF | T27: 152.979.931-72 | U27: (61) - 992896324 | V27: bykraw@gmail.com | W27: 22067 | X27: DF | Y27: =IFS(H:H="Encerrado","Encerrado",COUNTBLANK(AF27:AN27)>0,"Ativo",SUM(AF27:AN27)=0,"Inativo",SUM(AF27:AN27)>0,"Ativo") -> Ativo | AA27: Moderado | AD27: 45757 | AE27: 49075100018693 | AK27: 472901.29 | AL27: 567332.05 | AM27: 572937.39 | AN27: 578373.72 | AO27: 584363.41 | AP27: 82874.624 | AQ27: 32832.17 | AR27: 33133.545 | AS27: 33519.368 | AT27: 33109.219 | AU27: 0 | AV27: 1.06 | AW27: 1.06 | AX27: 1.06 | AY27: 1.06 | AZ27: {=XLOOKUP(C27,'PL TOTAL D0'!K:K,'PL TOTAL D0'!L:L,"")} -> 0
A28: XP | B28: Claudio Queiroz Mundim | C28: 2738150 | D28: VcInvest | E28: GO | F28: Bruno Ribeiro | G28: =IFS($AZ$3:$AZ$993<=250000,"David",$AZ$3:$AZ$993<=800000,"Gabriel", $AZ$3:$AZ$993>800000,"Marcus") -> Gabriel | H28: Ativo | I28: Monitoramento | J28: =IF(Q28=0,"Não","Sim") -> Não | K28: 45908 | M28: MOD / GR | N28: 0.015 | O28: ------ | P28: 0 | S28: PF | T28: 199.124.716-87 | U28: 62 98286-0550 | V28: karen.neves.edwards@gmail.com | W28: 18801 | X28: RJ | Y28: Ativo | AA28: Arrojado | AD28: 45908 | AE28: 49075100019398 | AN28: 481220.52 | AO28: 500103.74 | AP28: 507814.25 | AQ28: 515065.19 | AR28: 533265.11 | AS28: 553081.56 | AT28: 606502.58 | AU28: 649668.82 | AV28: 676664.1 | AW28: 676651.22 | AX28: 637532.11 | AY28: 622157.93 | AZ28: {=XLOOKUP(C28,'PL TOTAL D0'!K:K,'PL TOTAL D0'!L:L,"")} -> 643437.77
A29: XP | B29: Cristovam da Silva Pinheiro | C29: 19771047 | D29: Investeseg | E29: BA | F29: Murilo Silva | G29: =IFS($AZ$3:$AZ$993<=250000,"David",$AZ$3:$AZ$993<=800000,"Gabriel", $AZ$3:$AZ$993>800000,"Marcus") -> David | H29: Ativo | I29: ------ | J29: =IF(Q29=0,"Não","Sim") -> Não | K29: 46225 | M29: PREV CON | N29: 0.007 | O29: ------ | P29: 0 | S29: PF | T29: 073.539.795-34 | U29: 71 99125-3703 | V29: cspinheiro64@gmail.com | W29: 18671 | X29: BA | Y29: Ativo | AA29: Moderado
A30: XP | B30: Daniela Ferreira Salomão Pontes | C30: 3723914 | D30: Bluemetrix | E30: DF | F30: Thiago Canabrava | G30: =IFS($AZ$3:$AZ$993<=250000,"David",$AZ$3:$AZ$993<=800000,"Gabriel", $AZ$3:$AZ$993>800000,"Marcus") -> Marcus | H30: Ativo | I30: ------ | J30: =IF(Q30=0,"Não","Sim") -> Não | K30: 45630 | M30: INC | N30: 0.007 | O30: ------ | P30: 0 | S30: PF | T30: 526.535.956-72 | U30: (61) - 984233355 | V30: danielasalomaobsb@gmail.com | W30: 23909 | X30: DF | Y30: =IFS(H:H="Encerrado","Encerrado",COUNTBLANK(AF30:AN30)>0,"Ativo",SUM(AF30:AN30)=0,"Inativo",SUM(AF30:AN30)>0,"Ativo") -> Ativo | AA30: Moderado | AD30: 45665 | AE30: 49075100016542 | AF30: 0 | AG30: 124287.46 | AH30: 201011.76 | AI30: 229261.03 | AJ30: 231110 | AK30: 233745.22 | AL30: 234857.93 | AM30: 236134.53 | AN30: 638163.69 | AO30: 644489.51 | AP30: 750774.88 | AQ30: 834333.53 | AR30: 840504.44 | AS30: 848808.16 | AT30: 861156.35 | AU30: 866685.82 | AV30: 876608.61 | AW30: 1508787.5 | AX30: 1520122.2 | AY30: 1534974.4 | AZ30: {=XLOOKUP(C30,'PL TOTAL D0'!K:K,'PL TOTAL D0'!L:L,"")} -> 1548957.3
A31: XP | B31: Danielle Borges Siqueira Rodrigues | C31: 3862487 | D31: MI Smart | E31: DF | F31: Mariana Rocha | G31: =IFS($AZ$3:$AZ$993<=250000,"David",$AZ$3:$AZ$993<=800000,"Gabriel", $AZ$3:$AZ$993>800000,"Marcus") -> David | H31: Ativo | I31: ------ | J31: =IF(Q31=0,"Não","Sim") -> Sim | K31: 45706 | M31: INC | N31: 0.012 | O31: ------ | P31: 0 | Q31: 50K D+0/ Manter fundo Kinea Alpes (24/03/2025) | S31: PF | T31: 001.924.551-33 | U31: (61) - 991192492 | V31: daniellebsiqueira@gmail.com | W31: 30877 | X31: DF | Y31: =IFS(H:H="Encerrado","Encerrado",COUNTBLANK(AF31:AN31)>0,"Ativo",SUM(AF31:AN31)=0,"Inativo",SUM(AF31:AN31)>0,"Ativo") -> Ativo | AA31: Conservador | AD31: 45706 | AE31: 49075100017875 | AI31: R$ 229.321,34 | AJ31: R$ 233.521,47 | AK31: R$ 238.335,75 | AL31: R$ 243.126,65 | AM31: R$ 207.530,08 | AN31: R$ 80.376,55 | AO31: R$ 83.763,47 | AP31: R$ 85.649,80 | AQ31: 87768.349 | AR31: 90401.95 | AS31: 89573.02 | AT31: 94375.4 | AU31: 95573.75 | AV31: 95882.85 | AW31: 95875.58 | AX31: 94050.49 | AY31: 94839.91 | AZ31: {=XLOOKUP(C31,'PL TOTAL D0'!K:K,'PL TOTAL D0'!L:L,"")} -> 93858.81
A32: XP | B32: Davi Amaral Lopes | C32: 19228697 | D32: Expert | E32: GO | F32: Alcivana Marques | G32: =IFS($AZ$3:$AZ$993<=250000,"David",$AZ$3:$AZ$993<=800000,"Gabriel", $AZ$3:$AZ$993>800000,"Marcus") -> Marcus | H32: Encerrado | I32: ------ | J32: =IF(Q32=0,"Não","Sim") -> Não | K32: 46090 | L32: 46155 | M32: CON | N32: 0.012 | O32: ------ | P32: 0 | R32: Distrato unilateral | S32: PF | T32: 042.582.051-33 | U32: 62 98335-6701 | V32: daviamarallopes@outlook.com | W32: 36169 | X32: GO | Y32: =IFS(H:H="Encerrado","Encerrado",COUNTBLANK(AF32:AN32)>0,"Ativo",SUM(AF32:AN32)=0,"Inativo",SUM(AF32:AN32)>0,"Ativo") -> Encerrado | AA32: Moderado | AV32: 0 | AW32: 0 | AX32: 0 | AY32: 0 | AZ32: {=XLOOKUP(C32,'PL TOTAL D0'!K:K,'PL TOTAL D0'!L:L,"")}
A33: XP | B33: David Tae Hwan Kim | C33: 3977611 | D33: MI Smart | E33: DF | F33: Mariana Rocha | G33: =IFS($AZ$3:$AZ$993<=250000,"David",$AZ$3:$AZ$993<=800000,"Gabriel", $AZ$3:$AZ$993>800000,"Marcus") -> David | H33: Inativo | I33: Resgate Total | J33: =IF(Q33=0,"Não","Sim") -> Sim | K33: 45716 | M33: INC | N33: 0.012 | O33: ------ | P33: 0 | Q33: 50K D+0 (28/03/2025) | S33: PF | T33: 021.648.571-19 | U33: (61) - 991016516 | V33: davidkim63@gmail.com | W33: 36179 | X33: DF | Y33: =IFS(H:H="Encerrado","Encerrado",COUNTBLANK(AF33:AN33)>0,"Ativo",SUM(AF33:AN33)=0,"Inativo",SUM(AF33:AN33)>0,"Ativo") -> Ativo | AA33: Conservador | AD33: 45716 | AE33: 49075100017980 | AI33: 51377.12 | AJ33: 51610.236 | AK33: 21457.53 | AL33: 16882.55 | AM33: 3002.96 | AN33: 590.33 | AO33: 0.44 | AP33: 0.44 | AQ33: 0.44 | AR33: 0.44 | AS33: 0.44 | AT33: 0.44 | AU33: 0.44 | AV33: 0.44 | AW33: 0.44 | AX33: 0.44 | AY33: 0.44 | AZ33: {=XLOOKUP(C33,'PL TOTAL D0'!K:K,'PL TOTAL D0'!L:L,"")} -> 0
A34: XP | B34: Diana Maria Nunes | C34: 2209353 | D34: MI Smart | E34: DF | F34: Mariana Rocha | G34: =IFS($AZ$3:$AZ$993<=250000,"David",$AZ$3:$AZ$993<=800000,"Gabriel", $AZ$3:$AZ$993>800000,"Marcus") -> David | H34: Ativo | I34: ------ | J34: =IF(Q34=0,"Não","Sim") -> Não | K34: 45863 | M34: INC | N34: 0.012 | O34: ------ | P34: 0 | S34: PF | T34: 440.599.733-00 | U34: (61) - 981765788 | V34: dianan@mpf.mp.br | W34: 25427 | X34: DF | Y34: =IFS(H:H="Encerrado","Encerrado",COUNTBLANK(AF34:AN34)>0,"Ativo",SUM(AF34:AN34)=0,"Inativo",SUM(AF34:AN34)>0,"Ativo") -> Ativo | AA34: Conservador | AD34: 45863 | AE34: 49075100019096 | AN34: 271370.1 | AO34: 273663.13 | AP34: 277181.55 | AQ34: 280322.19 | AR34: 26762.66 | AS34: 26987.96 | AT34: 27271.87 | AU34: 27512.29 | AV34: 27826.66 | AW34: 28094.12 | AX34: 28090.25 | AY34: 28372.43 | AZ34: {=XLOOKUP(C34,'PL TOTAL D0'!K:K,'PL TOTAL D0'!L:L,"")} -> 28700.55
A35: XP | B35: Domingos Jose Arantes | C35: 2570963 | D35: VcInvest | E35: GO | F35: Bruno Ribeiro | G35: =IFS($AZ$3:$AZ$993<=250000,"David",$AZ$3:$AZ$993<=800000,"Gabriel", $AZ$3:$AZ$993>800000,"Marcus") -> Marcus | H35: Ativo | I35: ------ | J35: =IF(Q35=0,"Não","Sim") -> Não | K35: 45671 | M35: INC | N35: 0.012 | O35: ------ | P35: 0 | S35: PF | T35: 060.268.181-20 | U35: (62) - 999808750 | V35: domingosd.arantes@gmail.com | W35: 18064 | X35: GO | Y35: =IFS(H:H="Encerrado","Encerrado",COUNTBLANK(AF35:AN35)>0,"Ativo",SUM(AF35:AN35)=0,"Inativo",SUM(AF35:AN35)>0,"Ativo") -> Ativo | AA35: Moderado | AD35: 45665 | AE35: 49075100016593 | AH35: 992468.25 | AI35: 991333.26 | AJ35: 979193 | AK35: 956771.24 | AL35: 953735.52 | AM35: 960688.2 | AN35: 946639.22 | AO35: 941355.93 | AP35: 941352.53 | AQ35: 922097.22 | AR35: 918323.95 | AS35: 916152.41 | AT35: 901147.74 | AU35: 876127.28 | AV35: 871476.96 | AW35: 863639.43 | AX35: 852555.2 | AY35: 838668.14 | AZ35: {=XLOOKUP(C35,'PL TOTAL D0'!K:K,'PL TOTAL D0'!L:L,"")} -> 830226.06
A36: XP | B36: Edna Cândida Vasconcelos | C36: 7294113 | D36: Poupinvista | E36: DF | F36: Bruno Rodrigues | G36: =IFS($AZ$3:$AZ$993<=250000,"David",$AZ$3:$AZ$993<=800000,"Gabriel", $AZ$3:$AZ$993>800000,"Marcus") -> David | H36: Ativo | I36: ------ | J36: =IF(Q36=0,"Não","Sim") -> Não | K36: 45947 | M36: FUND | N36: 0.005 | O36: ------ | P36: 0 | S36: PF | T36: 783.140.898-34 | U36: 11 94014-2366 | V36: hedna_sp@yahoo.com.br | W36: 19609 | X36: SP | Y36: =IFS(H:H="Encerrado","Encerrado",COUNTBLANK(AF36:AN36)>0,"Ativo",SUM(AF36:AN36)=0,"Inativo",SUM(AF36:AN36)>0,"Ativo") -> Ativo | AA36: Moderado | AD36: 45947 | AE36: 49075100019592 | AQ36: 30647.666 | AR36: 30834.216 | AS36: 31145.91 | AT36: 29404.7 | AU36: 20507.13 | AV36: 20752.55 | AW36: 21016.88 | AX36: 21112.61 | AY36: 11265.58 | AZ36: {=XLOOKUP(C36,'PL TOTAL D0'!K:K,'PL TOTAL D0'!L:L,"")} -> 11476.64
A37: XP | B37: Edna Souza Bulc | C37: 6548318 | D37: Bluemetrix | E37: DF | F37: Flavio Silva | G37: =IFS($AZ$3:$AZ$993<=250000,"David",$AZ$3:$AZ$993<=800000,"Gabriel", $AZ$3:$AZ$993>800000,"Marcus") -> Marcus | H37: Inativo | I37: Distrato | J37: =IF(Q37=0,"Não","Sim") -> Não | K37: 46064 | M37: PREV CON | N37: 0.007 | O37: ------ | P37: 0 | S37: PF | T37: 040.531.396-94 | U37: 61 98124-2354 | V37: EDNA.BULC@gmail.com | W37: 27158 | X37: DF | Y37: =IFS(H:H="Encerrado","Encerrado",COUNTBLANK(AF37:AN37)>0,"Ativo",SUM(AF37:AN37)=0,"Inativo",SUM(AF37:AN37)>0,"Ativo") -> Ativo | AA37: Conservador | AU37: 0 | AV37: 0 | AW37: 0 | AX37: 0 | AY37: 0 | AZ37: {=XLOOKUP(C37,'PL TOTAL D0'!K:K,'PL TOTAL D0'!L:L,"")}
A38: XP | B38: Edson Juliano Dias Braga | C38: 297338 | D38: Bluemetrix | E38: DF | F38: Jorge Luiz Braga de Carvalho | G38: =IFS($AZ$3:$AZ$993<=250000,"David",$AZ$3:$AZ$993<=800000,"Gabriel", $AZ$3:$AZ$993>800000,"Marcus") -> David | H38: Ativo | I38: ------ | J38: =IF(Q38=0,"Não","Sim") -> Não | K38: 45835 | M38: FUND | N38: 0.005 | O38: ------ | P38: 0 | S38: PF | T38: 009.847.439-10 | U38: (41) - 35981347 | V38: personal_edson@hotmail.com | W38: 31884 | X38: PR | Y38: =IFS(H:H="Encerrado","Encerrado",COUNTBLANK(AF38:AN38)>0,"Ativo",SUM(AF38:AN38)=0,"Inativo",SUM(AF38:AN38)>0,"Ativo") -> Ativo | AA38: Moderado | AD38: 45835 | AE38: 49075100019452 | AM38: 10.22 | AN38: 10.22 | AO38: 10.22 | AP38: 13566.771 | AQ38: 13777.78 | AR38: 13930.78 | AS38: 15291.47 | AT38: 15504.64 | AU38: 17092 | AV38: 17024.56 | AW38: 17367.85 | AX38: 17470.23 | AY38: 17689.74 | AZ38: {=XLOOKUP(C38,'PL TOTAL D0'!K:K,'PL TOTAL D0'!L:L,"")} -> 17803.27
A39: XP | B39: Elton Barroso Rodrigues | C39: 18826594 | D39: MI Smart | E39: DF | F39: Mariana Rocha | G39: =IFS($AZ$3:$AZ$993<=250000,"David",$AZ$3:$AZ$993<=800000,"Gabriel", $AZ$3:$AZ$993>800000,"Marcus") -> Marcus | H39: Ativo | I39: ------ | J39: =IF(Q39=0,"Não","Sim") -> Não | K39: 45978 | M39: INC | N39: 0.012 | O39: ------ | P39: 0 | S39: PF | T39: 450.954.772-20 | U39: 61 99849-9552 | V39: elton2arq@gmail.com | W39: 28009 | X39: DF | Y39: =IFS(H:H="Encerrado","Encerrado",COUNTBLANK(AF39:AN39)>0,"Ativo",SUM(AF39:AN39)=0,"Inativo",SUM(AF39:AN39)>0,"Ativo") -> Ativo | AA39: Conservador | AR39: 0 | AS39: 0 | AT39: 359636.44 | AU39: 1007106.7 | AV39: 1019777.4 | AW39: 1030738.5 | AX39: 1040102.6 | AY39: 1050853.9 | AZ39: {=XLOOKUP(C39,'PL TOTAL D0'!K:K,'PL TOTAL D0'!L:L,"")} -> 1062981.7
A40: XP | B40: Engel Cristina de Carvalho Sociedade Individual De Advocacia | C40: 9290248 | D40: MI Smart | E40: DF | F40: Mariana Rocha | G40: =IFS($AZ$3:$AZ$993<=250000,"David",$AZ$3:$AZ$993<=800000,"Gabriel", $AZ$3:$AZ$993>800000,"Marcus") -> Gabriel | H40: Ativo | I40: ------ | J40: =IF(Q40=0,"Não","Sim") -> Sim | K40: 45707 | M40: INC | N40: 0.012 | O40: ------ | P40: 0 | Q40: 100K D+0 (28/03/2025) | S40: PJ | T40: 29.812.654/0001-00 | U40: (61) - 984879649 | V40: engelccarvalho@gmail.com | W40: PJ | X40: DF | Y40: =IFS(H:H="Encerrado","Encerrado",COUNTBLANK(AF40:AN40)>0,"Ativo",SUM(AF40:AN40)=0,"Inativo",SUM(AF40:AN40)>0,"Ativo") -> Ativo | AA40: Conservador | AD40: 45707 | AE40: 49075100017794 | AI40: 187972.99 | AJ40: 169167.55 | AK40: 169986 | AL40: 201517.36 | AM40: 153212.12 | AN40: 154935.99 | AO40: 156595.13 | AP40: 158241.24 | AQ40: 109429.26 | AR40: 210040.51 | AS40: 212377.07 | AT40: 224602.7 | AU40: 309184.27 | AV40: 282275.75 | AW40: 357637.04 | AX40: 350946.25 | AY40: 424789.45 | AZ40: {=XLOOKUP(C40,'PL TOTAL D0'!K:K,'PL TOTAL D0'!L:L,"")} -> 419119.89
A41: XP | B41: Erika Verediana Ferreira | C41: 19423561 | D41: VcInvest | E41: GO | F41: Bruno Ribeiro | G41: =IFS($AZ$3:$AZ$993<=250000,"David",$AZ$3:$AZ$993<=800000,"Gabriel", $AZ$3:$AZ$993>800000,"Marcus") -> David | H41: Ativo | I41: ------ | J41: =IF(Q41=0,"Não","Sim") -> Não | K41: 46126 | M41: CON | N41: 0.012 | O41: CDI | P41: 0.1 | S41: PF | T41: 768.096.251-00 | U41: 62 99974-0447 | V41: erikavf@gmail.com | W41: 27679 | X41: GO | Y41: =IFS(H:H="Encerrado","Encerrado",COUNTBLANK(AF41:AN41)>0,"Ativo",SUM(AF41:AN41)=0,"Inativo",SUM(AF41:AN41)>0,"Ativo") -> Ativo | AA41: Moderado | AW41: 0 | AX41: 0 | AY41: 0 | AZ41: {=XLOOKUP(C41,'PL TOTAL D0'!K:K,'PL TOTAL D0'!L:L,"")} -> 0
A42: XP | B42: Fabiola Araujo Cordeiro | C42: 4097264 | D42: MI Smart | E42: DF | F42: Mariana Rocha | G42: =IFS($AZ$3:$AZ$993<=250000,"David",$AZ$3:$AZ$993<=800000,"Gabriel", $AZ$3:$AZ$993>800000,"Marcus") -> Gabriel | H42: Ativo | I42: ------ | J42: =IF(Q42=0,"Não","Sim") -> Sim | K42: 45707 | M42: INC | N42: 0.012 | O42: ------ | P42: 0 | Q42: 70K D+0 (28/03/2025) | S42: PF | T42: 893.233.787-04 | U42: (21) - 995596510 | V42: fabiola_cordeiro@yahoo.com.br | W42: 24560 | X42: RJ | Y42: =IFS(H:H="Encerrado","Encerrado",COUNTBLANK(AF42:AN42)>0,"Ativo",SUM(AF42:AN42)=0,"Inativo",SUM(AF42:AN42)>0,"Ativo") -> Ativo | AA42: Conservador | AD42: 45707 | AE42: 49075100018065 | AI42: 640981.78 | AJ42: 633780.24 | AK42: 625774.15 | AL42: 616385.73 | AM42: 617537.34 | AN42: 614859.81 | AO42: 613378.47 | AP42: 591889.05 | AQ42: 597643.24 | AR42: 595088.56 | AS42: 584031.48 | AT42: 587676.83 | AU42: 590162.57 | AV42: 576178.32 | AW42: 587650.97 | AX42: 593100.28 | AY42: 589746.6 | AZ42: {=XLOOKUP(C42,'PL TOTAL D0'!K:K,'PL TOTAL D0'!L:L,"")} -> 592985.78
A43: XP | B43: Fatima Cristina Silva Barreto Franco | C43: 19622653 | D43: Investeseg | E43: BA | F43: Murilo Silva | G43: =IFS($AZ$3:$AZ$993<=250000,"David",$AZ$3:$AZ$993<=800000,"Gabriel", $AZ$3:$AZ$993>800000,"Marcus") -> Gabriel | H43: Ativo | I43: ------ | J43: =IF(Q43=0,"Não","Sim") -> Sim | K43: 46178 | M43: CON/ GR | N43: 0.013 | O43: ------ | P43: 0 | Q43: Resgates mensais 2.500,00 (09/06/2026). | S43: PF | T43: 658.970.565-87 | U43: 73 99122-1138 | V43: laisfranco.agro@yahoo.com.br | W43: 23159 | X43: BA | Y43: =IFS(H:H="Encerrado","Encerrado",COUNTBLANK(AF43:AN43)>0,"Ativo",SUM(AF43:AN43)=0,"Inativo",SUM(AF43:AN43)>0,"Ativo") -> Ativo | AA43: Moderado | AX43: 0 | AY43: 436220.85 | AZ43: {=XLOOKUP(C43,'PL TOTAL D0'!K:K,'PL TOTAL D0'!L:L,"")} -> 464717.22
A44: XP | B44: Fernanda Bruno Ferreira | C44: 3237400 | D44: VcInvest | E44: GO | F44: Bruno Ribeiro | G44: =IFS($AZ$3:$AZ$993<=250000,"David",$AZ$3:$AZ$993<=800000,"Gabriel", $AZ$3:$AZ$993>800000,"Marcus") -> Gabriel | H44: Ativo | I44: ------ | J44: =IF(Q44=0,"Não","Sim") -> Não | K44: 45728 | M44: INC | N44: 0.012 | O44: ------ | P44: 0 | S44: PF | T44: 734.011.101-87 | X44: GO | Y44: =IFS(H:H="Encerrado","Encerrado",COUNTBLANK(AF44:AN44)>0,"Ativo",SUM(AF44:AN44)=0,"Inativo",SUM(AF44:AN44)>0,"Ativo") -> Ativo | AA44: Moderado | AD44: 45728 | AE44: 49075100018472 | AJ44: 317741.35 | AK44: 322001.39 | AL44: 325671.1 | AM44: 327333.75 | AN44: 331482.28 | AO44: 334054.63 | AP44: 337298.31 | AQ44: 341262.59 | AR44: 343172.48 | AS44: 346566.16 | AT44: 350017.51 | AU44: 350742.94 | AV44: 384663.2 | AW44: 388852.84 | AX44: 392125.24 | AY44: 396023.43 | AZ44: {=XLOOKUP(C44,'PL TOTAL D0'!K:K,'PL TOTAL D0'!L:L,"")} -> 400568.41
A45: XP | B45: Fernanda Nunes Alvarenga | C45: 89660 | D45: MI Smart | E45: DF | F45: Mariana Rocha | G45: =IFS($AZ$3:$AZ$993<=250000,"David",$AZ$3:$AZ$993<=800000,"Gabriel", $AZ$3:$AZ$993>800000,"Marcus") -> Gabriel | H45: Ativo | I45: ------ | J45: =IF(Q45=0,"Não","Sim") -> Sim | K45: 45705 | M45: INC | N45: 0.011 | O45: ------ | P45: 0 | Q45: 50K D+0 (28/03/2025) | S45: PF | T45: 012.195.191-03 | U45: (61) - 996612008 | V45: fernanda.alvarengab@gmail.com | W45: 31644 | X45: RJ | Y45: =IFS(H:H="Encerrado","Encerrado",COUNTBLANK(AF45:AN45)>0,"Ativo",SUM(AF45:AN45)=0,"Inativo",SUM(AF45:AN45)>0,"Ativo") -> Ativo | AA45: Conservador | AD45: 45705 | AE45: 49075100017891 | AI45: 249908.6 | AJ45: 245850.09 | AK45: 249873.62 | AL45: 258233.12 | AM45: 261332.05 | AN45: 263206.27 | AO45: 267162.96 | AP45: 274297.72 | AQ45: 277952.35 | AR45: 278322.58 | AS45: 277424.78 | AT45: 245670.97 | AU45: 247293.28 | AV45: 245850.09 | AW45: 249694.29 | AX45: 251992.64 | AY45: 252913.16 | AZ45: {=XLOOKUP(C45,'PL TOTAL D0'!K:K,'PL TOTAL D0'!L:L,"")} -> 267527.65
A46: XP | B46: Gabriela Delvaux Maia | C46: 2375512 | D46: Poupinvista | E46: DF | F46: Bruno Rodrigues | G46: =IFS($AZ$3:$AZ$993<=250000,"David",$AZ$3:$AZ$993<=800000,"Gabriel", $AZ$3:$AZ$993>800000,"Marcus") -> David | H46: Ativo | I46: ------ | J46: =IF(Q46=0,"Não","Sim") -> Não | K46: 45700 | M46: INC | N46: 0.012 | O46: ------ | P46: 0 | S46: PF | T46: 634.697.071-20 | U46: (61) - 993039181 | V46: gabidelvaux@gmail.com | W46: 30008 | X46: DF | Y46: =IFS(H:H="Encerrado","Encerrado",COUNTBLANK(AF46:AN46)>0,"Ativo",SUM(AF46:AN46)=0,"Inativo",SUM(AF46:AN46)>0,"Ativo") -> Ativo | AA46: Moderado | AD46: 45700 | AE46: 49075100017808 | AI46: 38266.764 | AJ46: 32084.072 | AK46: 32384.984 | AL46: 32959.091 | AM46: 33256.229 | AN46: 33739.04 | AO46: 34031.557 | AP46: 35201.516 | AQ46: 36397.913 | AR46: 36225.188 | AS46: 37748.047 | AT46: 38659.573 | AU46: 44179.979 | AV46: 56155.62 | AW46: 56732.17 | AX46: 56981.853 | AY46: 57439.274 | AZ46: {=XLOOKUP(C46,'PL TOTAL D0'!K:K,'PL TOTAL D0'!L:L,"")} -> 61556.146
A47: XP | B47: Glaucy Martins Cananeia Miranda | C47: 18446216 | D47: MI Smart | E47: DF | F47: Mariana Rocha | G47: =IFS($AZ$3:$AZ$993<=250000,"David",$AZ$3:$AZ$993<=800000,"Gabriel", $AZ$3:$AZ$993>800000,"Marcus") -> David | H47: Ativo | I47: ------ | J47: =IF(Q47=0,"Não","Sim") -> Sim | K47: 45874 | M47: INC | N47: 0.012 | O47: ------ | P47: 0 | Q47: 70K D+0 (05/08/2025) | S47: PF | T47: 024.034.771-41 | U47: (62) - 991129999 | V47: atendimento@terroircerrado.com.br | W47: 32468 | X47: DF | Y47: =IFS(H:H="Encerrado","Encerrado",COUNTBLANK(AF47:AN47)>0,"Ativo",SUM(AF47:AN47)=0,"Inativo",SUM(AF47:AN47)>0,"Ativo") -> Ativo | AA47: Conservador | AD47: 45876 | AE47: 49075100019363 | AN47: 0 | AO47: 117969.84 | AP47: 113849.61 | AQ47: 115185.69 | AR47: 18836.26 | AS47: 18998.7 | AT47: 1975.22 | AU47: 1985.36 | AV47: 6054.24 | AW47: 0 | AX47: 0 | AY47: 0.22 | AZ47: {=XLOOKUP(C47,'PL TOTAL D0'!K:K,'PL TOTAL D0'!L:L,"")} -> 0.22
A48: XP | B48: Gleuber Lucas Alves | C48: 3917632 | D48: Expert | E48: GO | F48: Alcivana Marques | G48: =IFS($AZ$3:$AZ$993<=250000,"David",$AZ$3:$AZ$993<=800000,"Gabriel", $AZ$3:$AZ$993>800000,"Marcus") -> David | H48: Ativo | I48: ------ | J48: =IF(Q48=0,"Não","Sim") -> Não | K48: 45840 | M48: INC | N48: 0.012 | O48: ------ | P48: 0 | S48: PF | T48: 743.818.907-44 | U48: (62) - 981174320 | V48: gleuber.alves@gmail.com | W48: 22608 | X48: GO | Y48: =IFS(H:H="Encerrado","Encerrado",COUNTBLANK(AF48:AN48)>0,"Ativo",SUM(AF48:AN48)=0,"Inativo",SUM(AF48:AN48)>0,"Ativo") -> Ativo | AA48: Moderado | AD48: 45840 | AE48: 49075100019266 | AN48: 116717.12 | AO48: 120816.97 | AP48: 49902.38 | AQ48: 48883.81 | AR48: 52526.19 | AS48: 49068.73 | AT48: 55498.37 | AU48: 54721.02 | AV48: 49353.7 | AW48: 47091.19 | AX48: 45503.96 | AY48: 43173.03 | AZ48: {=XLOOKUP(C48,'PL TOTAL D0'!K:K,'PL TOTAL D0'!L:L,"")} -> 43576.4
A49: XP | B49: Grasielle Rodrigues Santana | C49: 5282208 | D49: Poupinvista | E49: DF | F49: Bruno Rodrigues | G49: =IFS($AZ$3:$AZ$993<=250000,"David",$AZ$3:$AZ$993<=800000,"Gabriel", $AZ$3:$AZ$993>800000,"Marcus") -> David | H49: Ativo | I49: ------ | J49: =IF(Q49=0,"Não","Sim") -> Não | K49: 45891 | M49: INC | N49: 0.012 | O49: ------ | P49: 0 | S49: PF | T49: 097.553.326-69 | U49: (34) 99175-2088 | V49: grasirsantana@gmail.com | W49: 32511 | X49: DF | Y49: =IFS(H:H="Encerrado","Encerrado",COUNTBLANK(AF49:AN49)>0,"Ativo",SUM(AF49:AN49)=0,"Inativo",SUM(AF49:AN49)>0,"Ativo") -> Ativo | AA49: Moderado | AD49: 45891 | AE49: 49075100019304 | AN49: 120888.73 | AO49: 124008.9 | AP49: 121515.15 | AQ49: 122345.08 | AR49: 113022.21 | AS49: 113863.44 | AT49: 91610.705 | AU49: 91841.677 | AV49: 116436.6 | AW49: 117410.17 | AX49: 121211.88 | AY49: 112520.48 | AZ49: {=XLOOKUP(C49,'PL TOTAL D0'!K:K,'PL TOTAL D0'!L:L,"")} -> 113541.78
A50: XP | B50: Guilherme Rebello Rocha Mangueira | C50: 12398948 | D50: MI Smart | E50: DF | F50: Mariana Rocha | G50: =IFS($AZ$3:$AZ$993<=250000,"David",$AZ$3:$AZ$993<=800000,"Gabriel", $AZ$3:$AZ$993>800000,"Marcus") -> Marcus | H50: Encerrado | I50: ------ | J50: =IF(Q50=0,"Não","Sim") -> Sim | K50: 45712 | L50: 46084 | M50: INC | N50: 0.012 | O50: ------ | P50: 0 | Q50: 50K D+0 (28/03/2025) | S50: PF | T50: 036.493.901-08 | U50: (61) - 999330230 | V50: guilhermereb@gmail.com | W50: 33512 | X50: DF | Y50: =IFS(H:H="Encerrado","Encerrado",COUNTBLANK(AF50:AN50)>0,"Ativo",SUM(AF50:AN50)=0,"Inativo",SUM(AF50:AN50)>0,"Ativo") -> Encerrado | AA50: Moderado | AD50: 45712 | AE50: 49075100017905 | AI50: 184939.78 | AJ50: 186107.14 | AK50: 189006.39 | AL50: 150663.79 | AM50: 152229.13 | AN50: 153924.05 | AO50: 155521.97 | AP50: 156723.7 | AQ50: 158532.97 | AR50: 159563.66 | AS50: 141931.92 | AT50: 140121.43 | AU50: 0 | AV50: 0 | AW50: 0 | AX50: 0 | AY50: 0 | AZ50: {=XLOOKUP(C50,'PL TOTAL D0'!K:K,'PL TOTAL D0'!L:L,"")}
A51: XP | B51: Gustavo Mendonça Nunes de Oliveira | C51: 3426143 | D51: Bluemetrix | E51: DF | F51: Gustavo Amorim | G51: =IFS($AZ$3:$AZ$993<=250000,"David",$AZ$3:$AZ$993<=800000,"Gabriel", $AZ$3:$AZ$993>800000,"Marcus") -> Marcus | H51: Ativo | I51: ------ | J51: =IF(Q51=0,"Não","Sim") -> Não | K51: 45698 | M51: MULT PRIV/ COADM | N51: 0.015 | O51: ------ | P51: 0 | S51: PF | T51: 693.814.881-34 | U51: (61) - 981753061 | V51: drgmendonca@gmail.com | W51: 28975 | X51: DF | Y51: =IFS(H:H="Encerrado","Encerrado",COUNTBLANK(AF51:AN51)>0,"Ativo",SUM(AF51:AN51)=0,"Inativo",SUM(AF51:AN51)>0,"Ativo") -> Ativo | AA51: Arrojado | AD51: 45698 | AE51: 49075100017867 | AI51: 1632889.8 | AJ51: 1666344 | AK51: 1698779.8 | AL51: 2092213.6 | AM51: 2114731.3 | AN51: 2213648.5 | AO51: 2250104.6 | AP51: 2272539.7 | AQ51: 2304668.9 | AR51: 2344050.9 | AS51: 2478766.3 | AT51: 2532070.3 | AU51: 2557838.8 | AV51: 2534587.4 | AW51: 2590767.1 | AX51: 2564245.9 | AY51: 2596003.6 | AZ51: {=XLOOKUP(C51,'PL TOTAL D0'!K:K,'PL TOTAL D0'!L:L,"")} -> 2627979.9
A52: XP | B52: Gustavo Rassi Nader | C52: 750425 | D52: VcInvest | E52: GO | F52: Bruno Ribeiro | G52: =IFS($AZ$3:$AZ$993<=250000,"David",$AZ$3:$AZ$993<=800000,"Gabriel", $AZ$3:$AZ$993>800000,"Marcus") -> Marcus | H52: Ativo | I52: ------ | J52: =IF(Q52=0,"Não","Sim") -> Não | K52: 45660 | M52: INC | N52: 0.012 | O52: ------ | P52: 0 | S52: PF | T52: 813.771.001-97 | U52: (62) - 39542136 | V52: grnader@hotmail.com | W52: 28276 | X52: GO | Y52: =IFS(H:H="Encerrado","Encerrado",COUNTBLANK(AF52:AN52)>0,"Ativo",SUM(AF52:AN52)=0,"Inativo",SUM(AF52:AN52)>0,"Ativo") -> Ativo | AA52: Moderado | AD52: 45660 | AE52: 49075100016518 | AG52: 822357.35 | AH52: 827047.73 | AI52: 829582.49 | AJ52: 884055.52 | AK52: 906086.5 | AL52: 913889.44 | AM52: 924386.13 | AN52: 935273.16 | AO52: 945823.2 | AP52: 956160.81 | AQ52: 975947.26 | AR52: 981004.87 | AS52: 990099.61 | AT52: 1062733.2 | AU52: 1006975.7 | AV52: 999046.49 | AW52: 1022163.1 | AX52: 1035776.8 | AY52: 1042071.4 | AZ52: {=XLOOKUP(C52,'PL TOTAL D0'!K:K,'PL TOTAL D0'!L:L,"")} -> 1044558.9
A53: XP | B53: Helaine Taia Silveira | C53: 8961166 | D53: Expert | E53: GO | F53: André de Queiroz Coelho | G53: =IFS($AZ$3:$AZ$993<=250000,"David",$AZ$3:$AZ$993<=800000,"Gabriel", $AZ$3:$AZ$993>800000,"Marcus") -> Gabriel | H53: Ativo | I53: ------ | J53: =IF(Q53=0,"Não","Sim") -> Sim | K53: 45782 | M53: INC | N53: 0.012 | O53: ------ | P53: 0 | Q53: 30K D+0 (07/05/2025) | S53: PF | T53: 316.386.271-34 | U53: (62) - 991112888 | V53: helainets@hotmail.com | W53: 25195 | X53: GO | Y53: =IFS(H:H="Encerrado","Encerrado",COUNTBLANK(AF53:AN53)>0,"Ativo",SUM(AF53:AN53)=0,"Inativo",SUM(AF53:AN53)>0,"Ativo") -> Ativo | AA53: Moderado | AD53: 45782 | AE53: 49075100018911 | AL53: 203090.53 | AM53: 205211.55 | AN53: 207597.55 | AO53: 209784.1 | AP53: 212051.99 | AQ53: 214560.1 | AR53: 215936.32 | AS53: 218294.93 | AT53: 220604.02 | AU53: 222605.46 | AV53: 225363.22 | AW53: 243021.79 | AX53: 339747.14 | AY53: 380786.84 | AZ53: {=XLOOKUP(C53,'PL TOTAL D0'!K:K,'PL TOTAL D0'!L:L,"")} -> 389022.33
A54: XP | B54: Helder Quadros Santos | C54: 19800198 | D54: Investeseg | E54: BA | F54: Caroline Cichello | G54: =IFS($AZ$3:$AZ$993<=250000,"David",$AZ$3:$AZ$993<=800000,"Gabriel", $AZ$3:$AZ$993>800000,"Marcus") -> David | H54: Ativo | I54: ------ | J54: =IF(Q54=0,"Não","Sim") -> Sim | K54: 46232 | M54: CON | N54: 0.012 | O54: CDI | P54: 0.1 | Q54: 40% D+0 (03/08/2026) | S54: PF | T54: 651.853.405-25 | U54: 71 99900-9012 | V54: hquadros@pobox.com | W54: 26731 | X54: BA | Y54: =IFS(H:H="Encerrado","Encerrado",COUNTBLANK(AF54:AN54)>0,"Ativo",SUM(AF54:AN54)=0,"Inativo",SUM(AF54:AN54)>0,"Ativo") -> Ativo | AA54: Arrojado
A55: XP | B55: Henny Wilson Bahmad Scalon Botosso | C55: 18862172 | D55: Expert | E55: GO | F55: Alcivana Marques | G55: =IFS($AZ$3:$AZ$993<=250000,"David",$AZ$3:$AZ$993<=800000,"Gabriel", $AZ$3:$AZ$993>800000,"Marcus") -> Marcus | H55: Encerrado | I55: ------ | J55: =IF(Q55=0,"Não","Sim") -> Sim | K55: 46063 | L55: 46176 | M55: INC | N55: 0.012 | O55: ------ | P55: 0 | Q55: Alocar em liquidez diária, até ordem do assessor (12/02/2026). | S55: PF | T55: 001.223.211-46 | U55: 61 98136-7471 | V55: henny_fisio@hotmail.com | W55: 30546 | X55: DF | Y55: =IFS(H:H="Encerrado","Encerrado",COUNTBLANK(AF55:AN55)>0,"Ativo",SUM(AF55:AN55)=0,"Inativo",SUM(AF55:AN55)>0,"Ativo") -> Encerrado | AA55: Moderado | AU55: 811791.77 | AV55: 821057.13 | AW55: 399829.13 | AX55: 298266.72 | AY55: 0 | AZ55: {=XLOOKUP(C55,'PL TOTAL D0'!K:K,'PL TOTAL D0'!L:L,"")}
A56: XP | B56: Ilton Luis Guimaraes De Siqueira | C56: 2427806 | D56: Bluemetrix | E56: GO | F56: Vivian | G56: =IFS($AZ$3:$AZ$993<=250000,"David",$AZ$3:$AZ$993<=800000,"Gabriel", $AZ$3:$AZ$993>800000,"Marcus") -> Marcus | H56: Encerrado | I56: ------ | J56: =IF(Q56=0,"Não","Sim") -> Não | K56: 45712 | L56: 45894 | M56: INC | N56: 0.012 | O56: ------ | P56: 0 | S56: PF | T56: 378.213.426-53 | U56: (62) - 981790243 | V56: iltonluis52@gmail.com | W56: 22305 | X56: GO | Y56: =IFS(H:H="Encerrado","Encerrado",COUNTBLANK(AF56:AN56)>0,"Ativo",SUM(AF56:AN56)=0,"Inativo",SUM(AF56:AN56)>0,"Ativo") -> Encerrado | AA56: Conservador | AD56: 45712 | AE56: 49075100017840 | AI56: 58754.42 | AJ56: 58959.96 | AK56: 59889.46 | AL56: 59954.3 | AM56: 60080.9 | AN56: 60338.22 | AO56: 0 | AP56: 0 | AQ56: 0 | AR56: 0 | AS56: 0 | AT56: 0 | AU56: 0 | AV56: 0 | AW56: 0 | AX56: 0 | AY56: 0 | AZ56: {=XLOOKUP(C56,'PL TOTAL D0'!K:K,'PL TOTAL D0'!L:L,"")}
A57: XP | B57: Ivone Aparecida Vaccaro | C57: 8406743 | D57: Expert | E57: GO | F57: Alcivana Marques | G57: =IFS($AZ$3:$AZ$993<=250000,"David",$AZ$3:$AZ$993<=800000,"Gabriel", $AZ$3:$AZ$993>800000,"Marcus") -> Marcus | H57: Encerrado | I57: ------ | J57: =IF(Q57=0,"Não","Sim") -> Não | K57: 45805 | L57: 46105 | M57: INC | N57: 0.012 | O57: ------ | P57: 0 | S57: PF | T57: 652.174.629-49 | U57: (62) - 981449594 | V57: ivonevaccaro3@gmail.com | W57: 22931 | X57: GO | Y57: =IFS(H:H="Encerrado","Encerrado",COUNTBLANK(AF57:AN57)>0,"Ativo",SUM(AF57:AN57)=0,"Inativo",SUM(AF57:AN57)>0,"Ativo") -> Encerrado | AA57: Moderado | AD57: 45805 | AE57: 49075100018898 | AL57: 1001409.1 | AM57: 1016865 | AN57: 1006029.4 | AO57: 894108.33 | AP57: 630348.25 | AQ57: 616530.66 | AR57: 429631.53 | AS57: 248580.45 | AT57: 248347.78 | AU57: 158191.89 | AV57: 0 | AW57: 0 | AX57: 0 | AY57: 0 | AZ57: {=XLOOKUP(C57,'PL TOTAL D0'!K:K,'PL TOTAL D0'!L:L,"")}
A58: XP | B58: Janilson Sampaio De Oliveira | C58: 5698370 | D58: Bluemetrix | E58: GO | F58: Felipe Rios | G58: =IFS($AZ$3:$AZ$993<=250000,"David",$AZ$3:$AZ$993<=800000,"Gabriel", $AZ$3:$AZ$993>800000,"Marcus") -> David | H58: Ativo | I58: ------ | J58: =IF(#REF!=0,"Não","Sim") -> #REF! | K58: 45821 | M58: INC | N58: 0.012 | O58: ------ | P58: 0 | S58: PF | T58: 644.424.112-04 | U58: (91) - 987356593 | V58: jsampaiopa@gmail.com | W58: 28749 | X58: PA | Y58: =IFS(H:H="Encerrado","Encerrado",COUNTBLANK(AF58:AN58)>0,"Ativo",SUM(AF58:AN58)=0,"Inativo",SUM(AF58:AN58)>0,"Ativo") -> Ativo | AA58: Conservador | AD58: 45824 | AE58: 49075100019126 | AM58: 90431.76 | AN58: 107692.5 | AO58: 108758.07 | AP58: 109912.57 | AQ58: 121232.93 | AR58: 122173.83 | AS58: 122739.85 | AT58: 124153.19 | AU58: 125192.64 | AV58: 126781.56 | AW58: 229211.31 | AX58: 231390.72 | AY58: 233087.9 | AZ58: {=XLOOKUP(C58,'PL TOTAL D0'!K:K,'PL TOTAL D0'!L:L,"")} -> 229685.85
A59: XP | B59: Jennifer do Carmo Souza Pinheiro | C59: 19771677 | D59: Investeseg | E59: BA | F59: Murilo Silva | G59: =IFS($AZ$3:$AZ$993<=250000,"David",$AZ$3:$AZ$993<=800000,"Gabriel", $AZ$3:$AZ$993>800000,"Marcus") -> David | H59: Ativo | I59: ------ | J59: =IF(Q58=0,"Não","Sim") -> Não | K59: 46225 | M59: CON | N59: 0.012 | O59: CDI | P59: 0.1 | Q59: 100k D+0 (22/07/2026) | S59: PF | T59: 963.419.805-82 | U59: 71 99131-5505 | V59: jey_souza@hotmail.com | W59: 29349 | X59: BA | Y59: =IFS(H:H="Encerrado","Encerrado",COUNTBLANK(AF59:AN59)>0,"Ativo",SUM(AF59:AN59)=0,"Inativo",SUM(AF59:AN59)>0,"Ativo") -> Ativo | AA59: Moderado
A60: XP | B60: Joanice De Moraes Arantes | C60: 2570762 | D60: VcInvest | E60: GO | F60: Bruno Ribeiro | G60: =IFS($AZ$3:$AZ$993<=250000,"David",$AZ$3:$AZ$993<=800000,"Gabriel", $AZ$3:$AZ$993>800000,"Marcus") -> Gabriel | H60: Ativo | I60: ------ | J60: =IF(Q60=0,"Não","Sim") -> Não | K60: 45666 | M60: INC | N60: 0.012 | O60: ------ | P60: 0 | S60: PF | T60: 895.761.521-00 | U60: (62) - 999788043 | V60: nicearantes@hotmail.com | W60: 19011 | X60: GO | Y60: =IFS(H:H="Encerrado","Encerrado",COUNTBLANK(AF60:AN60)>0,"Ativo",SUM(AF60:AN60)=0,"Inativo",SUM(AF60:AN60)>0,"Ativo") -> Ativo | AA60: Moderado | AD60: 45666 | AE60: 49075100016569 | AH60: 593540.39 | AI60: 601092.42 | AJ60: 599543.23 | AK60: 552566.63 | AL60: 541143.2 | AM60: 549188.67 | AN60: 538894.78 | AO60: 529717.54 | AP60: 533644.76 | AQ60: 527436.58 | AR60: 526254.08 | AS60: 528328.78 | AT60: 521611.46 | AU60: 506208.05 | AV60: 503921.38 | AW60: 512698.12 | AX60: 508206.88 | AY60: 500390.06 | AZ60: {=XLOOKUP(C60,'PL TOTAL D0'!K:K,'PL TOTAL D0'!L:L,"")} -> 494038.87
A61: XP | B61: Joao Vitor Cabral de Morais | C61: 18718220 | D61: Expert | E61: GO | F61: André de Queiroz Coelho | G61: =IFS($AZ$3:$AZ$993<=250000,"David",$AZ$3:$AZ$993<=800000,"Gabriel", $AZ$3:$AZ$993>800000,"Marcus") -> David | H61: Inativo | I61: Monitoramento | J61: =IF(Q61=0,"Não","Sim") -> Não | K61: 45938 | M61: MONT | N61: 0 | O61: ------ | P61: 0 | S61: PF | T61: 038.144.411-25 | U61: 5562993412365 | V61: joaovitorcabral94@gmail.com | W61: 34523 | X61: GO | Y61: =IFS(H:H="Encerrado","Encerrado",COUNTBLANK(AF61:AN61)>0,"Ativo",SUM(AF61:AN61)=0,"Inativo",SUM(AF61:AN61)>0,"Ativo") -> Ativo | AA61: Moderado | AQ61: 0 | AR61: 0 | AS61: 0.01 | AT61: 0 | AU61: 0 | AV61: 4.23 | AW61: 18.7 | AX61: 18.7 | AY61: 18.7 | AZ61: {=XLOOKUP(C61,'PL TOTAL D0'!K:K,'PL TOTAL D0'!L:L,"")} -> 20.87
A62: XP | B62: Jose Valmir Paulino Dias | C62: 17033260 | D62: Bluemetrix | E62: DF | F62: João Moreira | G62: =IFS($AZ$3:$AZ$993<=250000,"David",$AZ$3:$AZ$993<=800000,"Gabriel", $AZ$3:$AZ$993>800000,"Marcus") -> David | H62: Inativo | I62: Sem Saldo | J62: =IF(Q62=0,"Não","Sim") -> Não | K62: 45905 | M62: PREV CON | N62: 0.005 | O62: ------ | P62: 0 | S62: PF | T62: 072.914.933-15 | U62: 61 98175-4138 | V62: valmir1001@gmail.com | W62: 19369 | X62: DF | Y62: =IFS(H:H="Encerrado","Encerrado",COUNTBLANK(AF62:AN62)>0,"Ativo",SUM(AF62:AN62)=0,"Inativo",SUM(AF62:AN62)>0,"Ativo") -> Ativo | AA62: Moderado | AN62: 0 | AO62: 0 | AP62: 0 | AQ62: 0 | AR62: 0 | AS62: 0 | AT62: 0 | AU62: 0 | AV62: 0 | AW62: 0 | AX62: 0 | AY62: 0 | AZ62: {=XLOOKUP(C62,'PL TOTAL D0'!K:K,'PL TOTAL D0'!L:L,"")} -> 0
A63: XP | B63: Juliana Fontes de Melo | C63: 19784770 | D63: Investeseg | E63: BA | F63: Caroline Cichello | G63: =IFS($AZ$3:$AZ$993<=250000,"David",$AZ$3:$AZ$993<=800000,"Gabriel", $AZ$3:$AZ$993>800000,"Marcus") -> David | H63: Ativo | I63: ------ | J63: =IF(Q63=0,"Não","Sim") -> Não | K63: 46227 | M63: CON | N63: 0.012 | O63: CDI | P63: 0.1 | S63: PF | T63: 105.750.447-56 | U63: 21 98871-2533 | V63: jufontes.jf@gmail.com | W63: 32921 | X63: RJ | Y63: =IFS(H:H="Encerrado","Encerrado",COUNTBLANK(AF63:AN63)>0,"Ativo",SUM(AF63:AN63)=0,"Inativo",SUM(AF63:AN63)>0,"Ativo") -> Ativo | AA63: Moderado
A64: XP | B64: Juliana Gomes Falleiros Cavalheiro | C64: 2044321 | D64: Altum | E64: DF | F64: Guilherme Marques | G64: =IFS($AZ$3:$AZ$993<=250000,"David",$AZ$3:$AZ$993<=800000,"Gabriel", $AZ$3:$AZ$993>800000,"Marcus") -> David | H64: Inativo | I64: Monitoramento | J64: =IF(Q64=0,"Não","Sim") -> Não | K64: 45777 | M64: MONT | N64: 0 | O64: ------ | P64: 0 | S64: PF | T64: 219.105.138-30 | U64: (61) - 991772687 | V64: julianafalleiros@yahoo.com.br | W64: 29004 | X64: DF | Y64: =IFS(H:H="Encerrado","Encerrado",COUNTBLANK(AF64:AN64)>0,"Ativo",SUM(AF64:AN64)=0,"Inativo",SUM(AF64:AN64)>0,"Ativo") -> Ativo | AA64: Moderado | AD64: 45777 | AE64: 49075100018855 | AK64: 28677.33 | AL64: 28683.49 | AM64: 29236.08 | AN64: 29453.5 | AO64: 29606.06 | AP64: 29760.98 | AQ64: 29985.9 | AR64: 29894.89 | AS64: 30022.22 | AT64: 30160.61 | AU64: 30281.85 | AV64: 30447.41 | AW64: 30571.32 | AX64: 30279.31 | AY64: 30531.13 | AZ64: {=XLOOKUP(C64,'PL TOTAL D0'!K:K,'PL TOTAL D0'!L:L,"")} -> 30599.31
A65: XP | B65: Juliano Falleiros Cavalheiro | C65: 516643 | D65: Altum | E65: DF | F65: Guilherme Marques | G65: =IFS($AZ$3:$AZ$993<=250000,"David",$AZ$3:$AZ$993<=800000,"Gabriel", $AZ$3:$AZ$993>800000,"Marcus") -> David | H65: Inativo | I65: Monitoramento | J65: =IF(Q65=0,"Não","Sim") -> Não | K65: 45789 | M65: MONT | N65: 0 | O65: ------ | P65: 0 | S65: PF | T65: 268.878.568-08 | U65: (11) - 995965703 | V65: cavalheiro.juliano@gmail.com | W65: 28731 | X65: DF | Y65: =IFS(H:H="Encerrado","Encerrado",COUNTBLANK(AF65:AN65)>0,"Ativo",SUM(AF65:AN65)=0,"Inativo",SUM(AF65:AN65)>0,"Ativo") -> Ativo | AA65: Moderado | AD65: 45789 | AE65: 49075100018863 | AL65: 34581.5 | AM65: 35246.39 | AN65: 35509.46 | AO65: 35694.59 | AP65: 35882.59 | AQ65: 36154.75 | AR65: 36045.53 | AS65: 36200.47 | AT65: 36368.65 | AU65: 36515.99 | AV65: 36716.97 | AW65: 36867.63 | AX65: 36517.33 | AY65: 36821.71 | AZ65: {=XLOOKUP(C65,'PL TOTAL D0'!K:K,'PL TOTAL D0'!L:L,"")} -> 36905.89
A66: XP | B66: Karen Neves Edwards | C66: 19550454 | D66: VcInvest | E66: GO | F66: Bruno Ribeiro | G66: =IFS($AZ$3:$AZ$993<=250000,"David",$AZ$3:$AZ$993<=800000,"Gabriel", $AZ$3:$AZ$993>800000,"Marcus") -> David | H66: Ativo | I66: ------ | J66: =IF(Q66=0,"Não","Sim") -> Não | K66: 46157 | M66: MOD | N66: 0.015 | O66: CDI | P66: 0.1 | S66: PF | T66: 728.488.042-20 | U66: 62 98286-0550 | V66: karen.neves.edwards@gmail.com | W66: 30336 | X66: RJ | Y66: =IFS(H:H="Encerrado","Encerrado",COUNTBLANK(AF66:AN66)>0,"Ativo",SUM(AF66:AN66)=0,"Inativo",SUM(AF66:AN66)>0,"Ativo") -> Ativo | AA66: Arrojado | AX66: 0 | AY66: 69356.65 | AZ66: {=XLOOKUP(C66,'PL TOTAL D0'!K:K,'PL TOTAL D0'!L:L,"")} -> 72010.502
A67: XP | B67: Lailson da Silva Oliveira | C67: 18610732 | D67: Bluemetrix | E67: GO | F67: Felipe Rios | G67: =IFS($AZ$3:$AZ$993<=250000,"David",$AZ$3:$AZ$993<=800000,"Gabriel", $AZ$3:$AZ$993>800000,"Marcus") -> David | H67: Inativo | I67: ------ | J67: =IF(Q67=0,"Não","Sim") -> Não | K67: 45915 | M67: INC | N67: 0.012 | O67: ------ | P67: 0 | S67: PF | T67: 036.079.621-46 | U67: 63 99915-9000 | V67: lailson.oliveira.01@gmail.com | W67: 32986 | X67: MA | Y67: =IFS(H:H="Encerrado","Encerrado",COUNTBLANK(AF67:AN67)>0,"Ativo",SUM(AF67:AN67)=0,"Inativo",SUM(AF67:AN67)>0,"Ativo") -> Ativo | AA67: Moderado | AN67: 0 | AO67: 0 | AP67: 0 | AQ67: 0 | AR67: 0 | AS67: 0 | AT67: 0 | AU67: 0 | AV67: 0 | AW67: 0 | AX67: 0 | AY67: 0 | AZ67: {=XLOOKUP(C67,'PL TOTAL D0'!K:K,'PL TOTAL D0'!L:L,"")} -> 0
A68: XP | B68: Lais Barreto Franco | C68: 19625446 | D68: Investeseg | E68: BA | F68: Murilo Silva | G68: =IFS($AZ$3:$AZ$993<=250000,"David",$AZ$3:$AZ$993<=800000,"Gabriel", $AZ$3:$AZ$993>800000,"Marcus") -> David | H68: Ativo | I68: ------ | J68: =IF(Q68=0,"Não","Sim") -> Não | K68: 46178 | M68: CON/ GR | N68: 0.013 | O68: ------ | P68: 0 | S68: PF | T68: 031.050.455-46 | U68: 71 99122-1138 | V68: laisfranco.agro@yahoo.com.br | W68: 32883 | X68: SE | Y68: =IFS(H:H="Encerrado","Encerrado",COUNTBLANK(AF68:AN68)>0,"Ativo",SUM(AF68:AN68)=0,"Inativo",SUM(AF68:AN68)>0,"Ativo") -> Ativo | AA68: Moderado | AX68: 0 | AY68: 108546.61 | AZ68: {=XLOOKUP(C68,'PL TOTAL D0'!K:K,'PL TOTAL D0'!L:L,"")} -> 108852.85
A69: XP | B69: Layla Achkar Magalhaes Torres | C69: 17684846 | D69: Poupinvista | E69: DF | F69: Bruno Rodrigues | G69: =IFS($AZ$3:$AZ$993<=250000,"David",$AZ$3:$AZ$993<=800000,"Gabriel", $AZ$3:$AZ$993>800000,"Marcus") -> David | H69: Ativo | I69: ------ | J69: =IF(Q69=0,"Não","Sim") -> Sim | K69: 45733 | M69: CON | N69: 0.012 | O69: CDI | P69: 0.1 | Q69: 100% D+0 (07/04/2025) | R69: Alteração de carteira finalizada (17/06/2025) | S69: PF | T69: 100.573.857-26 | U69: (61) - 996276478 | V69: laylachkar@gmail.com | W69: 30750 | X69: DF | Y69: =IFS(H:H="Encerrado","Encerrado",COUNTBLANK(AF69:AN69)>0,"Ativo",SUM(AF69:AN69)=0,"Inativo",SUM(AF69:AN69)>0,"Ativo") -> Ativo | AA69: Conservador | AD69: 45733 | AE69: 49075100018448 | AJ69: 228355.94 | AK69: 418718.58 | AL69: 137261.1 | AM69: 136271.03 | AN69: 136253.72 | AO69: 139630.3 | AP69: 121770.93 | AQ69: 123181.2 | AR69: 124402.78 | AS69: 104575.62 | AT69: 105006.04 | AU69: 114966.82 | AV69: 116350.09 | AW69: 117614.48 | AX69: 119413.94 | AY69: 120700.65 | AZ69: {=XLOOKUP(C69,'PL TOTAL D0'!K:K,'PL TOTAL D0'!L:L,"")} -> 120657.56
A70: XP | B70: Leandro Araujo Lobo | C70: 15919404 | D70: MI Smart | E70: DF | F70: Mariana Rocha | G70: =IFS($AZ$3:$AZ$993<=250000,"David",$AZ$3:$AZ$993<=800000,"Gabriel", $AZ$3:$AZ$993>800000,"Marcus") -> Gabriel | H70: Ativo | I70: ------ | J70: =IF(Q70=0,"Não","Sim") -> Sim | K70: 45712 | M70: INC | N70: 0.011 | O70: ------ | P70: 0 | Q70: 50K D+0 (28/03/2025) | S70: PF | T70: 052.033.347-06 | U70: (21) - 999496066 | V70: lelelobo@gmail.com | W70: 28060 | X70: RJ | Y70: =IFS(H:H="Encerrado","Encerrado",COUNTBLANK(AF70:AN70)>0,"Ativo",SUM(AF70:AN70)=0,"Inativo",SUM(AF70:AN70)>0,"Ativo") -> Ativo | AA70: Conservador | AD70: 45712 | AE70: 49075100017913 | AI70: 260192.58 | AJ70: 262403.19 | AK70: 267339.59 | AL70: 275311.87 | AM70: 277974.56 | AN70: 281080.43 | AO70: 283850.25 | AP70: 286674.45 | AQ70: 290066.43 | AR70: 291858.21 | AS70: 295059.27 | AT70: 298246.05 | AU70: 298307.82 | AV70: 301473 | AW70: 301827.56 | AX70: 302805.93 | AY70: 305827 | AZ70: {=XLOOKUP(C70,'PL TOTAL D0'!K:K,'PL TOTAL D0'!L:L,"")} -> 309356.26
A71: XP | B71: Leandro Augusto de Araujo Cunha Teixeira Bueno | C71: 4340593 | D71: Poupinvista | E71: DF | F71: Bruno Rodrigues | G71: =IFS($AZ$3:$AZ$993<=250000,"David",$AZ$3:$AZ$993<=800000,"Gabriel", $AZ$3:$AZ$993>800000,"Marcus") -> David | H71: Inativo | I71: Sem Saldo | J71: =IF(Q71=0,"Não","Sim") -> Não | K71: 45756 | M71: MOD | N71: 0.0085 | O71: CDI | P71: 0.1 | S71: PF | T71: 342.258.488-92 | U71: (61) - 981303300 | V71: cunhabueno.law@gmail.com | W71: 31873 | X71: DF | Y71: =IFS(H:H="Encerrado","Encerrado",COUNTBLANK(AF71:AN71)>0,"Ativo",SUM(AF71:AN71)=0,"Inativo",SUM(AF71:AN71)>0,"Ativo") -> Ativo | AA71: Moderado | AD71: 45756 | AE71: 49075100018707 | AK71: 306994.36 | AL71: 1887.28 | AM71: 1914.73 | AN71: 339.8 | AO71: 343.76 | AP71: 347.9 | AQ71: 352.35 | AR71: 356.04 | AS71: 360.39 | AT71: 364.6 | AU71: 368.24 | AV71: 372.82 | AW71: 376.84 | AX71: 380.89 | AY71: 385.13 | AZ71: {=XLOOKUP(C71,'PL TOTAL D0'!K:K,'PL TOTAL D0'!L:L,"")} -> 389.82
A72: XP | B72: Leonardo Araujo Laperche | C72: 19538063 | D72: Expert | E72: GO | F72: André de Queiroz Coelho | G72: =IFS($AZ$3:$AZ$993<=250000,"David",$AZ$3:$AZ$993<=800000,"Gabriel", $AZ$3:$AZ$993>800000,"Marcus") -> David | H72: Ativo | I72: ------ | J72: =IF(Q72=0,"Não","Sim") -> Não | K72: 46210 | M72: MOD | N72: 0.015 | O72: CDI | P72: 0.1 | S72: PF | T72: 041.266.381-30 | U72: 62 99134-8995 | V72: leolaperche@gmail.com | W72: 34476 | X72: GO | Y72: =IFS(H:H="Encerrado","Encerrado",COUNTBLANK(AF72:AN72)>0,"Ativo",SUM(AF72:AN72)=0,"Inativo",SUM(AF72:AN72)>0,"Ativo") -> Ativo | AA72: Moderado | AY72: 0 | AZ72: {=XLOOKUP(C72,'PL TOTAL D0'!K:K,'PL TOTAL D0'!L:L,"")} -> 0
A73: XP | B73: Levi Silva Filho | C73: 8625760 | D73: VcInvest | E73: GO | F73: Bruno Ribeiro | G73: =IFS($AZ$3:$AZ$993<=250000,"David",$AZ$3:$AZ$993<=800000,"Gabriel", $AZ$3:$AZ$993>800000,"Marcus") -> Marcus | H73: Ativo | I73: ------ | J73: =IF(Q73=0,"Não","Sim") -> Não | K73: 45678 | M73: INC | N73: 0.012 | O73: ------ | P73: 0 | S73: PF | T73: 154.536.691-87 | U73: (62) - 996887440 | V73: levisilvafilho@yahoo.com.br | W73: 19022 | X73: GO | Y73: =IFS(H:H="Encerrado","Encerrado",COUNTBLANK(AF73:AN73)>0,"Ativo",SUM(AF73:AN73)=0,"Inativo",SUM(AF73:AN73)>0,"Ativo") -> Ativo | AA73: Moderado | AD73: 45678 | AE73: 49075100016461 | AH73: 1454771.9 | AI73: 1436046.7 | AJ73: 1407872.5 | AK73: 1403231.7 | AL73: 1467571.9 | AM73: 1511377.6 | AN73: 1534746.3 | AO73: 1567271.4 | AP73: 1601170.1 | AQ73: 1630864.5 | AR73: 1598426.4 | AS73: 1612558 | AT73: 1625341.4 | AU73: 1617138.8 | AV73: 1520366.6 | AW73: 1668684.1 | AX73: 1751245 | AY73: 1725478 | AZ73: {=XLOOKUP(C73,'PL TOTAL D0'!K:K,'PL TOTAL D0'!L:L,"")} -> 1737473.3
A74: XP | B74: Lidyane Marques De Paula Gomide | C74: 390262 | D74: Bluemetrix | E74: GO | F74: Felipe Rios | G74: =IFS($AZ$3:$AZ$993<=250000,"David",$AZ$3:$AZ$993<=800000,"Gabriel", $AZ$3:$AZ$993>800000,"Marcus") -> Gabriel | H74: Ativo | I74: ------ | J74: =IF(Q74=0,"Não","Sim") -> Não | K74: 45819 | M74: INC | N74: 0.012 | O74: ------ | P74: 0 | S74: PF | T74: 012.062.941-08 | U74: (63) - 32553271 | V74: lidyanegomide@hotmail.com | W74: 31261 | X74: GO | Y74: =IFS(H:H="Encerrado","Encerrado",COUNTBLANK(AF74:AN74)>0,"Ativo",SUM(AF74:AN74)=0,"Inativo",SUM(AF74:AN74)>0,"Ativo") -> Ativo | AA74: Moderado | AD74: 45819 | AE74: 49075100019010 | AM74: 324684.39 | AN74: 326373.62 | AO74: 329962.41 | AP74: 334252.35 | AQ74: 338305.85 | AR74: 340969.18 | AS74: 383228.74 | AT74: 386854.45 | AU74: 388883.47 | AV74: 330286.93 | AW74: 333648.85 | AX74: 337528.34 | AY74: 340934.24 | AZ74: {=XLOOKUP(C74,'PL TOTAL D0'!K:K,'PL TOTAL D0'!L:L,"")} -> 314115.8
A75: XP | B75: Lilia Rosa de Sousa | C75: 11371496 | D75: Expert | E75: GO | F75: Alcivana Marques | G75: =IFS($AZ$3:$AZ$993<=250000,"David",$AZ$3:$AZ$993<=800000,"Gabriel", $AZ$3:$AZ$993>800000,"Marcus") -> Gabriel | H75: Ativo | I75: ------ | J75: =IF(Q75=0,"Não","Sim") -> Não | K75: 45919 | M75: INC | N75: 0.012 | O75: ------ | P75: 0 | S75: PF | T75: 426.590.601-00 | U75: 62 99986-6039 | V75: liliarosavascon75@gmail.com | W75: 23956 | X75: GO | Y75: =IFS(H:H="Encerrado","Encerrado",COUNTBLANK(AF75:AN75)>0,"Ativo",SUM(AF75:AN75)=0,"Inativo",SUM(AF75:AN75)>0,"Ativo") -> Ativo | AA75: Moderado | AD75: 45919 | AE75: 49075100019444 | AN75: 576562.51 | AO75: 577850.35 | AP75: 575006.06 | AQ75: 579623.63 | AR75: 569302.06 | AS75: 574413.08 | AT75: 607725.08 | AU75: 554790.88 | AV75: 558313 | AW75: 535364.12 | AX75: 539645.27 | AY75: 543520.24 | AZ75: {=XLOOKUP(C75,'PL TOTAL D0'!K:K,'PL TOTAL D0'!L:L,"")} -> 548683.56
A76: XP | B76: Luana Bailão | C76: 5745802 | D76: Bluemetrix | E76: DF | F76: Thiago Canabrava | G76: =IFS($AZ$3:$AZ$993<=250000,"David",$AZ$3:$AZ$993<=800000,"Gabriel", $AZ$3:$AZ$993>800000,"Marcus") -> Marcus | H76: Ativo | I76: ------ | J76: =IF(Q76=0,"Não","Sim") -> Sim | K76: 45723 | M76: CON | N76: 0.012 | O76: CDI | P76: 0.1 | Q76: Manter ETF HashDex (10/03/2025) | S76: PF | T76: 796.850.991-20 | U76: (61) - 993686182 | V76: luanabailao@gmail.com | W76: 27619 | X76: DF | Y76: =IFS(H:H="Encerrado","Encerrado",COUNTBLANK(AF76:AN76)>0,"Ativo",SUM(AF76:AN76)=0,"Inativo",SUM(AF76:AN76)>0,"Ativo") -> Ativo | AA76: Moderado | AD76: 45723 | AE76: 49075100018480 | AJ76: 574530.77 | AK76: 649677.23 | AL76: 764691.73 | AM76: 807260.93 | AN76: 963567.93 | AO76: 970065.96 | AP76: 984349.55 | AQ76: 984130.19 | AR76: 946913.08 | AS76: 932180.72 | AT76: 899486.74 | AU76: 863702.69 | AV76: 871550.62 | AW76: 884713.14 | AX76: 874803.19 | AY76: 801863.11 | AZ76: {=XLOOKUP(C76,'PL TOTAL D0'!K:K,'PL TOTAL D0'!L:L,"")} -> 1031495
A77: XP | B77: Lucas Henrique Inácio Santos | C77: 17448472 | D77: Poupinvista | E77: DF | F77: Bruno Rodrigues | G77: =IFS($AZ$3:$AZ$993<=250000,"David",$AZ$3:$AZ$993<=800000,"Gabriel", $AZ$3:$AZ$993>800000,"Marcus") -> David | H77: Ativo | I77: ------ | J77: =IF(Q77=0,"Não","Sim") -> Não | K77: 45793 | M77: FUND | N77: 0 | O77: ------ | P77: 0 | S77: PF | T77: 011.123.731-95 | U77: (61) - 995596584 | V77: lucastempo@gmail.com | W77: 31546 | X77: DF | Y77: =IFS(H:H="Encerrado","Encerrado",COUNTBLANK(AF77:AN77)>0,"Ativo",SUM(AF77:AN77)=0,"Inativo",SUM(AF77:AN77)>0,"Ativo") -> Ativo | AA77: Moderado | AD77: 45800 | AE77: 49075100018936 | AL77: 300962.12 | AM77: 304602.81 | AN77: 612219.24 | AO77: 29.38 | AP77: 32.07 | AQ77: 32.07 | AR77: 32.07 | AS77: 32.07 | AT77: 32.07 | AU77: 32.07 | AV77: 32.07 | AW77: 0 | AX77: 32.07 | AY77: 32.07 | AZ77: {=XLOOKUP(C77,'PL TOTAL D0'!K:K,'PL TOTAL D0'!L:L,"")} -> 32.07
A78: XP | B78: Luciana Ariki Hiromoto | C78: 8759647 | D78: Miura | E78: SP | F78: Thais Helena | G78: =IFS($AZ$3:$AZ$993<=250000,"David",$AZ$3:$AZ$993<=800000,"Gabriel", $AZ$3:$AZ$993>800000,"Marcus") -> Marcus | H78: Inativo | I78: Distrato | J78: =IF(Q78=0,"Não","Sim") -> Não | K78: 45786 | M78: MONT | N78: 0.006 | O78: ------ | P78: 0 | S78: PF | T78: 286.809.168-70 | U78: (15) - 981502445 | V78: luciana.ariki@gmail.com | W78: 29281 | X78: SP | Y78: =IFS(H:H="Encerrado","Encerrado",COUNTBLANK(AF78:AN78)>0,"Ativo",SUM(AF78:AN78)=0,"Inativo",SUM(AF78:AN78)>0,"Ativo") -> Ativo | AA78: Moderado | AD78: 45786 | AE78: 49075100018944 | AL78: 1575212.7 | AM78: 1421475.1 | AN78: 1134531.2 | AO78: 1153509 | AP78: 1173299 | AQ78: 1196023.8 | AR78: 1217735.7 | AS78: 1212734.2 | AT78: 1231112.7 | AU78: 1222812 | AV78: 1182517.1 | AW78: 1247210.9 | AX78: 1277549.8 | AY78: 0 | AZ78: {=XLOOKUP(C78,'PL TOTAL D0'!K:K,'PL TOTAL D0'!L:L,"")}
A79: XP | B79: Luis Daniel Bonfim Fernandes | C79: 12630126 | D79: VcInvest | E79: GO | F79: Bruno Ribeiro | G79: =IFS($AZ$3:$AZ$993<=250000,"David",$AZ$3:$AZ$993<=800000,"Gabriel", $AZ$3:$AZ$993>800000,"Marcus") -> Marcus | H79: Encerrado | I79: ------ | J79: =IF(Q79=0,"Não","Sim") -> Sim | K79: 45622 | L79: 45958 | M79: INC | N79: 0.012 | O79: ------ | P79: 0 | Q79: Não movimentar carteira (27/11/2024) | S79: PF | T79: 031.861.946-60 | U79: (61) - 981291257 | V79: bonfimluis@yahoo.com.br | W79: 28361 | X79: DF | Y79: =IFS(H:H="Encerrado","Encerrado",COUNTBLANK(AF79:AN79)>0,"Ativo",SUM(AF79:AN79)=0,"Inativo",SUM(AF79:AN79)>0,"Ativo") -> Encerrado | AA79: Moderado | AD79: 45660 | AE79: 49075100016526 | AF79: 304650.08 | AG79: 293927.12 | AH79: 296223.86 | AI79: 286883.99 | AJ79: 149582.82 | AK79: 149996.2 | AL79: 84950.359 | AM79: 73047.89 | AN79: 73827.966 | AO79: 72912.648 | AP79: 50571.52 | AQ79: 0 | AR79: 0 | AS79: 0 | AT79: 0 | AU79: 13.47 | AV79: 0 | AW79: 0 | AX79: 0 | AY79: 0 | AZ79: {=XLOOKUP(C79,'PL TOTAL D0'!K:K,'PL TOTAL D0'!L:L,"")}
A80: XP | B80: Luisa Lemos Pimentel | C80: 9851852 | D80: Poupinvista | E80: DF | F80: Bruno Rodrigues | G80: =IFS($AZ$3:$AZ$993<=250000,"David",$AZ$3:$AZ$993<=800000,"Gabriel", $AZ$3:$AZ$993>800000,"Marcus") -> Marcus | H80: Ativo | I80: ------ | J80: =IF(Q80=0,"Não","Sim") -> Sim | K80: 45905 | M80: INC | N80: 0.012 | O80: ------ | P80: 0 | Q80: 100k D+0 e 100k aplic. de 6 meses (15/09/2025) | S80: PF | T80: 027.177.281-63 | U80: 61 98146-8178 | V80: lpimentel.luisa@gmail.com | W80: 32700 | X80: DF | Y80: =IFS(H:H="Encerrado","Encerrado",COUNTBLANK(AF80:AN80)>0,"Ativo",SUM(AF80:AN80)=0,"Inativo",SUM(AF80:AN80)>0,"Ativo") -> Ativo | AA80: Moderado | AD80: 45905 | AE80: 49075100019495 | AN80: 41776.51 | AO80: 41776.51 | AP80: 947785.01 | AQ80: 950177.44 | AR80: 957653.71 | AS80: 967428.14 | AT80: 976979.77 | AU80: 985845.05 | AV80: 998100.83 | AW80: 1009166.4 | AX80: 1015135.9 | AY80: 1018286.6 | AZ80: {=XLOOKUP(C80,'PL TOTAL D0'!K:K,'PL TOTAL D0'!L:L,"")} -> 1215973.5
A81: XP | B81: Luiza Amelia Marques Vinhal De Carvalho | C81: 3709188 | D81: MI Smart | E81: DF | F81: Mariana Rocha | G81: =IFS($AZ$3:$AZ$993<=250000,"David",$AZ$3:$AZ$993<=800000,"Gabriel", $AZ$3:$AZ$993>800000,"Marcus") -> Gabriel | H81: Ativo | I81: ------ | J81: =IF(Q81=0,"Não","Sim") -> Não | K81: 45744 | M81: INC CP | N81: 0.012 | O81: ------ | P81: 0 | S81: PF | T81: 055.981.101-21 | U81: (61) - 991979440 | V81: luizamvinhal@gmail.com | W81: 35263 | X81: DF | Y81: =IFS(H:H="Encerrado","Encerrado",COUNTBLANK(AF81:AN81)>0,"Ativo",SUM(AF81:AN81)=0,"Inativo",SUM(AF81:AN81)>0,"Ativo") -> Ativo | AA81: Conservador | AD81: 45744 | AE81: 49075100018464 | AJ81: 345947.89 | AK81: 349448.43 | AL81: 353180.14 | AM81: 340782.2 | AN81: 361973.76 | AO81: 366101.77 | AP81: 383916.19 | AQ81: 388309.97 | AR81: 378715.71 | AS81: 381654.14 | AT81: 342953.19 | AU81: 345848.93 | AV81: 346838.39 | AW81: 350297.86 | AX81: 350815.11 | AY81: 352946.33 | AZ81: {=XLOOKUP(C81,'PL TOTAL D0'!K:K,'PL TOTAL D0'!L:L,"")} -> 371516.36
A82: XP | B82: Luzinildes Maria Santana Ramos | C82: 18801240 | D82: Nexco | E82: DF | F82: Italo Teles | G82: =IFS($AZ$3:$AZ$993<=250000,"David",$AZ$3:$AZ$993<=800000,"Gabriel", $AZ$3:$AZ$993>800000,"Marcus") -> Gabriel | H82: Ativo | I82: ------ | J82: =IF(Q82=0,"Não","Sim") -> Não | K82: 45959 | M82: MULT PRIV | N82: 0.015 | O82: IPCA +7% | P82: 0.1 | S82: PF | T82: 295.919.021-15 | U82: 61 98433-1682 | V82: nildeslu@hotmail.com | W82: 23131 | X82: DF | Y82: =IFS(H:H="Encerrado","Encerrado",COUNTBLANK(AF82:AN82)>0,"Ativo",SUM(AF82:AN82)=0,"Inativo",SUM(AF82:AN82)>0,"Ativo") -> Ativo | AA82: Moderado | AQ82: 0 | AR82: 0 | AS82: 441040.08 | AT82: 448979.98 | AU82: 316121.02 | AV82: 310818.88 | AW82: 311311.92 | AX82: 310933.11 | AY82: 309317.79 | AZ82: {=XLOOKUP(C82,'PL TOTAL D0'!K:K,'PL TOTAL D0'!L:L,"")} -> 373840.87
A83: XP | B83: Marcelo Moreira da Silva | C83: 18795350 | D83: Poupinvista | E83: DF | F83: Bruno Rodrigues | G83: =IFS($AZ$3:$AZ$993<=250000,"David",$AZ$3:$AZ$993<=800000,"Gabriel", $AZ$3:$AZ$993>800000,"Marcus") -> Marcus | H83: Ativo | I83: Sem Saldo | J83: =IF(Q83=0,"Não","Sim") -> Não | K83: 45958 | M83: CON | N83: 0.012 | O83: CDI | P83: 0.1 | S83: PF | T83: 013.491.756-17 | U83: 61 98333-6162 | V83: marceloms_med@yahoo.com.br | W83: 29843 | X83: DF | Y83: Ativo | AA83: Moderado | AQ83: 0 | AR83: 0 | AS83: 0 | AT83: 0 | AU83: 0 | AV83: 0 | AW83: 0 | AX83: 0 | AY83: 0 | AZ83: {=XLOOKUP(C83,'PL TOTAL D0'!K:K,'PL TOTAL D0'!L:L,"")}
A84: XP | B84: Maria Alba Sá | C84: 17159452 | D84: Poupinvista | E84: DF | F84: Bruno Rodrigues | G84: =IFS($AZ$3:$AZ$993<=250000,"David",$AZ$3:$AZ$993<=800000,"Gabriel", $AZ$3:$AZ$993>800000,"Marcus") -> Gabriel | H84: Ativo | I84: ------ | J84: =IF(Q84=0,"Não","Sim") -> Sim | K84: 45756 | M84: FUND | N84: 0 | O84: ------ | P84: 0 | Q84: Manter 51k Fundo Riza Lotus (15/09/2025) | S84: PF | T84: 224.618.849-00 | U84: (48) - 999826712 | V84: maria.alba.sa12@gmail.com | W84: 19522 | X84: SC | Y84: =IFS(H:H="Encerrado","Encerrado",COUNTBLANK(AF84:AN84)>0,"Ativo",SUM(AF84:AN84)=0,"Inativo",SUM(AF84:AN84)>0,"Ativo") -> Ativo | AA84: Conservador | AD84: 45758 | AE84: 49075100018715 | AK84: 221244.85 | AL84: 223262.38 | AM84: 225811.89 | AN84: 228755.99 | AO84: 231454.74 | AP84: 285476.89 | AQ84: 289026.38 | AR84: 289450.97 | AS84: 292985.09 | AT84: 296475.42 | AU84: 299282.96 | AV84: 302863.57 | AW84: 306062.83 | AX84: 306494.04 | AY84: 289816.59 | AZ84: {=XLOOKUP(C84,'PL TOTAL D0'!K:K,'PL TOTAL D0'!L:L,"")} -> 293255.15
A85: XP | B85: Maria de Fatima Rabelo Jacomo | C85: 2679780 | D85: VcInvest | E85: GO | F85: Bruno Ribeiro | G85: =IFS($AZ$3:$AZ$993<=250000,"David",$AZ$3:$AZ$993<=800000,"Gabriel", $AZ$3:$AZ$993>800000,"Marcus") -> Marcus | H85: Ativo | I85: ------ | J85: =IF(Q85=0,"Não","Sim") -> Sim | K85: 45645 | M85: INC | N85: 0.01 | O85: ------ | P85: 0 | Q85: Próximos vencimentos D+0 (04/06/2025) | S85: PF | T85: 166.328.851-87 | U85: (62) - 982218585 | V85: jacomo@jacomo.com.br | W85: 20576 | X85: GO | Y85: =IFS(H:H="Encerrado","Encerrado",COUNTBLANK(AF85:AN85)>0,"Ativo",SUM(AF85:AN85)=0,"Inativo",SUM(AF85:AN85)>0,"Ativo") -> Ativo | AA85: Moderado | AD85: 45663 | AE85: 49075100016550 | AG85: 2098555.9 | AH85: 2113065.6 | AI85: 2115494.7 | AJ85: 2098233.7 | AK85: 2077249.6 | AL85: 2094850 | AM85: 1810900.7 | AN85: 1510371.9 | AO85: 1525159.1 | AP85: 1540763.3 | AQ85: 1559999.2 | AR85: 1382722 | AS85: 973240.42 | AT85: 982820.65 | AU85: 987929.88 | AV85: 1000755.5 | AW85: 1013055.4 | AX85: 1018235.7 | AY85: 1020641.6 | AZ85: {=XLOOKUP(C85,'PL TOTAL D0'!K:K,'PL TOTAL D0'!L:L,"")} -> 1023555.2
A86: XP | B86: Maria Do Carmo Pereira De Souza | C86: 15733167 | D86: Expert | E86: GO | F86: Paula Bonfim | G86: =IFS($AZ$3:$AZ$993<=250000,"David",$AZ$3:$AZ$993<=800000,"Gabriel", $AZ$3:$AZ$993>800000,"Marcus") -> Marcus | H86: Ativo | I86: ------ | J86: =IF(Q86=0,"Não","Sim") -> Não | K86: 45861 | M86: INC | N86: 0.012 | O86: ------ | P86: 0 | S86: PF | T86: 375.329.521-34 | U86: (0) - 0 | V86: mariadcarmo63@hotmail.com | W86: 23081 | X86: GO | Y86: =IFS(H:H="Encerrado","Encerrado",COUNTBLANK(AF86:AN86)>0,"Ativo",SUM(AF86:AN86)=0,"Inativo",SUM(AF86:AN86)>0,"Ativo") -> Ativo | AA86: Conservador | AD86: 45861 | AE86: 49075100019061 | AN86: 1123067.3 | AO86: 1134683.4 | AP86: 1146262.4 | AQ86: 1158822.4 | AR86: 1168488.9 | AS86: 1180839.4 | AT86: 1192280.9 | AU86: 1202349.2 | AV86: 1216264 | AW86: 1228933.7 | AX86: 1240096.9 | AY86: 1252478.6 | AZ86: {=XLOOKUP(C86,'PL TOTAL D0'!K:K,'PL TOTAL D0'!L:L,"")} -> 1266947.1
A87: XP | B87: Mariana Lima de Oliveira | C87: 2872613 | D87: Expert | E87: GO | F87: Alcivana Marques | G87: =IFS($AZ$3:$AZ$993<=250000,"David",$AZ$3:$AZ$993<=800000,"Gabriel", $AZ$3:$AZ$993>800000,"Marcus") -> Marcus | H87: Ativo | I87: ------ | J87: =IF(Q87=0,"Não","Sim") -> Sim | K87: 45805 | M87: INC | N87: 0.012 | O87: ------ | P87: 0 | Q87: R$ 1.000.000,00 D+0 para envio para o exterior (05/01/2025) | S87: PF | T87: 958.285.161-91 | U87: (62) - 992234225 | V87: mariana@energoato.com.br | W87: 30662 | X87: GO | Y87: =IFS(H:H="Encerrado","Encerrado",COUNTBLANK(AF87:AN87)>0,"Ativo",SUM(AF87:AN87)=0,"Inativo",SUM(AF87:AN87)>0,"Ativo") -> Ativo | AA87: Moderado | AD87: 45805 | AE87: 49075100018871 | AL87: 4527319.8 | AM87: 4432164.1 | AN87: 4521045.4 | AO87: 4462177 | AP87: 4506390.9 | AQ87: 4554137.4 | AR87: 4482883.1 | AS87: 4826386.6 | AT87: 6891090.4 | AU87: 6772090.1 | AV87: 6490272.1 | AW87: 6160752.9 | AX87: 6204358.6 | AY87: 6207642.3 | AZ87: {=XLOOKUP(C87,'PL TOTAL D0'!K:K,'PL TOTAL D0'!L:L,"")} -> 6117365.4
A88: XP | B88: Mariana Lima de Oliveira | C88: 17319807 | D88: Expert | E88: GO | F88: Alcivana Marques | G88: =IFS($AZ$3:$AZ$993<=250000,"David",$AZ$3:$AZ$993<=800000,"Gabriel", $AZ$3:$AZ$993>800000,"Marcus") -> Gabriel | H88: Ativo | I88: ------ | J88: =IF(Q88=0,"Não","Sim") -> Não | K88: 45826 | M88: EQT | N88: 0.025 | O88: IBOVESPA | P88: 0.2 | S88: PF | T88: 958.285.161-91 | U88: (62) - 992234225 | V88: mariana@energoato.com.br | W88: 30662 | X88: GO | Y88: =IFS(H:H="Encerrado","Encerrado",COUNTBLANK(AF88:AN88)>0,"Ativo",SUM(AF88:AN88)=0,"Inativo",SUM(AF88:AN88)>0,"Ativo") -> Ativo | AA88: Moderado | AD88: 45826 | AE88: 49075100019274 | AM88: 112559.35 | AN88: 107238.18 | AO88: 111039.37 | AP88: 110115.37 | AQ88: 113843.3 | AR88: 119173.47 | AS88: 124618 | AT88: 301870.65 | AU88: 310299.13 | AV88: 308448.37 | AW88: 309756.49 | AX88: 291861.01 | AY88: 295750.13 | AZ88: {=XLOOKUP(C88,'PL TOTAL D0'!K:K,'PL TOTAL D0'!L:L,"")} -> 296964.86
A89: XP | B89: Marlene Bonfim Pereira | C89: 16286158 | D89: Expert | E89: GO | F89: Paula Bonfim | G89: =IFS($AZ$3:$AZ$993<=250000,"David",$AZ$3:$AZ$993<=800000,"Gabriel", $AZ$3:$AZ$993>800000,"Marcus") -> Marcus | H89: Ativo | I89: ------ | J89: =IF(Q89=0,"Não","Sim") -> Não | K89: 45817 | M89: INC | N89: 0.012 | O89: ------ | P89: 0 | S89: PF | T89: 526.577.601-04 | U89: (62) - 984210238 | V89: marlene-pitanga@uol.com.br | W89: 25808 | X89: GO | Y89: =IFS(H:H="Encerrado","Encerrado",COUNTBLANK(AF89:AN89)>0,"Ativo",SUM(AF89:AN89)=0,"Inativo",SUM(AF89:AN89)>0,"Ativo") -> Ativo | AA89: Conservador | AD89: 45817 | AE89: 49075100019002 | AM89: 844539.65 | AN89: 854340.48 | AO89: 863237.9 | AP89: 872878.34 | AQ89: 882761.24 | AR89: 890425.41 | AS89: 900050.54 | AT89: 909636.29 | AU89: 917232.53 | AV89: 926986.29 | AW89: 936520.25 | AX89: 945420.04 | AY89: 955416.35 | AZ89: {=XLOOKUP(C89,'PL TOTAL D0'!K:K,'PL TOTAL D0'!L:L,"")} -> 964412.82
A90: XP | B90: Mateus Fernandes Carvalho | C90: 2037686 | D90: Bluemetrix | E90: GO | F90: Felipe Rios | G90: =IFS($AZ$3:$AZ$993<=250000,"David",$AZ$3:$AZ$993<=800000,"Gabriel", $AZ$3:$AZ$993>800000,"Marcus") -> Gabriel | H90: Ativo | I90: ------ | J90: =IF(Q90=0,"Não","Sim") -> Não | K90: 45685 | M90: CON | N90: 0.01 | O90: CDI | P90: 0.1 | S90: PF | T90: 004.242.451-83 | U90: (62) - 999184089 | V90: mateusfernandescarvalho@gmail.com | W90: 33816 | X90: GO | Y90: =IFS(H:H="Encerrado","Encerrado",COUNTBLANK(AF90:AN90)>0,"Ativo",SUM(AF90:AN90)=0,"Inativo",SUM(AF90:AN90)>0,"Ativo") -> Ativo | AA90: Moderado | AD90: 45685 | AE90: 49075100016501 | AH90: 302505.16 | AI90: 301019.82 | AJ90: 306520.54 | AK90: 299252.19 | AL90: 305733.04 | AM90: 310434.28 | AN90: 310759.23 | AO90: 316258.5 | AP90: 319832.53 | AQ90: 323881.93 | AR90: 326177.36 | AS90: 328035.97 | AT90: 331917.97 | AU90: 334160.89 | AV90: 335519.53 | AW90: 337445.64 | AX90: 337364.37 | AY90: 339124.95 | AZ90: {=XLOOKUP(C90,'PL TOTAL D0'!K:K,'PL TOTAL D0'!L:L,"")} -> 341520.86
A91: XP | B91: Mauricio Tutida Iryoda | C91: 2146957 | D91: MI Smart | E91: DF | F91: Mariana Rocha | G91: =IFS($AZ$3:$AZ$993<=250000,"David",$AZ$3:$AZ$993<=800000,"Gabriel", $AZ$3:$AZ$993>800000,"Marcus") -> Gabriel | H91: Inativo | I91: Monitoramento | J91: =IF(Q91=0,"Não","Sim") -> Não | K91: 45722 | M91: MONT | N91: 0 | O91: ------ | P91: 0 | R91: Alteração de carteira finalizada (24/03/2025) | S91: PF | T91: 717.045.311-87 | U91: (61) - 981737773 | V91: mauricio.tutida@gmail.com | W91: 01/07/1981 | X91: DF | Y91: =IFS(H:H="Encerrado","Encerrado",COUNTBLANK(AF91:AN91)>0,"Ativo",SUM(AF91:AN91)=0,"Inativo",SUM(AF91:AN91)>0,"Ativo") -> Ativo | AA91: Conservador | AD91: 45722 | AE91: 49075100018431 | AJ91: 1247472.8 | AK91: 1046161.8 | AL91: 1056032 | AM91: 1067974.4 | AN91: 349620 | AO91: 353029.28 | AP91: 348443.09 | AQ91: 352560.81 | AR91: 355063.49 | AS91: 357112.64 | AT91: 241524.97 | AU91: 243363.14 | AV91: 244609.31 | AW91: 246613.32 | AX91: 248573.65 | AY91: 250673.35 | AZ91: {=XLOOKUP(C91,'PL TOTAL D0'!K:K,'PL TOTAL D0'!L:L,"")} -> 253112
A92: XP | B92: Milene Lacerda Macedo Falcao Hora | C92: 4334650 | D92: MI Smart | E92: DF | F92: Mariana Rocha | G92: =IFS($AZ$3:$AZ$993<=250000,"David",$AZ$3:$AZ$993<=800000,"Gabriel", $AZ$3:$AZ$993>800000,"Marcus") -> David | H92: Ativo | I92: ------ | J92: =IF(Q92=0,"Não","Sim") -> Não | K92: 45709 | M92: INC | N92: 0.012 | O92: ------ | P92: 0 | S92: PF | T92: 026.246.774-70 | U92: (61) - 985766996 | V92: milenemacedoneuro@gmail.com | W92: 28306 | X92: DF | Y92: =IFS(H:H="Encerrado","Encerrado",COUNTBLANK(AF92:AN92)>0,"Ativo",SUM(AF92:AN92)=0,"Inativo",SUM(AF92:AN92)>0,"Ativo") -> Ativo | AA92: Conservador | AD92: 45709 | AE92: 49075100018081 | AI92: 469243.26 | AJ92: 302661.95 | AK92: 811912.05 | AL92: 820070.72 | AM92: 742683.46 | AN92: 113295.32 | AO92: 93593.428 | AP92: 97392.737 | AQ92: 98623.765 | AR92: 99327.985 | AS92: 97727.335 | AT92: 87758.281 | AU92: 46089.861 | AV92: 46542.11 | AW92: 44516.15 | AX92: 44850.08 | AY92: 45389.3 | AZ92: {=XLOOKUP(C92,'PL TOTAL D0'!K:K,'PL TOTAL D0'!L:L,"")} -> 33614.276
A93: XP | B93: Milla Cerdeira Bernat | C93: 9071920 | D93: MI Smart | E93: DF | F93: Mariana Rocha | G93: =IFS($AZ$3:$AZ$993<=250000,"David",$AZ$3:$AZ$993<=800000,"Gabriel", $AZ$3:$AZ$993>800000,"Marcus") -> David | H93: Ativo | I93: ------ | J93: =IF(Q93=0,"Não","Sim") -> Não | K93: 45716 | M93: INC | N93: 0.012 | O93: ------ | P93: 0 | S93: PF | T93: 006.462.091-32 | U93: (61) - 996587422 | V93: millabernat@yahoo.com.br | W93: 30747 | X93: DF | Y93: =IFS(H:H="Encerrado","Encerrado",COUNTBLANK(AF93:AN93)>0,"Ativo",SUM(AF93:AN93)=0,"Inativo",SUM(AF93:AN93)>0,"Ativo") -> Ativo | AA93: Conservador | AD93: 45716 | AE93: 49075100018073 | AI93: 113362.83 | AJ93: 19104.42 | AK93: 19165.87 | AL93: 19914.479 | AM93: 20425.965 | AN93: 20802.968 | AO93: 21260.773 | AP93: 21653.55 | AQ93: 22107.38 | AR93: 22063.33 | AS93: 22296.13 | AT93: 22530.94 | AU93: 22545.02 | AV93: 21654.95 | AW93: 17935.09 | AX93: 18607.9 | AY93: 18607.54 | AZ93: {=XLOOKUP(C93,'PL TOTAL D0'!K:K,'PL TOTAL D0'!L:L,"")} -> 18765.516
